Workbook

Sheet Executive Summary
A1: TUPENSACI | Business Plan 360° v3.0
A2: Base case | €9 / €89 / €69 | 7-day guided trial | Acceleration only after observed gates
A4: THREE-YEAR ECONOMIC VIEW | F4: ROUND & DEPLOYMENT
A5: Metric | B5: Year 1 | C5: Year 2 | D5: Year 3 | F5: Metric | G5: v3.0 plan
A6: Physical + extensions revenue | B6: =SUM('P&L 36 Months'!B10:M10) -> 364117.84 | C6: =SUM('P&L 36 Months'!N10:Y10) -> 556333.28 | D6: =SUM('P&L 36 Months'!Z10:AK10) -> 629195.72 | F6: Round committed | G6: =Assumptions!$C$47 -> 300000
A7: AI revenue | B7: =SUM('P&L 36 Months'!B11:M11) -> 121142.09 | C7: =SUM('P&L 36 Months'!N11:Y11) -> 337997.88 | D7: =SUM('P&L 36 Months'!Z11:AK11) -> 482450.09 | F7: Start tranche — M1 | G7: ='Capital Gates'!$C$5 -> 90000
A8: Total revenue | B8: =SUM('P&L 36 Months'!B12:M12) -> 485259.93 | C8: =SUM('P&L 36 Months'!N12:Y12) -> 894331.16 | D8: =SUM('P&L 36 Months'!Z12:AK12) -> 1111645.8 | F8: Post-M3 tranche | G8: ='Capital Gates'!$C$6 -> 80000
A9: Gross profit | B9: =SUM('P&L 36 Months'!B16:M16) -> 288357.95 | C9: =SUM('P&L 36 Months'!N16:Y16) -> 523224.57 | D9: =SUM('P&L 36 Months'!Z16:AK16) -> 644467.49 | F9: Post-M6 tranche | G9: ='Capital Gates'!$C$7 -> 115000
A10: Operating EBITDA before one-time build | B10: =SUM('P&L 36 Months'!B23:M23) -> 9357.9495 | C10: =SUM('P&L 36 Months'!N23:Y23) -> 163224.57 | D10: =SUM('P&L 36 Months'!Z23:AK23) -> 272467.49 | F10: Ring-fenced reserve | G10: =Assumptions!$C$48 -> 15000
A11: Cash operating result | B11: =SUM('P&L 36 Months'!B27:M27) -> -90642.051 | C11: =SUM('P&L 36 Months'!N27:Y27) -> 148224.57 | D11: =SUM('P&L 36 Months'!Z27:AK27) -> 257467.49 | F11: M12 decision | G11: Scale / correct / stop
F12: Verdict | G12: ='Cash & Funding'!B27 -> Base is funded with headroom; Accelerated deployment remains conditional on gates
A14: OPERATING KPIs & PROOF PLAN
A15: KPI | B15: Year 1 | C15: Year 2 | D15: Year 3 | F15: 1. Relaunch Diario, Crea and L’Arte with one accountable growth owner and specialist agency.
A16: Physical orders | B16: =SUM('Physical Business'!B14:M14) -> 10666.182 | C16: =SUM('Physical Business'!N14:Y14) -> 15160.414 | D16: =SUM('Physical Business'!Z14:AK14) -> 15924.866 | F16: 2. Keep the integrated Base prudent: ≈2,000 active AI users at M12 and ≈4,000 at M24.
A17: New physical buyers | B17: =SUM('Physical Business'!B15:M15) -> 10666.182 | C17: =SUM('Physical Business'!N15:Y15) -> 14093.796 | D17: =SUM('Physical Business'!Z15:AK15) -> 14515.487 | F17: 3. Launch at €9/month, €89/year and €69 founding for the first year; founding renews at €89.
A18: AI users acquired | B18: =SUM('AI Cohorts'!B15:M15) -> 2521.2241 | C18: =SUM('AI Cohorts'!N15:Y15) -> 4087.951 | D18: =SUM('AI Cohorts'!Z15:AK15) -> 4665.8344 | F18: 4. Use a guided 7-day no-card trial; no permanent free tier.
A19: AI active users at year end | B19: ='AI Cohorts'!M26 -> 2079.2872 | C19: ='AI Cohorts'!Y26 -> 3999.939 | D19: ='AI Cohorts'!AK26 -> 5152.4809 | F19: 5. Accelerate only after observed CAC ≤€20, churn ≤6%, acceptable safety and real return usage.
A20: AI ARR at year end | B20: ='AI Cohorts'!M42 -> 210192.04 | C20: ='AI Cohorts'!Y42 -> 402225.15 | D20: ='AI Cohorts'!AK42 -> 516476.97 | F20: 6. In the gated case, target ≈3,200 active users at M12 and ≈4,700–5,000 at M24.
A21: Physical → AI attach | B21: =Assumptions!$F$10 -> 0.1 | C21: =Assumptions!$F$10 -> 0.1 | D21: =Assumptions!$F$10 -> 0.1 | F21: 7. Collect the €300k round in full; authorize €90k / €80k / €115k and hold €15k in reserve.
A22: Effective monthly churn | B22: =Assumptions!$C$69 -> 0.08 | C22: =Assumptions!$C$69 -> 0.08 | D22: =Assumptions!$C$69 -> 0.08 | F22: 8. Keep one new workbook per year and early B2B pilots inside the ecosystem thesis.
A26: Year | B26: Physical | C26: AI | D26: EBITDA | F26: Year | G26: Ending cash
A27: Y1 | B27: =B6 -> 364117.84 | C27: =B7 -> 121142.09 | D27: =B10 -> 9357.9495 | F27: Y1 | G27: ='Cash & Funding'!M12 -> 209357.95
A28: Y2 | B28: =C6 -> 556333.28 | C28: =C7 -> 337997.88 | D28: =C10 -> 163224.57 | F28: Y2 | G28: ='Cash & Funding'!Y12 -> 357582.52
A29: Y3 | B29: =D6 -> 629195.72 | C29: =D7 -> 482450.09 | D29: =D10 -> 272467.49 | F29: Y3 | G29: ='Cash & Funding'!AK12 -> 615050.01

Sheet Assumptions
A1: TUPENSACI | Assumptions v3.0
A2: Base prudente con pricing €9/€89, offerta founding €69 e prova guidata di 7 giorni. Lo scenario Accelerato è separato e si attiva soltanto dopo evidenza su CAC, retention e qualità del prodotto.
A4: MODEL CONTROL | D4: BRANCH CONTROLS
A5: Scenario selected | B5: Base | D5: AI paid branch | E5: Test
D6: Growth extensions | E6: On
A7: SCENARIO DRIVERS
A8: Driver | B8: Unit | C8: Downside | D8: Base | E8: Upside | F8: Selected | G8: Rationale / source | H8: Status
A9: Historical customer → AI conversion | B9: % | C9: 0.01 | D9: 0.02 | E9: 0.04 | F9: =IF($B$5="Downside",C9,IF($B$5="Upside",E9,D9)) -> 0.02 | G9: Conservative reactivation of ~21k historical contacts | H9: Model assumption
A10: New physical buyer → AI attach | B10: % | C10: 0.07 | D10: 0.1 | E10: 0.15 | F10: =IF($B$5="Downside",C10,IF($B$5="Upside",E10,D10)) -> 0.1 | G10: Confirmed base hypothesis: AI supports the purchased workbook | H10: Confirmed base
A11: Annual payment share | B11: % | C11: 0.25 | D11: 0.3 | E11: 0.35 | F11: =IF($B$5="Downside",C11,IF($B$5="Upside",E11,D11)) -> 0.3 | G11: Confirmed mix: 30% annual / 70% monthly | H11: Confirmed base
A12: Monthly AI churn | B12: % | C12: 0.1 | D12: 0.08 | E12: 0.05 | F12: =IF($B$5="Downside",C12,IF($B$5="Upside",E12,D12)) -> 0.08 | G12: Base from reconciled AI model; 5% is target | H12: Confirmed base
A13: Annual AI renewal rate | B13: % | C13: 0.3 | D13: 0.45 | E13: 0.55 | F13: =IF($B$5="Downside",C13,IF($B$5="Upside",E13,D13)) -> 0.45 | G13: Separate assumption for annual cohorts after 12 months | H13: To validate
A14: Physical repeat / cross-sell after 12m | B14: % | C14: 0.0893 | D14: 0.1 | E14: 0.15 | F14: =IF($B$5="Downside",C14,IF($B$5="Upside",E14,D14)) -> 0.1 | G14: Historical repeat rate since 2023: 8.93%; base rounded to 10% | H14: Confirmed base
A15: Physical paid CAC per order | B15: € | C15: 16 | D15: 11.5 | E15: 9.7 | F15: =IF($B$5="Downside",C15,IF($B$5="Upside",E15,D15)) -> 11.5 | G15: Base target near 2023 ADV/order (€9.67), with execution buffer | H15: Core recovery gate
A16: Direct AI blended CAC — Test | B16: € | C16: 30 | D16: 22.4 | E16: 15 | F16: =IF($B$5="Downside",C16,IF($B$5="Upside",E16,D16)) -> 22.4 | G16: 80% paid at €28 in base ⇒ blended CAC €22.40 | H16: Working target
A17: Organic physical orders in M1 | B17: orders | C17: 80 | D17: 100 | E17: 120 | F17: =IF($B$5="Downside",C17,IF($B$5="Upside",E17,D17)) -> 100 | G17: Owned demand before paid relaunch | H17: To validate
A18: Monthly physical growth before scale | B18: % | C18: 0 | D18: 0.01 | E18: 0.02 | F18: =IF($B$5="Downside",C18,IF($B$5="Upside",E18,D18)) -> 0.01 | G18: M1–M6, before commercial proof | H18: To validate
A19: Monthly physical growth after scale | B19: % | C19: 0.01 | D19: 0.02 | E19: 0.03 | F19: =IF($B$5="Downside",C19,IF($B$5="Upside",E19,D19)) -> 0.02 | G19: M7 onward, only after recovery gate | H19: To validate
A20: Beta direct AI users / month | B20: users | C20: 30 | D20: 50 | E20: 80 | F20: =IF($B$5="Downside",C20,IF($B$5="Upside",E20,D20)) -> 50 | G20: Owned beta users from launch month through M6 | H20: To validate
... A25: Physical media budget M7–M12 | B25: €/month | C25: 8000 | D25: 11000 | E25: 13000 | F25: =IF($B$5="Downside",C25,IF($B$5="Upside",E25,D25)) -> 11000 | G25: Calibrated to recover approximately the 2023 order volume in Year 1 | H25: To validate
A27: PRICING, UNIT ECONOMICS & OPERATING INPUTS
A28: Input | B28: Unit | C28: Value | D28: Formula / source | H28: Status
A29: AI monthly price | B29: €/month | C29: 9 | D29: Management confirmed — August 2026 | H29: Confirmed
A30: AI annual standard price | B30: €/year | C30: 89 | D30: Management confirmed — renewals at standard price | H30: Confirmed
A31: AI annual founding / community price — first year | B31: €/year | C31: 69 | D31: Launch offer for community, historical and workbook-linked users; renews at €89 | H31: Confirmed
A32: VAT | B32: % | C32: 0.22 | D32: Italian consumer pricing assumption | H32: To validate
A33: Payment/platform fees | B33: % revenue net of VAT | C33: 0.15 | D33: Reconciled AI economic model | H33: To validate
A34: API cost per active user | B34: €/month | C34: 0.95 | D34: Reconciled AI economic model | H34: Confirmed model
A35: Cloud cost per active user | B35: €/month | C35: 0.3 | D35: Reconciled AI economic model | H35: Confirmed model
A36: Annual refund reserve | B36: % gross annual price | C36: 0.03 | D36: Reconciled AI economic model | H36: Confirmed model
A37: Monthly AI contribution per active user — €9 | B37: €/month | C37: =C29/(1+C32)*(1-C33)-C34-C35 -> 5.0204918 | D37: Net of VAT, fees, API and cloud | H37: Calculated
A38: Annual AI contribution — €89 | B38: €/sale | C38: =C30/(1+C32)*(1-C33-C36)-12*(C34+C35) -> 44.819672 | D38: Net of VAT, fees/refunds and 12m API/cloud | H38: Calculated
A39: Annual AI contribution — €69 founding | B39: €/sale | C39: =C31/(1+C32)*(1-C33-C36)-12*(C34+C35) -> 31.377049 | D39: Net of VAT, fees/refunds and 12m API/cloud | H39: Calculated
A40: Physical net revenue per order | B40: €/order | C40: 32 | D40: Planning value agreed; retail prices are €32.90 Diario and €34.90 Crea/L'Arte | H40: Confirmed planning value
A41: Print + shipping/stock per order | B41: €/order | C41: 12 | D41: €5 print + ~€7 shipping/stock | H41: Confirmed
A42: Historical customer database | B42: people | C42: 21000 | D42: Management estimate | H42: Confirmed
A43: Historical Diary purchasers | B43: people | C43: 18000 | D43: Management estimate | H43: Confirmed
A44: Physical copies sold historically — all channels | B44: copies | C44: 40000 | D44: Management estimate including ecommerce, Amazon, retail and corporate channels | H44: Confirmed
A45: Legacy physical fixed costs | B45: €/year | C45: 15000 | D45: Excludes founder compensation | H45: Confirmed
A46: Founder compensation | B46: €/year | C46: 0 | D46: Editable; default requested = zero | H46: Confirmed default
A47: Round under evaluation | B47: € | C47: 300000 | D47: Current investor pitch | H47: Confirmed
A48: Contingency reserve | B48: € | C48: 15000 | D48: Ring-fenced reserve inside the €300k round | H48: Confirmed model
A49: Beta starts | B49: month | C49: 4 | D49: Closed beta opens as soon as the core loop is functional | H49: Confirmed model
A50: Decision gate | B50: month | C50: 6 | D50: Commercial + beta capital release gate | H50: Confirmed model
A51: Paid scale starts | B51: month | C51: 7 | D51: Direct paid AI tests start only after M6 gate | H51: Confirmed model
... A67: Scale-gate monthly churn | B67: % | C67: 0.06 | D67: Required observed monthly churn before broad scale | H67: Gate target
A68: Effective direct AI CAC | B68: € | C68: =IF($E$5="Scale",$C$66,$F$16) -> 22.4 | D68: Test uses selected scenario; Scale uses gate target | H68: Calculated
A69: Effective monthly AI churn | B69: % | C69: =IF($E$5="Scale",$C$67,$F$12) -> 0.08 | D69: Test uses selected scenario; Scale uses gate target | H69: Calculated
A70: Current branch LTV / CAC | B70: x | C70: =($C$37/$C$69)/$C$68 -> 2.8016137 | D70: Monthly contribution / churn / effective CAC | H70: Calculated
A71: New workbook #1 launch month | B71: month | C71: 9 | D71: Q4 Year 1 | H71: To validate
A72: New workbook #2 launch month | B72: month | C72: 21 | D72: Q4 Year 2 | H72: To validate
A73: New workbook #3 launch month | B73: month | C73: 33 | D73: Q4 Year 3 | H73: To validate
A74: Launch investment per new workbook | B74: € | C74: 15000 | D74: Editorial, design, pre-production and launch assets | H74: To validate
A75: Build duration per new workbook | B75: months | C75: 6 | D75: Investment spread across the six months before launch | H75: To validate
A76: Organic orders per active new workbook / month | B76: orders | C76: 100 | D76: Planning hypothesis; no incremental paid media | H76: To validate
A77: B2B pilot start | B77: month | C77: 9 | D77: First corporate pilots before Year 2 | H77: To validate
A78: B2B monthly revenue — Y1 | B78: €/month | C78: 2500 | D78: Four pilot months = €10k | H78: To validate
A79: B2B monthly revenue — Y2 | B79: €/month | C79: 1666.67 | D79: Annual planning value ≈ €20k | H79: To validate
A80: B2B monthly revenue — Y3 | B80: €/month | C80: 2500 | D80: Annual planning value = €30k | H80: To validate
A81: B2B gross margin | B81: % | C81: 0.4 | D81: Includes customization, facilitation and delivery costs | H81: To validate
A82: Physical media budget M13–M36 | B82: €/month | C82: 9000 | D82: 12000 | E82: 15000 | F82: =IF($B$5="Downside",C82,IF($B$5="Upside",E82,D82)) -> 12000 | G82: Maintained only if M12 KPI gate is achieved | H82: Scale assumption
A83: Historical customers — all channels | B83: people | C83: 28000 | D83: Management estimate including corporate and retail buyers | H83: Confirmed KPI
A84: Guided free trial | B84: days | C84: 7 | D84: No card required; no permanent free tier | H84: Confirmed launch choice
A85: Accelerated warm media M7–M12 | B85: € total | C85: 25000 | D85: Community and customer retargeting | H85: Scale envelope
A86: Accelerated broad media M7–M12 | B86: € total | C86: 17000 | D86: Initial broad test; conservative CAC | H86: Scale envelope
A87: Accelerated broad media M13–M18 | B87: € total | C87: 28000 | D87: Released only after M12 evidence | H87: Scale envelope
A88: Accelerated broad media M19–M36 | B88: €/month | C88: 5000 | D88: Reinvested contribution and/or follow-on capital | H88: Conditional scale
A89: Warm/community paid CAC | B89: € | C89: 15 | D89: Expected advantage from the existing relationship | H89: To validate
A90: Broad CAC — launch | B90: € | C90: 28 | D90: Cautious initial broad assumption | H90: To validate
A91: Broad CAC — scale | B91: € | C91: 20 | D91: Gate target after creative and funnel learning | H91: Gate target
A92: Warm trial-to-paid conversion | B92: % | C92: 0.35 | D92: Operational funnel assumption; CAC remains measured per paid user | H92: To validate
A93: Broad trial-to-paid conversion | B93: % | C93: 0.25 | D93: Operational funnel assumption; CAC remains measured per paid user | H93: To validate
A94: Inactive account data retention | B94: days | C94: 30 | D94: Only with the user consent and documented deletion rules | H94: Product rule

Sheet Historical Actuals
A1: TUPENSACI | Historical Actuals
A2: Normalized from ANALISI ORDINI TP — sheet ‘Incassato e speso giornaliero’. 2026 is YTD through 17 June.
A4: ACTUAL PERFORMANCE
A5: Period | B5: Revenue | C5: ADV | D5: Print + fulfillment | E5: Fixed costs | F5: Operating result | G5: Fulfilled units | H5: MER | I5: ADV / unit | J5: Note
A6: 2023 | B6: 284492.32 | C6: 103161.38 | D6: 128076 | E6: 15000 | F6: =B6-C6-D6-E6 -> 38254.937 | G6: =D6/12 -> 10673 | H6: =B6/C6 -> 2.7577405 | I6: =C6/G6 -> 9.6656404 | J6: Full year
A7: 2024 | B7: 291924.17 | C7: 135964 | D7: 117804 | E7: 15000 | F7: =B7-C7-D7-E7 -> 23156.172 | G7: =D7/12 -> 9817 | H7: =B7/C7 -> 2.1470696 | I7: =C7/G7 -> 13.849852 | J7: Full year
A8: 2025 | B8: 126066.94 | C8: 84374 | D8: 41052 | E8: 15000 | F8: =B8-C8-D8-E8 -> -14359.056 | G8: =D8/12 -> 3421 | H8: =B8/C8 -> 1.4941445 | I8: =C8/G8 -> 24.663549 | J8: Full year
A9: 2026 YTD | B9: 34032.796 | C9: 25433 | D9: 11064 | E9: 6904.11 | F9: =B9-C9-D9-E9 -> -9368.3137 | G9: =D9/12 -> 922 | H9: =B9/C9 -> 1.3381353 | I9: =C9/G9 -> 27.584599 | J9: To 17 June

Sheet Physical Business
A1: TUPENSACI | Physical Business
A2: Relaunch of Diario, Crea and L’Arte from Month 1: owned demand + performance media + 12-month repeat. The Base case targets a recovery toward the best 2023 commercial KPIs.
A5: Month | B5: M1 | C5: M2 | D5: M3 | E5: M4 | F5: M5 | G5: M6 | H5: M7 | I5: M8 | J5: M9 | K5: M10 | L5: M11 | M5: M12 | N5: M13 | O5: M14 | P5: M15 | Q5: M16 | R5: M17 | S5: M18 | T5: M19 | U5: M20 | V5: M21 | W5: M22 | X5: M23 | Y5: M24 | Z5: M25 | AA5: M26 | AB5: M27 | AC5: M28 | AD5: M29 | AE5: M30 | AF5: M31 | AG5: M32 | AH5: M33 | AI5: M34 | AJ5: M35 | AK5: M36
A6: Year | B6: Y1 | C6: Y1 | D6: Y1 | E6: Y1 | F6: Y1 | G6: Y1 | H6: Y1 | I6: Y1 | J6: Y1 | K6: Y1 | L6: Y1 | M6: Y1 | N6: Y2 | O6: Y2 | P6: Y2 | Q6: Y2 | R6: Y2 | S6: Y2 | T6: Y2 | U6: Y2 | V6: Y2 | W6: Y2 | X6: Y2 | Y6: Y2 | Z6: Y3 | AA6: Y3 | AB6: Y3 | AC6: Y3 | AD6: Y3 | AE6: Y3 | AF6: Y3 | AG6: Y3 | AH6: Y3 | AI6: Y3 | AJ6: Y3 | AK6: Y3
A7: Stage | B7: Relaunch | C7: Relaunch | D7: Relaunch | E7: Beta build | F7: Beta build | G7: Gate M6 | H7: AI launch | I7: AI launch | J7: AI launch | K7: Scale test | L7: Scale test | M7: Scale test | N7: Scale | O7: Scale | P7: Scale | Q7: Scale | R7: Scale | S7: Scale | T7: Scale | U7: Scale | V7: Scale | W7: Scale | X7: Scale | Y7: Scale | Z7: Scale | AA7: Scale | AB7: Scale | AC7: Scale | AD7: Scale | AE7: Scale | AF7: Scale | AG7: Scale | AH7: Scale | AI7: Scale | AJ7: Scale | AK7: Scale
A9: PHYSICAL CUSTOMER & ORDER ENGINE
A10: Organic / owned new orders | B10: =Assumptions!$F$17 -> 100 | C10: =B10*(1+IF(2<10,Assumptions!$F$18,Assumptions!$F$19)) -> 101 | D10: =C10*(1+IF(3<10,Assumptions!$F$18,Assumptions!$F$19)) -> 102.01 | E10: =D10*(1+IF(4<10,Assumptions!$F$18,Assumptions!$F$19)) -> 103.0301 | F10: =E10*(1+IF(5<10,Assumptions!$F$18,Assumptions!$F$19)) -> 104.0604 | G10: =F10*(1+IF(6<10,Assumptions!$F$18,Assumptions!$F$19)) -> 105.10101 | H10: =G10*(1+IF(7<10,Assumptions!$F$18,Assumptions!$F$19)) -> 106.15202 | I10: =H10*(1+IF(8<10,Assumptions!$F$18,Assumptions!$F$19)) -> 107.21354 | J10: =I10*(1+IF(9<10,Assumptions!$F$18,Assumptions!$F$19)) -> 108.28567 | K10: =J10*(1+IF(10<10,Assumptions!$F$18,Assumptions!$F$19)) -> 110.45138 | L10: =K10*(1+IF(11<10,Assumptions!$F$18,Assumptions!$F$19)) -> 112.66041 | M10: =L10*(1+IF(12<10,Assumptions!$F$18,Assumptions!$F$19)) -> 114.91362 | N10: =M10*(1+IF(13<10,Assumptions!$F$18,Assumptions!$F$19)) -> 117.21189 | O10: =N10*(1+IF(14<10,Assumptions!$F$18,Assumptions!$F$19)) -> 119.55613 | P10: =O10*(1+IF(15<10,Assumptions!$F$18,Assumptions!$F$19)) -> 121.94725 | Q10: =P10*(1+IF(16<10,Assumptions!$F$18,Assumptions!$F$19)) -> 124.3862 | R10: =Q10*(1+IF(17<10,Assumptions!$F$18,Assumptions!$F$19)) -> 126.87392 | S10: =R10*(1+IF(18<10,Assumptions!$F$18,Assumptions!$F$19)) -> 129.4114 | T10: =S10*(1+IF(19<10,Assumptions!$F$18,Assumptions!$F$19)) -> 131.99963 | U10: =T10*(1+IF(20<10,Assumptions!$F$18,Assumptions!$F$19)) -> 134.63962 | V10: =U10*(1+IF(21<10,Assumptions!$F$18,Assumptions!$F$19)) -> 137.33241 | W10: =V10*(1+IF(22<10,Assumptions!$F$18,Assumptions!$F$19)) -> 140.07906 | X10: =W10*(1+IF(23<10,Assumptions!$F$18,Assumptions!$F$19)) -> 142.88064 | Y10: =X10*(1+IF(24<10,Assumptions!$F$18,Assumptions!$F$19)) -> 145.73826 | Z10: =Y10*(1+IF(25<10,Assumptions!$F$18,Assumptions!$F$19)) -> 148.65302 | AA10: =Z10*(1+IF(26<10,Assumptions!$F$18,Assumptions!$F$19)) -> 151.62608 | AB10: =AA10*(1+IF(27<10,Assumptions!$F$18,Assumptions!$F$19)) -> 154.6586 | AC10: =AB10*(1+IF(28<10,Assumptions!$F$18,Assumptions!$F$19)) -> 157.75177 | AD10: =AC10*(1+IF(29<10,Assumptions!$F$18,Assumptions!$F$19)) -> 160.90681 | AE10: =AD10*(1+IF(30<10,Assumptions!$F$18,Assumptions!$F$19)) -> 164.12495 | AF10: =AE10*(1+IF(31<10,Assumptions!$F$18,Assumptions!$F$19)) -> 167.40745 | AG10: =AF10*(1+IF(32<10,Assumptions!$F$18,Assumptions!$F$19)) -> 170.75559 | AH10: =AG10*(1+IF(33<10,Assumptions!$F$18,Assumptions!$F$19)) -> 174.17071 | AI10: =AH10*(1+IF(34<10,Assumptions!$F$18,Assumptions!$F$19)) -> 177.65412 | AJ10: =AI10*(1+IF(35<10,Assumptions!$F$18,Assumptions!$F$19)) -> 181.2072 | AK10: =AJ10*(1+IF(36<10,Assumptions!$F$18,Assumptions!$F$19)) -> 184.83135
A11: Paid media budget | B11: =IF(1<4,Assumptions!$F$23,IF(1<7,Assumptions!$F$24,IF(1<13,Assumptions!$F$25,Assumptions!$F$82))) -> 6000 | C11: =IF(2<4,Assumptions!$F$23,IF(2<7,Assumptions!$F$24,IF(2<13,Assumptions!$F$25,Assumptions!$F$82))) -> 6000 | D11: =IF(3<4,Assumptions!$F$23,IF(3<7,Assumptions!$F$24,IF(3<13,Assumptions!$F$25,Assumptions!$F$82))) -> 6000 | E11: =IF(4<4,Assumptions!$F$23,IF(4<7,Assumptions!$F$24,IF(4<13,Assumptions!$F$25,Assumptions!$F$82))) -> 8000 | F11: =IF(5<4,Assumptions!$F$23,IF(5<7,Assumptions!$F$24,IF(5<13,Assumptions!$F$25,Assumptions!$F$82))) -> 8000 | G11: =IF(6<4,Assumptions!$F$23,IF(6<7,Assumptions!$F$24,IF(6<13,Assumptions!$F$25,Assumptions!$F$82))) -> 8000 | H11: =IF(7<4,Assumptions!$F$23,IF(7<7,Assumptions!$F$24,IF(7<13,Assumptions!$F$25,Assumptions!$F$82))) -> 11000 | I11: =IF(8<4,Assumptions!$F$23,IF(8<7,Assumptions!$F$24,IF(8<13,Assumptions!$F$25,Assumptions!$F$82))) -> 11000 | J11: =IF(9<4,Assumptions!$F$23,IF(9<7,Assumptions!$F$24,IF(9<13,Assumptions!$F$25,Assumptions!$F$82))) -> 11000 | K11: =IF(10<4,Assumptions!$F$23,IF(10<7,Assumptions!$F$24,IF(10<13,Assumptions!$F$25,Assumptions!$F$82))) -> 11000 | L11: =IF(11<4,Assumptions!$F$23,IF(11<7,Assumptions!$F$24,IF(11<13,Assumptions!$F$25,Assumptions!$F$82))) -> 11000 | M11: =IF(12<4,Assumptions!$F$23,IF(12<7,Assumptions!$F$24,IF(12<13,Assumptions!$F$25,Assumptions!$F$82))) -> 11000 | N11: =IF(13<4,Assumptions!$F$23,IF(13<7,Assumptions!$F$24,IF(13<13,Assumptions!$F$25,Assumptions!$F$82))) -> 12000 | O11: =IF(14<4,Assumptions!$F$23,IF(14<7,Assumptions!$F$24,IF(14<13,Assumptions!$F$25,Assumptions!$F$82))) -> 12000 | P11: =IF(15<4,Assumptions!$F$23,IF(15<7,Assumptions!$F$24,IF(15<13,Assumptions!$F$25,Assumptions!$F$82))) -> 12000 | Q11: =IF(16<4,Assumptions!$F$23,IF(16<7,Assumptions!$F$24,IF(16<13,Assumptions!$F$25,Assumptions!$F$82))) -> 12000 | R11: =IF(17<4,Assumptions!$F$23,IF(17<7,Assumptions!$F$24,IF(17<13,Assumptions!$F$25,Assumptions!$F$82))) -> 12000 | S11: =IF(18<4,Assumptions!$F$23,IF(18<7,Assumptions!$F$24,IF(18<13,Assumptions!$F$25,Assumptions!$F$82))) -> 12000 | T11: =IF(19<4,Assumptions!$F$23,IF(19<7,Assumptions!$F$24,IF(19<13,Assumptions!$F$25,Assumptions!$F$82))) -> 12000 | U11: =IF(20<4,Assumptions!$F$23,IF(20<7,Assumptions!$F$24,IF(20<13,Assumptions!$F$25,Assumptions!$F$82))) -> 12000 | V11: =IF(21<4,Assumptions!$F$23,IF(21<7,Assumptions!$F$24,IF(21<13,Assumptions!$F$25,Assumptions!$F$82))) -> 12000 | W11: =IF(22<4,Assumptions!$F$23,IF(22<7,Assumptions!$F$24,IF(22<13,Assumptions!$F$25,Assumptions!$F$82))) -> 12000 | X11: =IF(23<4,Assumptions!$F$23,IF(23<7,Assumptions!$F$24,IF(23<13,Assumptions!$F$25,Assumptions!$F$82))) -> 12000 | Y11: =IF(24<4,Assumptions!$F$23,IF(24<7,Assumptions!$F$24,IF(24<13,Assumptions!$F$25,Assumptions!$F$82))) -> 12000 | Z11: =IF(25<4,Assumptions!$F$23,IF(25<7,Assumptions!$F$24,IF(25<13,Assumptions!$F$25,Assumptions!$F$82))) -> 12000 | AA11: =IF(26<4,Assumptions!$F$23,IF(26<7,Assumptions!$F$24,IF(26<13,Assumptions!$F$25,Assumptions!$F$82))) -> 12000 | AB11: =IF(27<4,Assumptions!$F$23,IF(27<7,Assumptions!$F$24,IF(27<13,Assumptions!$F$25,Assumptions!$F$82))) -> 12000 | AC11: =IF(28<4,Assumptions!$F$23,IF(28<7,Assumptions!$F$24,IF(28<13,Assumptions!$F$25,Assumptions!$F$82))) -> 12000 | AD11: =IF(29<4,Assumptions!$F$23,IF(29<7,Assumptions!$F$24,IF(29<13,Assumptions!$F$25,Assumptions!$F$82))) -> 12000 | AE11: =IF(30<4,Assumptions!$F$23,IF(30<7,Assumptions!$F$24,IF(30<13,Assumptions!$F$25,Assumptions!$F$82))) -> 12000 | AF11: =IF(31<4,Assumptions!$F$23,IF(31<7,Assumptions!$F$24,IF(31<13,Assumptions!$F$25,Assumptions!$F$82))) -> 12000 | AG11: =IF(32<4,Assumptions!$F$23,IF(32<7,Assumptions!$F$24,IF(32<13,Assumptions!$F$25,Assumptions!$F$82))) -> 12000 | AH11: =IF(33<4,Assumptions!$F$23,IF(33<7,Assumptions!$F$24,IF(33<13,Assumptions!$F$25,Assumptions!$F$82))) -> 12000 | AI11: =IF(34<4,Assumptions!$F$23,IF(34<7,Assumptions!$F$24,IF(34<13,Assumptions!$F$25,Assumptions!$F$82))) -> 12000 | AJ11: =IF(35<4,Assumptions!$F$23,IF(35<7,Assumptions!$F$24,IF(35<13,Assumptions!$F$25,Assumptions!$F$82))) -> 12000 | AK11: =IF(36<4,Assumptions!$F$23,IF(36<7,Assumptions!$F$24,IF(36<13,Assumptions!$F$25,Assumptions!$F$82))) -> 12000
A12: Paid-acquired new orders | B12: =B11/Assumptions!$F$15 -> 521.73913 | C12: =C11/Assumptions!$F$15 -> 521.73913 | D12: =D11/Assumptions!$F$15 -> 521.73913 | E12: =E11/Assumptions!$F$15 -> 695.65217 | F12: =F11/Assumptions!$F$15 -> 695.65217 | G12: =G11/Assumptions!$F$15 -> 695.65217 | H12: =H11/Assumptions!$F$15 -> 956.52174 | I12: =I11/Assumptions!$F$15 -> 956.52174 | ... AK12: =AK11/Assumptions!$F$15 -> 1043.4783
A13: Repeat / cross-sell orders (12m lag) | B13: 0 | C13: 0 | D13: 0 | E13: 0 | F13: 0 | G13: 0 | H13: 0 | I13: 0 | J13: 0 | K13: 0 | L13: 0 | M13: 0 | N13: =B15*Assumptions!$F$14 -> 62.173913 | O13: =C15*Assumptions!$F$14 -> 62.273913 | P13: =D15*Assumptions!$F$14 -> 62.374913 | Q13: =E15*Assumptions!$F$14 -> 79.868227 | R13: =F15*Assumptions!$F$14 -> 79.971257 | S13: =G15*Assumptions!$F$14 -> 80.075318 | T13: =H15*Assumptions!$F$14 -> 106.26738 | U13: =I15*Assumptions!$F$14 -> 106.37353 | ... AK13: =Y15*Assumptions!$F$14 -> 118.92165
A14: Total physical orders | B14: =SUM(B10,B12,B13) -> 621.73913 | C14: =SUM(C10,C12,C13) -> 622.73913 | D14: =SUM(D10,D12,D13) -> 623.74913 | E14: =SUM(E10,E12,E13) -> 798.68227 | F14: =SUM(F10,F12,F13) -> 799.71257 | G14: =SUM(G10,G12,G13) -> 800.75318 | H14: =SUM(H10,H12,H13) -> 1062.6738 | I14: =SUM(I10,I12,I13) -> 1063.7353 | ... AK14: =SUM(AK10,AK12,AK13) -> 1347.2313
A15: New unique physical buyers | B15: =SUM(B10,B12) -> 621.73913 | C15: =SUM(C10,C12) -> 622.73913 | D15: =SUM(D10,D12) -> 623.74913 | E15: =SUM(E10,E12) -> 798.68227 | F15: =SUM(F10,F12) -> 799.71257 | G15: =SUM(G10,G12) -> 800.75318 | H15: =SUM(H10,H12) -> 1062.6738 | I15: =SUM(I10,I12) -> 1063.7353 | ... AK15: =SUM(AK10,AK12) -> 1228.3096
A16: Cumulative addressable physical database | B16: =Assumptions!$C$42+B15 -> 21621.739 | C16: =B16+C15 -> 22244.478 | D16: =C16+D15 -> 22868.227 | E16: =D16+E15 -> 23666.91 | F16: =E16+F15 -> 24466.622 | G16: =F16+G15 -> 25267.375 | H16: =G16+H15 -> 26330.049 | I16: =H16+I15 -> 27393.784 | J16: =I16+J15 -> 28458.592 | ... AK16: =AJ16+AK15 -> 60275.465
A18: Net physical revenue | B18: =B14*Assumptions!$C$40 -> 19895.652 | C18: =C14*Assumptions!$C$40 -> 19927.652 | D18: =D14*Assumptions!$C$40 -> 19959.972 | E18: =E14*Assumptions!$C$40 -> 25557.833 | F18: =F14*Assumptions!$C$40 -> 25590.802 | G18: =G14*Assumptions!$C$40 -> 25624.102 | H18: =H14*Assumptions!$C$40 -> 34005.56 | I18: =I14*Assumptions!$C$40 -> 34039.529 | ... AK18: =AK14*Assumptions!$C$40 -> 43111.4
A19: Print + fulfillment cost | B19: =-B14*Assumptions!$C$41 -> -7460.8696 | C19: =-C14*Assumptions!$C$41 -> -7472.8696 | D19: =-D14*Assumptions!$C$41 -> -7484.9896 | E19: =-E14*Assumptions!$C$41 -> -9584.1873 | F19: =-F14*Assumptions!$C$41 -> -9596.5509 | G19: =-G14*Assumptions!$C$41 -> -9609.0381 | H19: =-H14*Assumptions!$C$41 -> -12752.085 | I19: =-I14*Assumptions!$C$41 -> -12764.823 | ... AK19: =-AK14*Assumptions!$C$41 -> -16166.775
A20: Physical acquisition cost | B20: =-B11 -> -6000 | C20: =-C11 -> -6000 | D20: =-D11 -> -6000 | E20: =-E11 -> -8000 | F20: =-F11 -> -8000 | G20: =-G11 -> -8000 | H20: =-H11 -> -11000 | I20: =-I11 -> -11000 | ... AK20: =-AK11 -> -12000
A21: Physical contribution after acquisition | B21: =SUM(B18:B20) -> 6434.7826 | C21: =SUM(C18:C20) -> 6454.7826 | D21: =SUM(D18:D20) -> 6474.9826 | E21: =SUM(E18:E20) -> 7973.6455 | F21: =SUM(F18:F20) -> 7994.2515 | G21: =SUM(G18:G20) -> 8015.0636 | H21: =SUM(H18:H20) -> 10253.475 | I21: =SUM(I18:I20) -> 10274.705 | ... AK21: =SUM(AK18:AK20) -> 14944.625
A23: AI attached users from physical buyers | B23: =B15*Assumptions!$F$10 -> 62.173913 | C23: =C15*Assumptions!$F$10 -> 62.273913 | D23: =D15*Assumptions!$F$10 -> 62.374913 | E23: =E15*Assumptions!$F$10 -> 79.868227 | F23: =F15*Assumptions!$F$10 -> 79.971257 | G23: =G15*Assumptions!$F$10 -> 80.075318 | H23: =H15*Assumptions!$F$10 -> 106.26738 | I23: =I15*Assumptions!$F$10 -> 106.37353 | ... AK23: =AK15*Assumptions!$F$10 -> 122.83096

Sheet AI Cohorts
A1: TUPENSACI | AI Cohorts — Base Case v3.0
A2: Il Base mantiene i volumi di acquisizione della v2.1 e cambia soltanto pricing e margine: €9/mese, €89/anno, €69 founding per community/clienti nel primo anno. La prova guidata dura 7 giorni e non è un tier gratuito permanente.
A5: Month | B5: M1 | C5: M2 | D5: M3 | E5: M4 | F5: M5 | G5: M6 | H5: M7 | I5: M8 | J5: M9 | K5: M10 | L5: M11 | M5: M12 | N5: M13 | O5: M14 | P5: M15 | Q5: M16 | R5: M17 | S5: M18 | T5: M19 | U5: M20 | V5: M21 | W5: M22 | X5: M23 | Y5: M24 | Z5: M25 | AA5: M26 | AB5: M27 | AC5: M28 | AD5: M29 | AE5: M30 | AF5: M31 | AG5: M32 | AH5: M33 | AI5: M34 | AJ5: M35 | AK5: M36
A6: Year | B6: Y1 | C6: Y1 | D6: Y1 | E6: Y1 | F6: Y1 | G6: Y1 | H6: Y1 | I6: Y1 | J6: Y1 | K6: Y1 | L6: Y1 | M6: Y1 | N6: Y2 | O6: Y2 | P6: Y2 | Q6: Y2 | R6: Y2 | S6: Y2 | T6: Y2 | U6: Y2 | V6: Y2 | W6: Y2 | X6: Y2 | Y6: Y2 | Z6: Y3 | AA6: Y3 | AB6: Y3 | AC6: Y3 | AD6: Y3 | AE6: Y3 | AF6: Y3 | AG6: Y3 | AH6: Y3 | AI6: Y3 | AJ6: Y3 | AK6: Y3
A7: Stage | B7: Relaunch | C7: Relaunch | D7: Relaunch | E7: Beta build | F7: Beta build | G7: Gate M6 | H7: AI launch | I7: AI launch | J7: AI launch | K7: Scale test | L7: Scale test | M7: Scale test | N7: Scale | O7: Scale | P7: Scale | Q7: Scale | R7: Scale | S7: Scale | T7: Scale | U7: Scale | V7: Scale | W7: Scale | X7: Scale | Y7: Scale | Z7: Scale | AA7: Scale | AB7: Scale | AC7: Scale | AD7: Scale | AE7: Scale | AF7: Scale | AG7: Scale | AH7: Scale | AI7: Scale | AJ7: Scale | AK7: Scale
A9: AI ACQUISITION & COHORT ROLL-FORWARD
A10: Historical database conversions | B10: =IF(AND(1>=Assumptions!$C$49,1<Assumptions!$C$49+Assumptions!$C$52),Assumptions!$C$42*Assumptions!$F$9/Assumptions!$C$52,0) -> 0 | C10: =IF(AND(2>=Assumptions!$C$49,2<Assumptions!$C$49+Assumptions!$C$52),Assumptions!$C$42*Assumptions!$F$9/Assumptions!$C$52,0) -> 0 | D10: =IF(AND(3>=Assumptions!$C$49,3<Assumptions!$C$49+Assumptions!$C$52),Assumptions!$C$42*Assumptions!$F$9/Assumptions!$C$52,0) -> 0 | E10: =IF(AND(4>=Assumptions!$C$49,4<Assumptions!$C$49+Assumptions!$C$52),Assumptions!$C$42*Assumptions!$F$9/Assumptions!$C$52,0) -> 70 | F10: =IF(AND(5>=Assumptions!$C$49,5<Assumptions!$C$49+Assumptions!$C$52),Assumptions!$C$42*Assumptions!$F$9/Assumptions!$C$52,0) -> 70 | G10: =IF(AND(6>=Assumptions!$C$49,6<Assumptions!$C$49+Assumptions!$C$52),Assumptions!$C$42*Assumptions!$F$9/Assumptions!$C$52,0) -> 70 | H10: =IF(AND(7>=Assumptions!$C$49,7<Assumptions!$C$49+Assumptions!$C$52),Assumptions!$C$42*Assumptions!$F$9/Assumptions!$C$52,0) -> 70 | I10: =IF(AND(8>=Assumptions!$C$49,8<Assumptions!$C$49+Assumptions!$C$52),Assumptions!$C$42*Assumptions!$F$9/Assumptions!$C$52,0) -> 70 | J10: =IF(AND(9>=Assumptions!$C$49,9<Assumptions!$C$49+Assumptions!$C$52),Assumptions!$C$42*Assumptions!$F$9/Assumptions!$C$52,0) -> 70 | K10: =IF(AND(10>=Assumptions!$C$49,10<Assumptions!$C$49+Assumptions!$C$52),Assumptions!$C$42*Assumptions!$F$9/Assumptions!$C$52,0) -> 0 | L10: =IF(AND(11>=Assumptions!$C$49,11<Assumptions!$C$49+Assumptions!$C$52),Assumptions!$C$42*Assumptions!$F$9/Assumptions!$C$52,0) -> 0 | M10: =IF(AND(12>=Assumptions!$C$49,12<Assumptions!$C$49+Assumptions!$C$52),Assumptions!$C$42*Assumptions!$F$9/Assumptions!$C$52,0) -> 0 | N10: =IF(AND(13>=Assumptions!$C$49,13<Assumptions!$C$49+Assumptions!$C$52),Assumptions!$C$42*Assumptions!$F$9/Assumptions!$C$52,0) -> 0 | O10: =IF(AND(14>=Assumptions!$C$49,14<Assumptions!$C$49+Assumptions!$C$52),Assumptions!$C$42*Assumptions!$F$9/Assumptions!$C$52,0) -> 0 | P10: =IF(AND(15>=Assumptions!$C$49,15<Assumptions!$C$49+Assumptions!$C$52),Assumptions!$C$42*Assumptions!$F$9/Assumptions!$C$52,0) -> 0 | Q10: =IF(AND(16>=Assumptions!$C$49,16<Assumptions!$C$49+Assumptions!$C$52),Assumptions!$C$42*Assumptions!$F$9/Assumptions!$C$52,0) -> 0 | R10: =IF(AND(17>=Assumptions!$C$49,17<Assumptions!$C$49+Assumptions!$C$52),Assumptions!$C$42*Assumptions!$F$9/Assumptions!$C$52,0) -> 0 | S10: =IF(AND(18>=Assumptions!$C$49,18<Assumptions!$C$49+Assumptions!$C$52),Assumptions!$C$42*Assumptions!$F$9/Assumptions!$C$52,0) -> 0 | T10: =IF(AND(19>=Assumptions!$C$49,19<Assumptions!$C$49+Assumptions!$C$52),Assumptions!$C$42*Assumptions!$F$9/Assumptions!$C$52,0) -> 0 | U10: =IF(AND(20>=Assumptions!$C$49,20<Assumptions!$C$49+Assumptions!$C$52),Assumptions!$C$42*Assumptions!$F$9/Assumptions!$C$52,0) -> 0 | V10: =IF(AND(21>=Assumptions!$C$49,21<Assumptions!$C$49+Assumptions!$C$52),Assumptions!$C$42*Assumptions!$F$9/Assumptions!$C$52,0) -> 0 | W10: =IF(AND(22>=Assumptions!$C$49,22<Assumptions!$C$49+Assumptions!$C$52),Assumptions!$C$42*Assumptions!$F$9/Assumptions!$C$52,0) -> 0 | X10: =IF(AND(23>=Assumptions!$C$49,23<Assumptions!$C$49+Assumptions!$C$52),Assumptions!$C$42*Assumptions!$F$9/Assumptions!$C$52,0) -> 0 | Y10: =IF(AND(24>=Assumptions!$C$49,24<Assumptions!$C$49+Assumptions!$C$52),Assumptions!$C$42*Assumptions!$F$9/Assumptions!$C$52,0) -> 0 | Z10: =IF(AND(25>=Assumptions!$C$49,25<Assumptions!$C$49+Assumptions!$C$52),Assumptions!$C$42*Assumptions!$F$9/Assumptions!$C$52,0) -> 0 | AA10: =IF(AND(26>=Assumptions!$C$49,26<Assumptions!$C$49+Assumptions!$C$52),Assumptions!$C$42*Assumptions!$F$9/Assumptions!$C$52,0) -> 0 | AB10: =IF(AND(27>=Assumptions!$C$49,27<Assumptions!$C$49+Assumptions!$C$52),Assumptions!$C$42*Assumptions!$F$9/Assumptions!$C$52,0) -> 0 | AC10: =IF(AND(28>=Assumptions!$C$49,28<Assumptions!$C$49+Assumptions!$C$52),Assumptions!$C$42*Assumptions!$F$9/Assumptions!$C$52,0) -> 0 | AD10: =IF(AND(29>=Assumptions!$C$49,29<Assumptions!$C$49+Assumptions!$C$52),Assumptions!$C$42*Assumptions!$F$9/Assumptions!$C$52,0) -> 0 | AE10: =IF(AND(30>=Assumptions!$C$49,30<Assumptions!$C$49+Assumptions!$C$52),Assumptions!$C$42*Assumptions!$F$9/Assumptions!$C$52,0) -> 0 | AF10: =IF(AND(31>=Assumptions!$C$49,31<Assumptions!$C$49+Assumptions!$C$52),Assumptions!$C$42*Assumptions!$F$9/Assumptions!$C$52,0) -> 0 | AG10: =IF(AND(32>=Assumptions!$C$49,32<Assumptions!$C$49+Assumptions!$C$52),Assumptions!$C$42*Assumptions!$F$9/Assumptions!$C$52,0) -> 0 | AH10: =IF(AND(33>=Assumptions!$C$49,33<Assumptions!$C$49+Assumptions!$C$52),Assumptions!$C$42*Assumptions!$F$9/Assumptions!$C$52,0) -> 0 | AI10: =IF(AND(34>=Assumptions!$C$49,34<Assumptions!$C$49+Assumptions!$C$52),Assumptions!$C$42*Assumptions!$F$9/Assumptions!$C$52,0) -> 0 | AJ10: =IF(AND(35>=Assumptions!$C$49,35<Assumptions!$C$49+Assumptions!$C$52),Assumptions!$C$42*Assumptions!$F$9/Assumptions!$C$52,0) -> 0 | AK10: =IF(AND(36>=Assumptions!$C$49,36<Assumptions!$C$49+Assumptions!$C$52),Assumptions!$C$42*Assumptions!$F$9/Assumptions!$C$52,0) -> 0
A11: Physical buyer AI attach conversions | B11: =IF(1<Assumptions!$C$49,0,'Physical Business'!B23) -> 0 | C11: =IF(2<Assumptions!$C$49,0,'Physical Business'!C23) -> 0 | D11: =IF(3<Assumptions!$C$49,0,'Physical Business'!D23) -> 0 | E11: =IF(4<Assumptions!$C$49,0,'Physical Business'!E23) -> 79.868227 | F11: =IF(5<Assumptions!$C$49,0,'Physical Business'!F23) -> 79.971257 | G11: =IF(6<Assumptions!$C$49,0,'Physical Business'!G23) -> 80.075318 | H11: =IF(7<Assumptions!$C$49,0,'Physical Business'!H23) -> 106.26738 | I11: =IF(8<Assumptions!$C$49,0,'Physical Business'!I23) -> 106.37353 | J11: =IF(9<Assumptions!$C$49,0,'Physical Business'!J23) -> 106.48074 | K11: =IF(10<Assumptions!$C$49,0,'Physical Business'!K23) -> 106.69731 | L11: =IF(11<Assumptions!$C$49,0,'Physical Business'!L23) -> 106.91822 | M11: =IF(12<Assumptions!$C$49,0,'Physical Business'!M23) -> 107.14354 | N11: =IF(13<Assumptions!$C$49,0,'Physical Business'!N23) -> 116.06902 | O11: =IF(14<Assumptions!$C$49,0,'Physical Business'!O23) -> 116.30344 | P11: =IF(15<Assumptions!$C$49,0,'Physical Business'!P23) -> 116.54255 | Q11: =IF(16<Assumptions!$C$49,0,'Physical Business'!Q23) -> 116.78645 | R11: =IF(17<Assumptions!$C$49,0,'Physical Business'!R23) -> 117.03522 | S11: =IF(18<Assumptions!$C$49,0,'Physical Business'!S23) -> 117.28897 | T11: =IF(19<Assumptions!$C$49,0,'Physical Business'!T23) -> 117.54779 | U11: =IF(20<Assumptions!$C$49,0,'Physical Business'!U23) -> 117.81179 | V11: =IF(21<Assumptions!$C$49,0,'Physical Business'!V23) -> 118.08107 | W11: =IF(22<Assumptions!$C$49,0,'Physical Business'!W23) -> 118.35573 | X11: =IF(23<Assumptions!$C$49,0,'Physical Business'!X23) -> 118.63589 | Y11: =IF(24<Assumptions!$C$49,0,'Physical Business'!Y23) -> 118.92165 | Z11: =IF(25<Assumptions!$C$49,0,'Physical Business'!Z23) -> 119.21313 | AA11: =IF(26<Assumptions!$C$49,0,'Physical Business'!AA23) -> 119.51043 | AB11: =IF(27<Assumptions!$C$49,0,'Physical Business'!AB23) -> 119.81369 | AC11: =IF(28<Assumptions!$C$49,0,'Physical Business'!AC23) -> 120.123 | AD11: =IF(29<Assumptions!$C$49,0,'Physical Business'!AD23) -> 120.43851 | AE11: =IF(30<Assumptions!$C$49,0,'Physical Business'!AE23) -> 120.76032 | AF11: =IF(31<Assumptions!$C$49,0,'Physical Business'!AF23) -> 121.08857 | AG11: =IF(32<Assumptions!$C$49,0,'Physical Business'!AG23) -> 121.42339 | AH11: =IF(33<Assumptions!$C$49,0,'Physical Business'!AH23) -> 121.7649 | AI11: =IF(34<Assumptions!$C$49,0,'Physical Business'!AI23) -> 122.11324 | AJ11: =IF(35<Assumptions!$C$49,0,'Physical Business'!AJ23) -> 122.46855 | AK11: =IF(36<Assumptions!$C$49,0,'Physical Business'!AK23) -> 122.83096
A12: Owned beta/direct users | B12: =IF(AND(1>=Assumptions!$C$49,1<=Assumptions!$C$50),Assumptions!$F$20,0) -> 0 | C12: =IF(AND(2>=Assumptions!$C$49,2<=Assumptions!$C$50),Assumptions!$F$20,0) -> 0 | D12: =IF(AND(3>=Assumptions!$C$49,3<=Assumptions!$C$50),Assumptions!$F$20,0) -> 0 | E12: =IF(AND(4>=Assumptions!$C$49,4<=Assumptions!$C$50),Assumptions!$F$20,0) -> 50 | F12: =IF(AND(5>=Assumptions!$C$49,5<=Assumptions!$C$50),Assumptions!$F$20,0) -> 50 | G12: =IF(AND(6>=Assumptions!$C$49,6<=Assumptions!$C$50),Assumptions!$F$20,0) -> 50 | H12: =IF(AND(7>=Assumptions!$C$49,7<=Assumptions!$C$50),Assumptions!$F$20,0) -> 0 | I12: =IF(AND(8>=Assumptions!$C$49,8<=Assumptions!$C$50),Assumptions!$F$20,0) -> 0 | J12: =IF(AND(9>=Assumptions!$C$49,9<=Assumptions!$C$50),Assumptions!$F$20,0) -> 0 | K12: =IF(AND(10>=Assumptions!$C$49,10<=Assumptions!$C$50),Assumptions!$F$20,0) -> 0 | L12: =IF(AND(11>=Assumptions!$C$49,11<=Assumptions!$C$50),Assumptions!$F$20,0) -> 0 | M12: =IF(AND(12>=Assumptions!$C$49,12<=Assumptions!$C$50),Assumptions!$F$20,0) -> 0 | N12: =IF(AND(13>=Assumptions!$C$49,13<=Assumptions!$C$50),Assumptions!$F$20,0) -> 0 | O12: =IF(AND(14>=Assumptions!$C$49,14<=Assumptions!$C$50),Assumptions!$F$20,0) -> 0 | P12: =IF(AND(15>=Assumptions!$C$49,15<=Assumptions!$C$50),Assumptions!$F$20,0) -> 0 | Q12: =IF(AND(16>=Assumptions!$C$49,16<=Assumptions!$C$50),Assumptions!$F$20,0) -> 0 | R12: =IF(AND(17>=Assumptions!$C$49,17<=Assumptions!$C$50),Assumptions!$F$20,0) -> 0 | S12: =IF(AND(18>=Assumptions!$C$49,18<=Assumptions!$C$50),Assumptions!$F$20,0) -> 0 | T12: =IF(AND(19>=Assumptions!$C$49,19<=Assumptions!$C$50),Assumptions!$F$20,0) -> 0 | U12: =IF(AND(20>=Assumptions!$C$49,20<=Assumptions!$C$50),Assumptions!$F$20,0) -> 0 | V12: =IF(AND(21>=Assumptions!$C$49,21<=Assumptions!$C$50),Assumptions!$F$20,0) -> 0 | W12: =IF(AND(22>=Assumptions!$C$49,22<=Assumptions!$C$50),Assumptions!$F$20,0) -> 0 | X12: =IF(AND(23>=Assumptions!$C$49,23<=Assumptions!$C$50),Assumptions!$F$20,0) -> 0 | Y12: =IF(AND(24>=Assumptions!$C$49,24<=Assumptions!$C$50),Assumptions!$F$20,0) -> 0 | Z12: =IF(AND(25>=Assumptions!$C$49,25<=Assumptions!$C$50),Assumptions!$F$20,0) -> 0 | AA12: =IF(AND(26>=Assumptions!$C$49,26<=Assumptions!$C$50),Assumptions!$F$20,0) -> 0 | AB12: =IF(AND(27>=Assumptions!$C$49,27<=Assumptions!$C$50),Assumptions!$F$20,0) -> 0 | AC12: =IF(AND(28>=Assumptions!$C$49,28<=Assumptions!$C$50),Assumptions!$F$20,0) -> 0 | AD12: =IF(AND(29>=Assumptions!$C$49,29<=Assumptions!$C$50),Assumptions!$F$20,0) -> 0 | AE12: =IF(AND(30>=Assumptions!$C$49,30<=Assumptions!$C$50),Assumptions!$F$20,0) -> 0 | AF12: =IF(AND(31>=Assumptions!$C$49,31<=Assumptions!$C$50),Assumptions!$F$20,0) -> 0 | AG12: =IF(AND(32>=Assumptions!$C$49,32<=Assumptions!$C$50),Assumptions!$F$20,0) -> 0 | AH12: =IF(AND(33>=Assumptions!$C$49,33<=Assumptions!$C$50),Assumptions!$F$20,0) -> 0 | AI12: =IF(AND(34>=Assumptions!$C$49,34<=Assumptions!$C$50),Assumptions!$F$20,0) -> 0 | AJ12: =IF(AND(35>=Assumptions!$C$49,35<=Assumptions!$C$50),Assumptions!$F$20,0) -> 0 | AK12: =IF(AND(36>=Assumptions!$C$49,36<=Assumptions!$C$50),Assumptions!$F$20,0) -> 0
A13: Direct AI media budget | B13: =IF(1<Assumptions!$C$51,0,IF(Assumptions!$E$5="Test",IF(1<19,Assumptions!$C$64,Assumptions!$C$65),IF(1<19,Assumptions!$F$21,Assumptions!$F$22))) -> 0 | C13: =IF(2<Assumptions!$C$51,0,IF(Assumptions!$E$5="Test",IF(2<19,Assumptions!$C$64,Assumptions!$C$65),IF(2<19,Assumptions!$F$21,Assumptions!$F$22))) -> 0 | D13: =IF(3<Assumptions!$C$51,0,IF(Assumptions!$E$5="Test",IF(3<19,Assumptions!$C$64,Assumptions!$C$65),IF(3<19,Assumptions!$F$21,Assumptions!$F$22))) -> 0 | E13: =IF(4<Assumptions!$C$51,0,IF(Assumptions!$E$5="Test",IF(4<19,Assumptions!$C$64,Assumptions!$C$65),IF(4<19,Assumptions!$F$21,Assumptions!$F$22))) -> 0 | F13: =IF(5<Assumptions!$C$51,0,IF(Assumptions!$E$5="Test",IF(5<19,Assumptions!$C$64,Assumptions!$C$65),IF(5<19,Assumptions!$F$21,Assumptions!$F$22))) -> 0 | G13: =IF(6<Assumptions!$C$51,0,IF(Assumptions!$E$5="Test",IF(6<19,Assumptions!$C$64,Assumptions!$C$65),IF(6<19,Assumptions!$F$21,Assumptions!$F$22))) -> 0 | H13: =IF(7<Assumptions!$C$51,0,IF(Assumptions!$E$5="Test",IF(7<19,Assumptions!$C$64,Assumptions!$C$65),IF(7<19,Assumptions!$F$21,Assumptions!$F$22))) -> 4000 | I13: =IF(8<Assumptions!$C$51,0,IF(Assumptions!$E$5="Test",IF(8<19,Assumptions!$C$64,Assumptions!$C$65),IF(8<19,Assumptions!$F$21,Assumptions!$F$22))) -> 4000 | J13: =IF(9<Assumptions!$C$51,0,IF(Assumptions!$E$5="Test",IF(9<19,Assumptions!$C$64,Assumptions!$C$65),IF(9<19,Assumptions!$F$21,Assumptions!$F$22))) -> 4000 | K13: =IF(10<Assumptions!$C$51,0,IF(Assumptions!$E$5="Test",IF(10<19,Assumptions!$C$64,Assumptions!$C$65),IF(10<19,Assumptions!$F$21,Assumptions!$F$22))) -> 4000 | L13: =IF(11<Assumptions!$C$51,0,IF(Assumptions!$E$5="Test",IF(11<19,Assumptions!$C$64,Assumptions!$C$65),IF(11<19,Assumptions!$F$21,Assumptions!$F$22))) -> 4000 | M13: =IF(12<Assumptions!$C$51,0,IF(Assumptions!$E$5="Test",IF(12<19,Assumptions!$C$64,Assumptions!$C$65),IF(12<19,Assumptions!$F$21,Assumptions!$F$22))) -> 4000 | N13: =IF(13<Assumptions!$C$51,0,IF(Assumptions!$E$5="Test",IF(13<19,Assumptions!$C$64,Assumptions!$C$65),IF(13<19,Assumptions!$F$21,Assumptions!$F$22))) -> 4000 | O13: =IF(14<Assumptions!$C$51,0,IF(Assumptions!$E$5="Test",IF(14<19,Assumptions!$C$64,Assumptions!$C$65),IF(14<19,Assumptions!$F$21,Assumptions!$F$22))) -> 4000 | P13: =IF(15<Assumptions!$C$51,0,IF(Assumptions!$E$5="Test",IF(15<19,Assumptions!$C$64,Assumptions!$C$65),IF(15<19,Assumptions!$F$21,Assumptions!$F$22))) -> 4000 | Q13: =IF(16<Assumptions!$C$51,0,IF(Assumptions!$E$5="Test",IF(16<19,Assumptions!$C$64,Assumptions!$C$65),IF(16<19,Assumptions!$F$21,Assumptions!$F$22))) -> 4000 | R13: =IF(17<Assumptions!$C$51,0,IF(Assumptions!$E$5="Test",IF(17<19,Assumptions!$C$64,Assumptions!$C$65),IF(17<19,Assumptions!$F$21,Assumptions!$F$22))) -> 4000 | S13: =IF(18<Assumptions!$C$51,0,IF(Assumptions!$E$5="Test",IF(18<19,Assumptions!$C$64,Assumptions!$C$65),IF(18<19,Assumptions!$F$21,Assumptions!$F$22))) -> 4000 | T13: =IF(19<Assumptions!$C$51,0,IF(Assumptions!$E$5="Test",IF(19<19,Assumptions!$C$64,Assumptions!$C$65),IF(19<19,Assumptions!$F$21,Assumptions!$F$22))) -> 6000 | U13: =IF(20<Assumptions!$C$51,0,IF(Assumptions!$E$5="Test",IF(20<19,Assumptions!$C$64,Assumptions!$C$65),IF(20<19,Assumptions!$F$21,Assumptions!$F$22))) -> 6000 | V13: =IF(21<Assumptions!$C$51,0,IF(Assumptions!$E$5="Test",IF(21<19,Assumptions!$C$64,Assumptions!$C$65),IF(21<19,Assumptions!$F$21,Assumptions!$F$22))) -> 6000 | W13: =IF(22<Assumptions!$C$51,0,IF(Assumptions!$E$5="Test",IF(22<19,Assumptions!$C$64,Assumptions!$C$65),IF(22<19,Assumptions!$F$21,Assumptions!$F$22))) -> 6000 | X13: =IF(23<Assumptions!$C$51,0,IF(Assumptions!$E$5="Test",IF(23<19,Assumptions!$C$64,Assumptions!$C$65),IF(23<19,Assumptions!$F$21,Assumptions!$F$22))) -> 6000 | Y13: =IF(24<Assumptions!$C$51,0,IF(Assumptions!$E$5="Test",IF(24<19,Assumptions!$C$64,Assumptions!$C$65),IF(24<19,Assumptions!$F$21,Assumptions!$F$22))) -> 6000 | Z13: =IF(25<Assumptions!$C$51,0,IF(Assumptions!$E$5="Test",IF(25<19,Assumptions!$C$64,Assumptions!$C$65),IF(25<19,Assumptions!$F$21,Assumptions!$F$22))) -> 6000 | AA13: =IF(26<Assumptions!$C$51,0,IF(Assumptions!$E$5="Test",IF(26<19,Assumptions!$C$64,Assumptions!$C$65),IF(26<19,Assumptions!$F$21,Assumptions!$F$22))) -> 6000 | AB13: =IF(27<Assumptions!$C$51,0,IF(Assumptions!$E$5="Test",IF(27<19,Assumptions!$C$64,Assumptions!$C$65),IF(27<19,Assumptions!$F$21,Assumptions!$F$22))) -> 6000 | AC13: =IF(28<Assumptions!$C$51,0,IF(Assumptions!$E$5="Test",IF(28<19,Assumptions!$C$64,Assumptions!$C$65),IF(28<19,Assumptions!$F$21,Assumptions!$F$22))) -> 6000 | AD13: =IF(29<Assumptions!$C$51,0,IF(Assumptions!$E$5="Test",IF(29<19,Assumptions!$C$64,Assumptions!$C$65),IF(29<19,Assumptions!$F$21,Assumptions!$F$22))) -> 6000 | AE13: =IF(30<Assumptions!$C$51,0,IF(Assumptions!$E$5="Test",IF(30<19,Assumptions!$C$64,Assumptions!$C$65),IF(30<19,Assumptions!$F$21,Assumptions!$F$22))) -> 6000 | AF13: =IF(31<Assumptions!$C$51,0,IF(Assumptions!$E$5="Test",IF(31<19,Assumptions!$C$64,Assumptions!$C$65),IF(31<19,Assumptions!$F$21,Assumptions!$F$22))) -> 6000 | AG13: =IF(32<Assumptions!$C$51,0,IF(Assumptions!$E$5="Test",IF(32<19,Assumptions!$C$64,Assumptions!$C$65),IF(32<19,Assumptions!$F$21,Assumptions!$F$22))) -> 6000 | AH13: =IF(33<Assumptions!$C$51,0,IF(Assumptions!$E$5="Test",IF(33<19,Assumptions!$C$64,Assumptions!$C$65),IF(33<19,Assumptions!$F$21,Assumptions!$F$22))) -> 6000 | AI13: =IF(34<Assumptions!$C$51,0,IF(Assumptions!$E$5="Test",IF(34<19,Assumptions!$C$64,Assumptions!$C$65),IF(34<19,Assumptions!$F$21,Assumptions!$F$22))) -> 6000 | AJ13: =IF(35<Assumptions!$C$51,0,IF(Assumptions!$E$5="Test",IF(35<19,Assumptions!$C$64,Assumptions!$C$65),IF(35<19,Assumptions!$F$21,Assumptions!$F$22))) -> 6000 | AK13: =IF(36<Assumptions!$C$51,0,IF(Assumptions!$E$5="Test",IF(36<19,Assumptions!$C$64,Assumptions!$C$65),IF(36<19,Assumptions!$F$21,Assumptions!$F$22))) -> 6000
A14: Direct AI paid users | B14: =B13/Assumptions!$C$68 -> 0 | C14: =C13/Assumptions!$C$68 -> 0 | D14: =D13/Assumptions!$C$68 -> 0 | E14: =E13/Assumptions!$C$68 -> 0 | F14: =F13/Assumptions!$C$68 -> 0 | G14: =G13/Assumptions!$C$68 -> 0 | H14: =H13/Assumptions!$C$68 -> 178.57143 | I14: =I13/Assumptions!$C$68 -> 178.57143 | ... AK14: =AK13/Assumptions!$C$68 -> 267.85714
A15: Total new AI users | B15: =SUM(B10:B12,B14) -> 0 | C15: =SUM(C10:C12,C14) -> 0 | D15: =SUM(D10:D12,D14) -> 0 | E15: =SUM(E10:E12,E14) -> 199.86823 | F15: =SUM(F10:F12,F14) -> 199.97126 | G15: =SUM(G10:G12,G14) -> 200.07532 | H15: =SUM(H10:H12,H14) -> 354.8388 | I15: =SUM(I10:I12,I14) -> 354.94496 | ... AK15: =SUM(AK10:AK12,AK14) -> 390.6881
A17: Founding annual users (€69) | B17: =SUM(B10:B11)*Assumptions!$F$11 -> 0 | C17: =SUM(C10:C11)*Assumptions!$F$11 -> 0 | D17: =SUM(D10:D11)*Assumptions!$F$11 -> 0 | E17: =SUM(E10:E11)*Assumptions!$F$11 -> 44.960468 | F17: =SUM(F10:F11)*Assumptions!$F$11 -> 44.991377 | G17: =SUM(G10:G11)*Assumptions!$F$11 -> 45.022595 | H17: =SUM(H10:H11)*Assumptions!$F$11 -> 52.880213 | I17: =SUM(I10:I11)*Assumptions!$F$11 -> 52.912058 | ... AK17: =SUM(AK10:AK11)*Assumptions!$F$11 -> 36.849288
A18: Standard annual users (€89) | B18: =SUM(B12,B14)*Assumptions!$F$11 -> 0 | C18: =SUM(C12,C14)*Assumptions!$F$11 -> 0 | D18: =SUM(D12,D14)*Assumptions!$F$11 -> 0 | E18: =SUM(E12,E14)*Assumptions!$F$11 -> 15 | F18: =SUM(F12,F14)*Assumptions!$F$11 -> 15 | G18: =SUM(G12,G14)*Assumptions!$F$11 -> 15 | H18: =SUM(H12,H14)*Assumptions!$F$11 -> 53.571429 | I18: =SUM(I12,I14)*Assumptions!$F$11 -> 53.571429 | ... AK18: =SUM(AK12,AK14)*Assumptions!$F$11 -> 80.357143
A19: New monthly users (€9) | B19: =B15*(1-Assumptions!$F$11) -> 0 | C19: =C15*(1-Assumptions!$F$11) -> 0 | D19: =D15*(1-Assumptions!$F$11) -> 0 | E19: =E15*(1-Assumptions!$F$11) -> 139.90776 | F19: =F15*(1-Assumptions!$F$11) -> 139.97988 | G19: =G15*(1-Assumptions!$F$11) -> 140.05272 | H19: =H15*(1-Assumptions!$F$11) -> 248.38716 | I19: =I15*(1-Assumptions!$F$11) -> 248.46147 | ... AK19: =AK15*(1-Assumptions!$F$11) -> 273.48167
A20: Annual renewals (€89) | B20: 0 | C20: 0 | D20: 0 | E20: 0 | F20: 0 | G20: 0 | H20: 0 | I20: 0 | J20: 0 | K20: 0 | L20: 0 | M20: 0 | N20: =SUM(B17:B18,B20)*Assumptions!$F$13 -> 0 | O20: =SUM(C17:C18,C20)*Assumptions!$F$13 -> 0 | P20: =SUM(D17:D18,D20)*Assumptions!$F$13 -> 0 | Q20: =SUM(E17:E18,E20)*Assumptions!$F$13 -> 26.982211 | R20: =SUM(F17:F18,F20)*Assumptions!$F$13 -> 26.99612 | S20: =SUM(G17:G18,G20)*Assumptions!$F$13 -> 27.010168 | T20: =SUM(H17:H18,H20)*Assumptions!$F$13 -> 47.903239 | U20: =SUM(I17:I18,I20)*Assumptions!$F$13 -> 47.917569 | ... AK20: =SUM(Y17:Y18,Y20)*Assumptions!$F$13 -> 69.572321
A22: Opening active monthly users | B22: =0 -> 0 | C22: =B24 -> 0 | D22: =C24 -> 0 | E22: =D24 -> 0 | F22: =E24 -> 139.90776 | G22: =F24 -> 268.69502 | H22: =G24 -> 387.25214 | I22: =H24 -> 604.65913 | J22: =I24 -> 804.74787 | ... AK22: =AJ24 -> 3015.4469
A23: Monthly churned users | B23: =-B22*Assumptions!$C$69 -> 0 | C23: =-C22*Assumptions!$C$69 -> 0 | D23: =-D22*Assumptions!$C$69 -> 0 | E23: =-E22*Assumptions!$C$69 -> 0 | F23: =-F22*Assumptions!$C$69 -> -11.192621 | G23: =-G22*Assumptions!$C$69 -> -21.495601 | H23: =-H22*Assumptions!$C$69 -> -30.980171 | I23: =-I22*Assumptions!$C$69 -> -48.372731 | ... AK23: =-AK22*Assumptions!$C$69 -> -241.23575
A24: Closing active monthly users | B24: =SUM(B22:B23,B19) -> 0 | C24: =SUM(C22:C23,C19) -> 0 | D24: =SUM(D22:D23,D19) -> 0 | E24: =SUM(E22:E23,E19) -> 139.90776 | F24: =SUM(F22:F23,F19) -> 268.69502 | G24: =SUM(G22:G23,G19) -> 387.25214 | H24: =SUM(H22:H23,H19) -> 604.65913 | I24: =SUM(I22:I23,I19) -> 804.74787 | ... AK24: =SUM(AK22:AK23,AK19) -> 3047.6929
A25: Active annual users | B25: =SUM(B17:B18)+SUM(B20) -> 0 | C25: =SUM(B17:C18)+SUM(B20:C20) -> 0 | D25: =SUM(B17:D18)+SUM(B20:D20) -> 0 | E25: =SUM(B17:E18)+SUM(B20:E20) -> 59.960468 | F25: =SUM(B17:F18)+SUM(B20:F20) -> 119.95185 | G25: =SUM(B17:G18)+SUM(B20:G20) -> 179.97444 | H25: =SUM(B17:H18)+SUM(B20:H20) -> 286.42608 | I25: =SUM(B17:I18)+SUM(B20:I20) -> 392.90957 | J25: =SUM(B17:J18)+SUM(B20:J20) -> 499.42522 | K25: =SUM(B17:K18)+SUM(B20:K20) -> 585.00584 | L25: =SUM(B17:L18)+SUM(B20:L20) -> 670.65274 | M25: =SUM(B17:M18)+SUM(B20:M20) -> 756.36722 | N25: =SUM(C17:N18)+SUM(C20:N20) -> 844.75936 | O25: =SUM(D17:O18)+SUM(D20:O20) -> 933.22182 | P25: =SUM(E17:P18)+SUM(E20:P20) -> 1021.756 | Q25: =SUM(F17:Q18)+SUM(F20:Q20) -> 1077.3851 | R25: =SUM(G17:R18)+SUM(G20:R20) -> 1133.0719 | S25: =SUM(H17:S18)+SUM(H20:S20) -> 1188.8175 | T25: =SUM(I17:T18)+SUM(I20:T20) -> 1245.8906 | ... AK25: =SUM(Z17:AK18)+SUM(Z20:AK20) -> 2104.7881
A26: Total active AI users | B26: =SUM(B24:B25) -> 0 | C26: =SUM(C24:C25) -> 0 | D26: =SUM(D24:D25) -> 0 | E26: =SUM(E24:E25) -> 199.86823 | F26: =SUM(F24:F25) -> 388.64686 | G26: =SUM(G24:G25) -> 567.22658 | H26: =SUM(H24:H25) -> 891.08521 | I26: =SUM(I24:I25) -> 1197.6574 | ... AK26: =SUM(AK24:AK25) -> 5152.4809
A28: Monthly subscription revenue | B28: =B24*Assumptions!$C$29 -> 0 | C28: =C24*Assumptions!$C$29 -> 0 | D28: =D24*Assumptions!$C$29 -> 0 | E28: =E24*Assumptions!$C$29 -> 1259.1698 | F28: =F24*Assumptions!$C$29 -> 2418.2552 | G28: =G24*Assumptions!$C$29 -> 3485.2693 | H28: =H24*Assumptions!$C$29 -> 5441.9322 | I28: =I24*Assumptions!$C$29 -> 7242.7308 | ... AK28: =AK24*Assumptions!$C$29 -> 27429.236
A29: Founding annual bookings | B29: =B17*Assumptions!$C$31 -> 0 | C29: =C17*Assumptions!$C$31 -> 0 | D29: =D17*Assumptions!$C$31 -> 0 | E29: =E17*Assumptions!$C$31 -> 3102.2723 | F29: =F17*Assumptions!$C$31 -> 3104.405 | G29: =G17*Assumptions!$C$31 -> 3106.5591 | H29: =H17*Assumptions!$C$31 -> 3648.7347 | I29: =I17*Assumptions!$C$31 -> 3650.932 | ... AK29: =AK17*Assumptions!$C$31 -> 2542.6009
A30: Standard annual bookings | B30: =B18*Assumptions!$C$30 -> 0 | C30: =C18*Assumptions!$C$30 -> 0 | D30: =D18*Assumptions!$C$30 -> 0 | E30: =E18*Assumptions!$C$30 -> 1335 | F30: =F18*Assumptions!$C$30 -> 1335 | G30: =G18*Assumptions!$C$30 -> 1335 | H30: =H18*Assumptions!$C$30 -> 4767.8571 | I30: =I18*Assumptions!$C$30 -> 4767.8571 | ... AK30: =AK18*Assumptions!$C$30 -> 7151.7857
A31: Annual renewal bookings | B31: =B20*Assumptions!$C$30 -> 0 | C31: =C20*Assumptions!$C$30 -> 0 | D31: =D20*Assumptions!$C$30 -> 0 | E31: =E20*Assumptions!$C$30 -> 0 | F31: =F20*Assumptions!$C$30 -> 0 | G31: =G20*Assumptions!$C$30 -> 0 | H31: =H20*Assumptions!$C$30 -> 0 | I31: =I20*Assumptions!$C$30 -> 0 | ... AK31: =AK20*Assumptions!$C$30 -> 6191.9366
A32: Total AI revenue | B32: =SUM(B28:B31) -> 0 | C32: =SUM(C28:C31) -> 0 | D32: =SUM(D28:D31) -> 0 | E32: =SUM(E28:E31) -> 5696.4421 | F32: =SUM(F28:F31) -> 6857.6602 | G32: =SUM(G28:G31) -> 7926.8283 | H32: =SUM(H28:H31) -> 13858.524 | I32: =SUM(I28:I31) -> 15661.52 | ... AK32: =SUM(AK28:AK31) -> 43315.559
A34: Monthly contribution | B34: =B24*Assumptions!$C$37 -> 0 | C34: =C24*Assumptions!$C$37 -> 0 | D34: =D24*Assumptions!$C$37 -> 0 | E34: =E24*Assumptions!$C$37 -> 702.40576 | F34: =F24*Assumptions!$C$37 -> 1348.9811 | G34: =G24*Assumptions!$C$37 -> 1944.1962 | H34: =H24*Assumptions!$C$37 -> 3035.6862 | I34: =I24*Assumptions!$C$37 -> 4040.2301 | ... AK34: =AK24*Assumptions!$C$37 -> 15300.917
A35: Discounted annual contribution | B35: =B17*Assumptions!$C$39 -> 0 | C35: =C17*Assumptions!$C$39 -> 0 | D35: =D17*Assumptions!$C$39 -> 0 | E35: =E17*Assumptions!$C$39 -> 1410.7268 | F35: =F17*Assumptions!$C$39 -> 1411.6967 | G35: =G17*Assumptions!$C$39 -> 1412.6762 | H35: =H17*Assumptions!$C$39 -> 1659.225 | I35: =I17*Assumptions!$C$39 -> 1660.2243 | ... AK35: =AK17*Assumptions!$C$39 -> 1156.2219
A36: Standard + renewal annual contribution | B36: =SUM(B18,B20)*Assumptions!$C$38 -> 0 | C36: =SUM(C18,C20)*Assumptions!$C$38 -> 0 | D36: =SUM(D18,D20)*Assumptions!$C$38 -> 0 | E36: =SUM(E18,E20)*Assumptions!$C$38 -> 672.29508 | F36: =SUM(F18,F20)*Assumptions!$C$38 -> 672.29508 | G36: =SUM(G18,G20)*Assumptions!$C$38 -> 672.29508 | H36: =SUM(H18,H20)*Assumptions!$C$38 -> 2401.0539 | I36: =SUM(I18,I20)*Assumptions!$C$38 -> 2401.0539 | ... AK36: =SUM(AK18,AK20)*Assumptions!$C$38 -> 6719.7894
A37: AI contribution before acquisition | B37: =SUM(B34:B36) -> 0 | C37: =SUM(C34:C36) -> 0 | D37: =SUM(D34:D36) -> 0 | E37: =SUM(E34:E36) -> 2785.4277 | F37: =SUM(F34:F36) -> 3432.9729 | G37: =SUM(G34:G36) -> 4029.1675 | H37: =SUM(H34:H36) -> 7095.9651 | I37: =SUM(I34:I36) -> 8101.5082 | ... AK37: =SUM(AK34:AK36) -> 23176.928
A38: Direct AI acquisition spend | B38: =-B13 -> 0 | C38: =-C13 -> 0 | D38: =-D13 -> 0 | E38: =-E13 -> 0 | F38: =-F13 -> 0 | G38: =-G13 -> 0 | H38: =-H13 -> -4000 | I38: =-I13 -> -4000 | ... AK38: =-AK13 -> -6000
A39: AI contribution after acquisition | B39: =SUM(B37:B38) -> 0 | C39: =SUM(C37:C38) -> 0 | D39: =SUM(D37:D38) -> 0 | E39: =SUM(E37:E38) -> 2785.4277 | F39: =SUM(F37:F38) -> 3432.9729 | G39: =SUM(G37:G38) -> 4029.1675 | H39: =SUM(H37:H38) -> 3095.9651 | I39: =SUM(I37:I38) -> 4101.5082 | ... AK39: =SUM(AK37:AK38) -> 17176.928
A41: AI recurring revenue run-rate / month | B41: =B24*Assumptions!$C$29+B25*Assumptions!$C$30/12 -> 0 | C41: =C24*Assumptions!$C$29+C25*Assumptions!$C$30/12 -> 0 | D41: =D24*Assumptions!$C$29+D25*Assumptions!$C$30/12 -> 0 | E41: =E24*Assumptions!$C$29+E25*Assumptions!$C$30/12 -> 1703.8766 | F41: =F24*Assumptions!$C$29+F25*Assumptions!$C$30/12 -> 3307.898 | G41: =G24*Assumptions!$C$29+G25*Assumptions!$C$30/12 -> 4820.0797 | H41: =H24*Assumptions!$C$29+H25*Assumptions!$C$30/12 -> 7566.259 | I41: =I24*Assumptions!$C$29+I25*Assumptions!$C$30/12 -> 10156.81 | ... AK41: =AK24*Assumptions!$C$29+AK25*Assumptions!$C$30/12 -> 43039.747
A42: AI annualized revenue run-rate | B42: =B41*12 -> 0 | C42: =C41*12 -> 0 | D42: =D41*12 -> 0 | E42: =E41*12 -> 20446.52 | F42: =F41*12 -> 39694.776 | G42: =G41*12 -> 57840.956 | H42: =H41*12 -> 90795.107 | I42: =I41*12 -> 121881.72 | ... AK42: =AK41*12 -> 516476.97
A43: Cumulative AI customers acquired | B43: =B15 -> 0 | C43: =B43+C15 -> 0 | D43: =C43+D15 -> 0 | E43: =D43+E15 -> 199.86823 | F43: =E43+F15 -> 399.83948 | G43: =F43+G15 -> 599.9148 | H43: =G43+H15 -> 954.75361 | I43: =H43+I15 -> 1309.6986 | J43: =I43+J15 -> 1664.7507 | ... AK43: =AJ43+AK15 -> 11275.009

Sheet Growth Extensions
A1: TUPENSACI | Growth Extensions
A2: Operating case: relaunch the three existing workbooks and introduce one new workbook every year, plus early B2B pilots. Toggle On/Off in Assumptions!E6.
A5: Month | B5: M1 | C5: M2 | D5: M3 | E5: M4 | F5: M5 | G5: M6 | H5: M7 | I5: M8 | J5: M9 | K5: M10 | L5: M11 | M5: M12 | N5: M13 | O5: M14 | P5: M15 | Q5: M16 | R5: M17 | S5: M18 | T5: M19 | U5: M20 | V5: M21 | W5: M22 | X5: M23 | Y5: M24 | Z5: M25 | AA5: M26 | AB5: M27 | AC5: M28 | AD5: M29 | AE5: M30 | AF5: M31 | AG5: M32 | AH5: M33 | AI5: M34 | AJ5: M35 | AK5: M36
A6: Year | B6: Y1 | C6: Y1 | D6: Y1 | E6: Y1 | F6: Y1 | G6: Y1 | H6: Y1 | I6: Y1 | J6: Y1 | K6: Y1 | L6: Y1 | M6: Y1 | N6: Y2 | O6: Y2 | P6: Y2 | Q6: Y2 | R6: Y2 | S6: Y2 | T6: Y2 | U6: Y2 | V6: Y2 | W6: Y2 | X6: Y2 | Y6: Y2 | Z6: Y3 | AA6: Y3 | AB6: Y3 | AC6: Y3 | AD6: Y3 | AE6: Y3 | AF6: Y3 | AG6: Y3 | AH6: Y3 | AI6: Y3 | AJ6: Y3 | AK6: Y3
A7: Stage | B7: Relaunch | C7: Relaunch | D7: Relaunch | E7: Beta build | F7: Beta build | G7: Gate M6 | H7: AI launch | I7: AI launch | J7: AI launch | K7: Scale test | L7: Scale test | M7: Scale test | N7: Scale | O7: Scale | P7: Scale | Q7: Scale | R7: Scale | S7: Scale | T7: Scale | U7: Scale | V7: Scale | W7: Scale | X7: Scale | Y7: Scale | Z7: Scale | AA7: Scale | AB7: Scale | AC7: Scale | AD7: Scale | AE7: Scale | AF7: Scale | AG7: Scale | AH7: Scale | AI7: Scale | AJ7: Scale | AK7: Scale
A9: NEW WORKBOOK + B2B OPERATING CASE
A10: New workbook organic orders | B10: =IF(Assumptions!$E$6="Off",0,Assumptions!$C$76*(IF(1>=Assumptions!$C$71,1,0)+IF(1>=Assumptions!$C$72,1,0)+IF(1>=Assumptions!$C$73,1,0))) -> 0 | C10: =IF(Assumptions!$E$6="Off",0,Assumptions!$C$76*(IF(2>=Assumptions!$C$71,1,0)+IF(2>=Assumptions!$C$72,1,0)+IF(2>=Assumptions!$C$73,1,0))) -> 0 | D10: =IF(Assumptions!$E$6="Off",0,Assumptions!$C$76*(IF(3>=Assumptions!$C$71,1,0)+IF(3>=Assumptions!$C$72,1,0)+IF(3>=Assumptions!$C$73,1,0))) -> 0 | E10: =IF(Assumptions!$E$6="Off",0,Assumptions!$C$76*(IF(4>=Assumptions!$C$71,1,0)+IF(4>=Assumptions!$C$72,1,0)+IF(4>=Assumptions!$C$73,1,0))) -> 0 | F10: =IF(Assumptions!$E$6="Off",0,Assumptions!$C$76*(IF(5>=Assumptions!$C$71,1,0)+IF(5>=Assumptions!$C$72,1,0)+IF(5>=Assumptions!$C$73,1,0))) -> 0 | G10: =IF(Assumptions!$E$6="Off",0,Assumptions!$C$76*(IF(6>=Assumptions!$C$71,1,0)+IF(6>=Assumptions!$C$72,1,0)+IF(6>=Assumptions!$C$73,1,0))) -> 0 | H10: =IF(Assumptions!$E$6="Off",0,Assumptions!$C$76*(IF(7>=Assumptions!$C$71,1,0)+IF(7>=Assumptions!$C$72,1,0)+IF(7>=Assumptions!$C$73,1,0))) -> 0 | I10: =IF(Assumptions!$E$6="Off",0,Assumptions!$C$76*(IF(8>=Assumptions!$C$71,1,0)+IF(8>=Assumptions!$C$72,1,0)+IF(8>=Assumptions!$C$73,1,0))) -> 0 | J10: =IF(Assumptions!$E$6="Off",0,Assumptions!$C$76*(IF(9>=Assumptions!$C$71,1,0)+IF(9>=Assumptions!$C$72,1,0)+IF(9>=Assumptions!$C$73,1,0))) -> 100 | K10: =IF(Assumptions!$E$6="Off",0,Assumptions!$C$76*(IF(10>=Assumptions!$C$71,1,0)+IF(10>=Assumptions!$C$72,1,0)+IF(10>=Assumptions!$C$73,1,0))) -> 100 | L10: =IF(Assumptions!$E$6="Off",0,Assumptions!$C$76*(IF(11>=Assumptions!$C$71,1,0)+IF(11>=Assumptions!$C$72,1,0)+IF(11>=Assumptions!$C$73,1,0))) -> 100 | M10: =IF(Assumptions!$E$6="Off",0,Assumptions!$C$76*(IF(12>=Assumptions!$C$71,1,0)+IF(12>=Assumptions!$C$72,1,0)+IF(12>=Assumptions!$C$73,1,0))) -> 100 | N10: =IF(Assumptions!$E$6="Off",0,Assumptions!$C$76*(IF(13>=Assumptions!$C$71,1,0)+IF(13>=Assumptions!$C$72,1,0)+IF(13>=Assumptions!$C$73,1,0))) -> 100 | O10: =IF(Assumptions!$E$6="Off",0,Assumptions!$C$76*(IF(14>=Assumptions!$C$71,1,0)+IF(14>=Assumptions!$C$72,1,0)+IF(14>=Assumptions!$C$73,1,0))) -> 100 | P10: =IF(Assumptions!$E$6="Off",0,Assumptions!$C$76*(IF(15>=Assumptions!$C$71,1,0)+IF(15>=Assumptions!$C$72,1,0)+IF(15>=Assumptions!$C$73,1,0))) -> 100 | Q10: =IF(Assumptions!$E$6="Off",0,Assumptions!$C$76*(IF(16>=Assumptions!$C$71,1,0)+IF(16>=Assumptions!$C$72,1,0)+IF(16>=Assumptions!$C$73,1,0))) -> 100 | R10: =IF(Assumptions!$E$6="Off",0,Assumptions!$C$76*(IF(17>=Assumptions!$C$71,1,0)+IF(17>=Assumptions!$C$72,1,0)+IF(17>=Assumptions!$C$73,1,0))) -> 100 | S10: =IF(Assumptions!$E$6="Off",0,Assumptions!$C$76*(IF(18>=Assumptions!$C$71,1,0)+IF(18>=Assumptions!$C$72,1,0)+IF(18>=Assumptions!$C$73,1,0))) -> 100 | T10: =IF(Assumptions!$E$6="Off",0,Assumptions!$C$76*(IF(19>=Assumptions!$C$71,1,0)+IF(19>=Assumptions!$C$72,1,0)+IF(19>=Assumptions!$C$73,1,0))) -> 100 | U10: =IF(Assumptions!$E$6="Off",0,Assumptions!$C$76*(IF(20>=Assumptions!$C$71,1,0)+IF(20>=Assumptions!$C$72,1,0)+IF(20>=Assumptions!$C$73,1,0))) -> 100 | V10: =IF(Assumptions!$E$6="Off",0,Assumptions!$C$76*(IF(21>=Assumptions!$C$71,1,0)+IF(21>=Assumptions!$C$72,1,0)+IF(21>=Assumptions!$C$73,1,0))) -> 200 | W10: =IF(Assumptions!$E$6="Off",0,Assumptions!$C$76*(IF(22>=Assumptions!$C$71,1,0)+IF(22>=Assumptions!$C$72,1,0)+IF(22>=Assumptions!$C$73,1,0))) -> 200 | X10: =IF(Assumptions!$E$6="Off",0,Assumptions!$C$76*(IF(23>=Assumptions!$C$71,1,0)+IF(23>=Assumptions!$C$72,1,0)+IF(23>=Assumptions!$C$73,1,0))) -> 200 | Y10: =IF(Assumptions!$E$6="Off",0,Assumptions!$C$76*(IF(24>=Assumptions!$C$71,1,0)+IF(24>=Assumptions!$C$72,1,0)+IF(24>=Assumptions!$C$73,1,0))) -> 200 | Z10: =IF(Assumptions!$E$6="Off",0,Assumptions!$C$76*(IF(25>=Assumptions!$C$71,1,0)+IF(25>=Assumptions!$C$72,1,0)+IF(25>=Assumptions!$C$73,1,0))) -> 200 | AA10: =IF(Assumptions!$E$6="Off",0,Assumptions!$C$76*(IF(26>=Assumptions!$C$71,1,0)+IF(26>=Assumptions!$C$72,1,0)+IF(26>=Assumptions!$C$73,1,0))) -> 200 | AB10: =IF(Assumptions!$E$6="Off",0,Assumptions!$C$76*(IF(27>=Assumptions!$C$71,1,0)+IF(27>=Assumptions!$C$72,1,0)+IF(27>=Assumptions!$C$73,1,0))) -> 200 | AC10: =IF(Assumptions!$E$6="Off",0,Assumptions!$C$76*(IF(28>=Assumptions!$C$71,1,0)+IF(28>=Assumptions!$C$72,1,0)+IF(28>=Assumptions!$C$73,1,0))) -> 200 | AD10: =IF(Assumptions!$E$6="Off",0,Assumptions!$C$76*(IF(29>=Assumptions!$C$71,1,0)+IF(29>=Assumptions!$C$72,1,0)+IF(29>=Assumptions!$C$73,1,0))) -> 200 | AE10: =IF(Assumptions!$E$6="Off",0,Assumptions!$C$76*(IF(30>=Assumptions!$C$71,1,0)+IF(30>=Assumptions!$C$72,1,0)+IF(30>=Assumptions!$C$73,1,0))) -> 200 | AF10: =IF(Assumptions!$E$6="Off",0,Assumptions!$C$76*(IF(31>=Assumptions!$C$71,1,0)+IF(31>=Assumptions!$C$72,1,0)+IF(31>=Assumptions!$C$73,1,0))) -> 200 | AG10: =IF(Assumptions!$E$6="Off",0,Assumptions!$C$76*(IF(32>=Assumptions!$C$71,1,0)+IF(32>=Assumptions!$C$72,1,0)+IF(32>=Assumptions!$C$73,1,0))) -> 200 | AH10: =IF(Assumptions!$E$6="Off",0,Assumptions!$C$76*(IF(33>=Assumptions!$C$71,1,0)+IF(33>=Assumptions!$C$72,1,0)+IF(33>=Assumptions!$C$73,1,0))) -> 300 | AI10: =IF(Assumptions!$E$6="Off",0,Assumptions!$C$76*(IF(34>=Assumptions!$C$71,1,0)+IF(34>=Assumptions!$C$72,1,0)+IF(34>=Assumptions!$C$73,1,0))) -> 300 | AJ10: =IF(Assumptions!$E$6="Off",0,Assumptions!$C$76*(IF(35>=Assumptions!$C$71,1,0)+IF(35>=Assumptions!$C$72,1,0)+IF(35>=Assumptions!$C$73,1,0))) -> 300 | AK10: =IF(Assumptions!$E$6="Off",0,Assumptions!$C$76*(IF(36>=Assumptions!$C$71,1,0)+IF(36>=Assumptions!$C$72,1,0)+IF(36>=Assumptions!$C$73,1,0))) -> 300
A11: New workbook net revenue | B11: =B10*Assumptions!$C$40 -> 0 | C11: =C10*Assumptions!$C$40 -> 0 | D11: =D10*Assumptions!$C$40 -> 0 | E11: =E10*Assumptions!$C$40 -> 0 | F11: =F10*Assumptions!$C$40 -> 0 | G11: =G10*Assumptions!$C$40 -> 0 | H11: =H10*Assumptions!$C$40 -> 0 | I11: =I10*Assumptions!$C$40 -> 0 | ... AK11: =AK10*Assumptions!$C$40 -> 9600
A12: New workbook print + fulfillment | B12: =-B10*Assumptions!$C$41 -> 0 | C12: =-C10*Assumptions!$C$41 -> 0 | D12: =-D10*Assumptions!$C$41 -> 0 | E12: =-E10*Assumptions!$C$41 -> 0 | F12: =-F10*Assumptions!$C$41 -> 0 | G12: =-G10*Assumptions!$C$41 -> 0 | H12: =-H10*Assumptions!$C$41 -> 0 | I12: =-I10*Assumptions!$C$41 -> 0 | ... AK12: =-AK10*Assumptions!$C$41 -> -3600
A13: New workbook contribution | B13: =SUM(B11:B12) -> 0 | C13: =SUM(C11:C12) -> 0 | D13: =SUM(D11:D12) -> 0 | E13: =SUM(E11:E12) -> 0 | F13: =SUM(F11:F12) -> 0 | G13: =SUM(G11:G12) -> 0 | H13: =SUM(H11:H12) -> 0 | I13: =SUM(I11:I12) -> 0 | ... AK13: =SUM(AK11:AK12) -> 6000
A15: B2B pilot revenue | B15: =IF(Assumptions!$E$6="Off",0,IF(1<Assumptions!$C$77,0,IF(1<13,Assumptions!$C$78,IF(1<25,Assumptions!$C$79,Assumptions!$C$80)))) -> 0 | C15: =IF(Assumptions!$E$6="Off",0,IF(2<Assumptions!$C$77,0,IF(2<13,Assumptions!$C$78,IF(2<25,Assumptions!$C$79,Assumptions!$C$80)))) -> 0 | D15: =IF(Assumptions!$E$6="Off",0,IF(3<Assumptions!$C$77,0,IF(3<13,Assumptions!$C$78,IF(3<25,Assumptions!$C$79,Assumptions!$C$80)))) -> 0 | E15: =IF(Assumptions!$E$6="Off",0,IF(4<Assumptions!$C$77,0,IF(4<13,Assumptions!$C$78,IF(4<25,Assumptions!$C$79,Assumptions!$C$80)))) -> 0 | F15: =IF(Assumptions!$E$6="Off",0,IF(5<Assumptions!$C$77,0,IF(5<13,Assumptions!$C$78,IF(5<25,Assumptions!$C$79,Assumptions!$C$80)))) -> 0 | G15: =IF(Assumptions!$E$6="Off",0,IF(6<Assumptions!$C$77,0,IF(6<13,Assumptions!$C$78,IF(6<25,Assumptions!$C$79,Assumptions!$C$80)))) -> 0 | H15: =IF(Assumptions!$E$6="Off",0,IF(7<Assumptions!$C$77,0,IF(7<13,Assumptions!$C$78,IF(7<25,Assumptions!$C$79,Assumptions!$C$80)))) -> 0 | I15: =IF(Assumptions!$E$6="Off",0,IF(8<Assumptions!$C$77,0,IF(8<13,Assumptions!$C$78,IF(8<25,Assumptions!$C$79,Assumptions!$C$80)))) -> 0 | J15: =IF(Assumptions!$E$6="Off",0,IF(9<Assumptions!$C$77,0,IF(9<13,Assumptions!$C$78,IF(9<25,Assumptions!$C$79,Assumptions!$C$80)))) -> 2500 | K15: =IF(Assumptions!$E$6="Off",0,IF(10<Assumptions!$C$77,0,IF(10<13,Assumptions!$C$78,IF(10<25,Assumptions!$C$79,Assumptions!$C$80)))) -> 2500 | L15: =IF(Assumptions!$E$6="Off",0,IF(11<Assumptions!$C$77,0,IF(11<13,Assumptions!$C$78,IF(11<25,Assumptions!$C$79,Assumptions!$C$80)))) -> 2500 | M15: =IF(Assumptions!$E$6="Off",0,IF(12<Assumptions!$C$77,0,IF(12<13,Assumptions!$C$78,IF(12<25,Assumptions!$C$79,Assumptions!$C$80)))) -> 2500 | N15: =IF(Assumptions!$E$6="Off",0,IF(13<Assumptions!$C$77,0,IF(13<13,Assumptions!$C$78,IF(13<25,Assumptions!$C$79,Assumptions!$C$80)))) -> 1666.67 | O15: =IF(Assumptions!$E$6="Off",0,IF(14<Assumptions!$C$77,0,IF(14<13,Assumptions!$C$78,IF(14<25,Assumptions!$C$79,Assumptions!$C$80)))) -> 1666.67 | P15: =IF(Assumptions!$E$6="Off",0,IF(15<Assumptions!$C$77,0,IF(15<13,Assumptions!$C$78,IF(15<25,Assumptions!$C$79,Assumptions!$C$80)))) -> 1666.67 | Q15: =IF(Assumptions!$E$6="Off",0,IF(16<Assumptions!$C$77,0,IF(16<13,Assumptions!$C$78,IF(16<25,Assumptions!$C$79,Assumptions!$C$80)))) -> 1666.67 | R15: =IF(Assumptions!$E$6="Off",0,IF(17<Assumptions!$C$77,0,IF(17<13,Assumptions!$C$78,IF(17<25,Assumptions!$C$79,Assumptions!$C$80)))) -> 1666.67 | S15: =IF(Assumptions!$E$6="Off",0,IF(18<Assumptions!$C$77,0,IF(18<13,Assumptions!$C$78,IF(18<25,Assumptions!$C$79,Assumptions!$C$80)))) -> 1666.67 | T15: =IF(Assumptions!$E$6="Off",0,IF(19<Assumptions!$C$77,0,IF(19<13,Assumptions!$C$78,IF(19<25,Assumptions!$C$79,Assumptions!$C$80)))) -> 1666.67 | U15: =IF(Assumptions!$E$6="Off",0,IF(20<Assumptions!$C$77,0,IF(20<13,Assumptions!$C$78,IF(20<25,Assumptions!$C$79,Assumptions!$C$80)))) -> 1666.67 | V15: =IF(Assumptions!$E$6="Off",0,IF(21<Assumptions!$C$77,0,IF(21<13,Assumptions!$C$78,IF(21<25,Assumptions!$C$79,Assumptions!$C$80)))) -> 1666.67 | W15: =IF(Assumptions!$E$6="Off",0,IF(22<Assumptions!$C$77,0,IF(22<13,Assumptions!$C$78,IF(22<25,Assumptions!$C$79,Assumptions!$C$80)))) -> 1666.67 | X15: =IF(Assumptions!$E$6="Off",0,IF(23<Assumptions!$C$77,0,IF(23<13,Assumptions!$C$78,IF(23<25,Assumptions!$C$79,Assumptions!$C$80)))) -> 1666.67 | Y15: =IF(Assumptions!$E$6="Off",0,IF(24<Assumptions!$C$77,0,IF(24<13,Assumptions!$C$78,IF(24<25,Assumptions!$C$79,Assumptions!$C$80)))) -> 1666.67 | Z15: =IF(Assumptions!$E$6="Off",0,IF(25<Assumptions!$C$77,0,IF(25<13,Assumptions!$C$78,IF(25<25,Assumptions!$C$79,Assumptions!$C$80)))) -> 2500 | AA15: =IF(Assumptions!$E$6="Off",0,IF(26<Assumptions!$C$77,0,IF(26<13,Assumptions!$C$78,IF(26<25,Assumptions!$C$79,Assumptions!$C$80)))) -> 2500 | AB15: =IF(Assumptions!$E$6="Off",0,IF(27<Assumptions!$C$77,0,IF(27<13,Assumptions!$C$78,IF(27<25,Assumptions!$C$79,Assumptions!$C$80)))) -> 2500 | AC15: =IF(Assumptions!$E$6="Off",0,IF(28<Assumptions!$C$77,0,IF(28<13,Assumptions!$C$78,IF(28<25,Assumptions!$C$79,Assumptions!$C$80)))) -> 2500 | AD15: =IF(Assumptions!$E$6="Off",0,IF(29<Assumptions!$C$77,0,IF(29<13,Assumptions!$C$78,IF(29<25,Assumptions!$C$79,Assumptions!$C$80)))) -> 2500 | AE15: =IF(Assumptions!$E$6="Off",0,IF(30<Assumptions!$C$77,0,IF(30<13,Assumptions!$C$78,IF(30<25,Assumptions!$C$79,Assumptions!$C$80)))) -> 2500 | AF15: =IF(Assumptions!$E$6="Off",0,IF(31<Assumptions!$C$77,0,IF(31<13,Assumptions!$C$78,IF(31<25,Assumptions!$C$79,Assumptions!$C$80)))) -> 2500 | AG15: =IF(Assumptions!$E$6="Off",0,IF(32<Assumptions!$C$77,0,IF(32<13,Assumptions!$C$78,IF(32<25,Assumptions!$C$79,Assumptions!$C$80)))) -> 2500 | AH15: =IF(Assumptions!$E$6="Off",0,IF(33<Assumptions!$C$77,0,IF(33<13,Assumptions!$C$78,IF(33<25,Assumptions!$C$79,Assumptions!$C$80)))) -> 2500 | AI15: =IF(Assumptions!$E$6="Off",0,IF(34<Assumptions!$C$77,0,IF(34<13,Assumptions!$C$78,IF(34<25,Assumptions!$C$79,Assumptions!$C$80)))) -> 2500 | AJ15: =IF(Assumptions!$E$6="Off",0,IF(35<Assumptions!$C$77,0,IF(35<13,Assumptions!$C$78,IF(35<25,Assumptions!$C$79,Assumptions!$C$80)))) -> 2500 | AK15: =IF(Assumptions!$E$6="Off",0,IF(36<Assumptions!$C$77,0,IF(36<13,Assumptions!$C$78,IF(36<25,Assumptions!$C$79,Assumptions!$C$80)))) -> 2500
A16: B2B direct delivery cost | B16: =-B15*(1-Assumptions!$C$81) -> 0 | C16: =-C15*(1-Assumptions!$C$81) -> 0 | D16: =-D15*(1-Assumptions!$C$81) -> 0 | E16: =-E15*(1-Assumptions!$C$81) -> 0 | F16: =-F15*(1-Assumptions!$C$81) -> 0 | G16: =-G15*(1-Assumptions!$C$81) -> 0 | H16: =-H15*(1-Assumptions!$C$81) -> 0 | I16: =-I15*(1-Assumptions!$C$81) -> 0 | ... AK16: =-AK15*(1-Assumptions!$C$81) -> -1500
A17: B2B gross profit | B17: =SUM(B15:B16) -> 0 | C17: =SUM(C15:C16) -> 0 | D17: =SUM(D15:D16) -> 0 | E17: =SUM(E15:E16) -> 0 | F17: =SUM(F15:F16) -> 0 | G17: =SUM(G15:G16) -> 0 | H17: =SUM(H15:H16) -> 0 | I17: =SUM(I15:I16) -> 0 | ... AK17: =SUM(AK15:AK16) -> 1000
A19: New workbook launch investment | B19: =IF(Assumptions!$E$6="Off",0,-Assumptions!$C$74/Assumptions!$C$75*(IF(AND(1>=Assumptions!$C$71-Assumptions!$C$75,1<Assumptions!$C$71),1,0)+IF(AND(1>=Assumptions!$C$72-Assumptions!$C$75,1<Assumptions!$C$72),1,0)+IF(AND(1>=Assumptions!$C$73-Assumptions!$C$75,1<Assumptions!$C$73),1,0))) -> 0 | C19: =IF(Assumptions!$E$6="Off",0,-Assumptions!$C$74/Assumptions!$C$75*(IF(AND(2>=Assumptions!$C$71-Assumptions!$C$75,2<Assumptions!$C$71),1,0)+IF(AND(2>=Assumptions!$C$72-Assumptions!$C$75,2<Assumptions!$C$72),1,0)+IF(AND(2>=Assumptions!$C$73-Assumptions!$C$75,2<Assumptions!$C$73),1,0))) -> 0 | D19: =IF(Assumptions!$E$6="Off",0,-Assumptions!$C$74/Assumptions!$C$75*(IF(AND(3>=Assumptions!$C$71-Assumptions!$C$75,3<Assumptions!$C$71),1,0)+IF(AND(3>=Assumptions!$C$72-Assumptions!$C$75,3<Assumptions!$C$72),1,0)+IF(AND(3>=Assumptions!$C$73-Assumptions!$C$75,3<Assumptions!$C$73),1,0))) -> -2500 | E19: =IF(Assumptions!$E$6="Off",0,-Assumptions!$C$74/Assumptions!$C$75*(IF(AND(4>=Assumptions!$C$71-Assumptions!$C$75,4<Assumptions!$C$71),1,0)+IF(AND(4>=Assumptions!$C$72-Assumptions!$C$75,4<Assumptions!$C$72),1,0)+IF(AND(4>=Assumptions!$C$73-Assumptions!$C$75,4<Assumptions!$C$73),1,0))) -> -2500 | F19: =IF(Assumptions!$E$6="Off",0,-Assumptions!$C$74/Assumptions!$C$75*(IF(AND(5>=Assumptions!$C$71-Assumptions!$C$75,5<Assumptions!$C$71),1,0)+IF(AND(5>=Assumptions!$C$72-Assumptions!$C$75,5<Assumptions!$C$72),1,0)+IF(AND(5>=Assumptions!$C$73-Assumptions!$C$75,5<Assumptions!$C$73),1,0))) -> -2500 | G19: =IF(Assumptions!$E$6="Off",0,-Assumptions!$C$74/Assumptions!$C$75*(IF(AND(6>=Assumptions!$C$71-Assumptions!$C$75,6<Assumptions!$C$71),1,0)+IF(AND(6>=Assumptions!$C$72-Assumptions!$C$75,6<Assumptions!$C$72),1,0)+IF(AND(6>=Assumptions!$C$73-Assumptions!$C$75,6<Assumptions!$C$73),1,0))) -> -2500 | H19: =IF(Assumptions!$E$6="Off",0,-Assumptions!$C$74/Assumptions!$C$75*(IF(AND(7>=Assumptions!$C$71-Assumptions!$C$75,7<Assumptions!$C$71),1,0)+IF(AND(7>=Assumptions!$C$72-Assumptions!$C$75,7<Assumptions!$C$72),1,0)+IF(AND(7>=Assumptions!$C$73-Assumptions!$C$75,7<Assumptions!$C$73),1,0))) -> -2500 | I19: =IF(Assumptions!$E$6="Off",0,-Assumptions!$C$74/Assumptions!$C$75*(IF(AND(8>=Assumptions!$C$71-Assumptions!$C$75,8<Assumptions!$C$71),1,0)+IF(AND(8>=Assumptions!$C$72-Assumptions!$C$75,8<Assumptions!$C$72),1,0)+IF(AND(8>=Assumptions!$C$73-Assumptions!$C$75,8<Assumptions!$C$73),1,0))) -> -2500 | J19: =IF(Assumptions!$E$6="Off",0,-Assumptions!$C$74/Assumptions!$C$75*(IF(AND(9>=Assumptions!$C$71-Assumptions!$C$75,9<Assumptions!$C$71),1,0)+IF(AND(9>=Assumptions!$C$72-Assumptions!$C$75,9<Assumptions!$C$72),1,0)+IF(AND(9>=Assumptions!$C$73-Assumptions!$C$75,9<Assumptions!$C$73),1,0))) -> 0 | K19: =IF(Assumptions!$E$6="Off",0,-Assumptions!$C$74/Assumptions!$C$75*(IF(AND(10>=Assumptions!$C$71-Assumptions!$C$75,10<Assumptions!$C$71),1,0)+IF(AND(10>=Assumptions!$C$72-Assumptions!$C$75,10<Assumptions!$C$72),1,0)+IF(AND(10>=Assumptions!$C$73-Assumptions!$C$75,10<Assumptions!$C$73),1,0))) -> 0 | L19: =IF(Assumptions!$E$6="Off",0,-Assumptions!$C$74/Assumptions!$C$75*(IF(AND(11>=Assumptions!$C$71-Assumptions!$C$75,11<Assumptions!$C$71),1,0)+IF(AND(11>=Assumptions!$C$72-Assumptions!$C$75,11<Assumptions!$C$72),1,0)+IF(AND(11>=Assumptions!$C$73-Assumptions!$C$75,11<Assumptions!$C$73),1,0))) -> 0 | M19: =IF(Assumptions!$E$6="Off",0,-Assumptions!$C$74/Assumptions!$C$75*(IF(AND(12>=Assumptions!$C$71-Assumptions!$C$75,12<Assumptions!$C$71),1,0)+IF(AND(12>=Assumptions!$C$72-Assumptions!$C$75,12<Assumptions!$C$72),1,0)+IF(AND(12>=Assumptions!$C$73-Assumptions!$C$75,12<Assumptions!$C$73),1,0))) -> 0 | N19: =IF(Assumptions!$E$6="Off",0,-Assumptions!$C$74/Assumptions!$C$75*(IF(AND(13>=Assumptions!$C$71-Assumptions!$C$75,13<Assumptions!$C$71),1,0)+IF(AND(13>=Assumptions!$C$72-Assumptions!$C$75,13<Assumptions!$C$72),1,0)+IF(AND(13>=Assumptions!$C$73-Assumptions!$C$75,13<Assumptions!$C$73),1,0))) -> 0 | O19: =IF(Assumptions!$E$6="Off",0,-Assumptions!$C$74/Assumptions!$C$75*(IF(AND(14>=Assumptions!$C$71-Assumptions!$C$75,14<Assumptions!$C$71),1,0)+IF(AND(14>=Assumptions!$C$72-Assumptions!$C$75,14<Assumptions!$C$72),1,0)+IF(AND(14>=Assumptions!$C$73-Assumptions!$C$75,14<Assumptions!$C$73),1,0))) -> 0 | P19: =IF(Assumptions!$E$6="Off",0,-Assumptions!$C$74/Assumptions!$C$75*(IF(AND(15>=Assumptions!$C$71-Assumptions!$C$75,15<Assumptions!$C$71),1,0)+IF(AND(15>=Assumptions!$C$72-Assumptions!$C$75,15<Assumptions!$C$72),1,0)+IF(AND(15>=Assumptions!$C$73-Assumptions!$C$75,15<Assumptions!$C$73),1,0))) -> -2500 | Q19: =IF(Assumptions!$E$6="Off",0,-Assumptions!$C$74/Assumptions!$C$75*(IF(AND(16>=Assumptions!$C$71-Assumptions!$C$75,16<Assumptions!$C$71),1,0)+IF(AND(16>=Assumptions!$C$72-Assumptions!$C$75,16<Assumptions!$C$72),1,0)+IF(AND(16>=Assumptions!$C$73-Assumptions!$C$75,16<Assumptions!$C$73),1,0))) -> -2500 | R19: =IF(Assumptions!$E$6="Off",0,-Assumptions!$C$74/Assumptions!$C$75*(IF(AND(17>=Assumptions!$C$71-Assumptions!$C$75,17<Assumptions!$C$71),1,0)+IF(AND(17>=Assumptions!$C$72-Assumptions!$C$75,17<Assumptions!$C$72),1,0)+IF(AND(17>=Assumptions!$C$73-Assumptions!$C$75,17<Assumptions!$C$73),1,0))) -> -2500 | S19: =IF(Assumptions!$E$6="Off",0,-Assumptions!$C$74/Assumptions!$C$75*(IF(AND(18>=Assumptions!$C$71-Assumptions!$C$75,18<Assumptions!$C$71),1,0)+IF(AND(18>=Assumptions!$C$72-Assumptions!$C$75,18<Assumptions!$C$72),1,0)+IF(AND(18>=Assumptions!$C$73-Assumptions!$C$75,18<Assumptions!$C$73),1,0))) -> -2500 | T19: =IF(Assumptions!$E$6="Off",0,-Assumptions!$C$74/Assumptions!$C$75*(IF(AND(19>=Assumptions!$C$71-Assumptions!$C$75,19<Assumptions!$C$71),1,0)+IF(AND(19>=Assumptions!$C$72-Assumptions!$C$75,19<Assumptions!$C$72),1,0)+IF(AND(19>=Assumptions!$C$73-Assumptions!$C$75,19<Assumptions!$C$73),1,0))) -> -2500 | U19: =IF(Assumptions!$E$6="Off",0,-Assumptions!$C$74/Assumptions!$C$75*(IF(AND(20>=Assumptions!$C$71-Assumptions!$C$75,20<Assumptions!$C$71),1,0)+IF(AND(20>=Assumptions!$C$72-Assumptions!$C$75,20<Assumptions!$C$72),1,0)+IF(AND(20>=Assumptions!$C$73-Assumptions!$C$75,20<Assumptions!$C$73),1,0))) -> -2500 | V19: =IF(Assumptions!$E$6="Off",0,-Assumptions!$C$74/Assumptions!$C$75*(IF(AND(21>=Assumptions!$C$71-Assumptions!$C$75,21<Assumptions!$C$71),1,0)+IF(AND(21>=Assumptions!$C$72-Assumptions!$C$75,21<Assumptions!$C$72),1,0)+IF(AND(21>=Assumptions!$C$73-Assumptions!$C$75,21<Assumptions!$C$73),1,0))) -> 0 | W19: =IF(Assumptions!$E$6="Off",0,-Assumptions!$C$74/Assumptions!$C$75*(IF(AND(22>=Assumptions!$C$71-Assumptions!$C$75,22<Assumptions!$C$71),1,0)+IF(AND(22>=Assumptions!$C$72-Assumptions!$C$75,22<Assumptions!$C$72),1,0)+IF(AND(22>=Assumptions!$C$73-Assumptions!$C$75,22<Assumptions!$C$73),1,0))) -> 0 | X19: =IF(Assumptions!$E$6="Off",0,-Assumptions!$C$74/Assumptions!$C$75*(IF(AND(23>=Assumptions!$C$71-Assumptions!$C$75,23<Assumptions!$C$71),1,0)+IF(AND(23>=Assumptions!$C$72-Assumptions!$C$75,23<Assumptions!$C$72),1,0)+IF(AND(23>=Assumptions!$C$73-Assumptions!$C$75,23<Assumptions!$C$73),1,0))) -> 0 | Y19: =IF(Assumptions!$E$6="Off",0,-Assumptions!$C$74/Assumptions!$C$75*(IF(AND(24>=Assumptions!$C$71-Assumptions!$C$75,24<Assumptions!$C$71),1,0)+IF(AND(24>=Assumptions!$C$72-Assumptions!$C$75,24<Assumptions!$C$72),1,0)+IF(AND(24>=Assumptions!$C$73-Assumptions!$C$75,24<Assumptions!$C$73),1,0))) -> 0 | Z19: =IF(Assumptions!$E$6="Off",0,-Assumptions!$C$74/Assumptions!$C$75*(IF(AND(25>=Assumptions!$C$71-Assumptions!$C$75,25<Assumptions!$C$71),1,0)+IF(AND(25>=Assumptions!$C$72-Assumptions!$C$75,25<Assumptions!$C$72),1,0)+IF(AND(25>=Assumptions!$C$73-Assumptions!$C$75,25<Assumptions!$C$73),1,0))) -> 0 | AA19: =IF(Assumptions!$E$6="Off",0,-Assumptions!$C$74/Assumptions!$C$75*(IF(AND(26>=Assumptions!$C$71-Assumptions!$C$75,26<Assumptions!$C$71),1,0)+IF(AND(26>=Assumptions!$C$72-Assumptions!$C$75,26<Assumptions!$C$72),1,0)+IF(AND(26>=Assumptions!$C$73-Assumptions!$C$75,26<Assumptions!$C$73),1,0))) -> 0 | AB19: =IF(Assumptions!$E$6="Off",0,-Assumptions!$C$74/Assumptions!$C$75*(IF(AND(27>=Assumptions!$C$71-Assumptions!$C$75,27<Assumptions!$C$71),1,0)+IF(AND(27>=Assumptions!$C$72-Assumptions!$C$75,27<Assumptions!$C$72),1,0)+IF(AND(27>=Assumptions!$C$73-Assumptions!$C$75,27<Assumptions!$C$73),1,0))) -> -2500 | AC19: =IF(Assumptions!$E$6="Off",0,-Assumptions!$C$74/Assumptions!$C$75*(IF(AND(28>=Assumptions!$C$71-Assumptions!$C$75,28<Assumptions!$C$71),1,0)+IF(AND(28>=Assumptions!$C$72-Assumptions!$C$75,28<Assumptions!$C$72),1,0)+IF(AND(28>=Assumptions!$C$73-Assumptions!$C$75,28<Assumptions!$C$73),1,0))) -> -2500 | AD19: =IF(Assumptions!$E$6="Off",0,-Assumptions!$C$74/Assumptions!$C$75*(IF(AND(29>=Assumptions!$C$71-Assumptions!$C$75,29<Assumptions!$C$71),1,0)+IF(AND(29>=Assumptions!$C$72-Assumptions!$C$75,29<Assumptions!$C$72),1,0)+IF(AND(29>=Assumptions!$C$73-Assumptions!$C$75,29<Assumptions!$C$73),1,0))) -> -2500 | AE19: =IF(Assumptions!$E$6="Off",0,-Assumptions!$C$74/Assumptions!$C$75*(IF(AND(30>=Assumptions!$C$71-Assumptions!$C$75,30<Assumptions!$C$71),1,0)+IF(AND(30>=Assumptions!$C$72-Assumptions!$C$75,30<Assumptions!$C$72),1,0)+IF(AND(30>=Assumptions!$C$73-Assumptions!$C$75,30<Assumptions!$C$73),1,0))) -> -2500 | AF19: =IF(Assumptions!$E$6="Off",0,-Assumptions!$C$74/Assumptions!$C$75*(IF(AND(31>=Assumptions!$C$71-Assumptions!$C$75,31<Assumptions!$C$71),1,0)+IF(AND(31>=Assumptions!$C$72-Assumptions!$C$75,31<Assumptions!$C$72),1,0)+IF(AND(31>=Assumptions!$C$73-Assumptions!$C$75,31<Assumptions!$C$73),1,0))) -> -2500 | AG19: =IF(Assumptions!$E$6="Off",0,-Assumptions!$C$74/Assumptions!$C$75*(IF(AND(32>=Assumptions!$C$71-Assumptions!$C$75,32<Assumptions!$C$71),1,0)+IF(AND(32>=Assumptions!$C$72-Assumptions!$C$75,32<Assumptions!$C$72),1,0)+IF(AND(32>=Assumptions!$C$73-Assumptions!$C$75,32<Assumptions!$C$73),1,0))) -> -2500 | AH19: =IF(Assumptions!$E$6="Off",0,-Assumptions!$C$74/Assumptions!$C$75*(IF(AND(33>=Assumptions!$C$71-Assumptions!$C$75,33<Assumptions!$C$71),1,0)+IF(AND(33>=Assumptions!$C$72-Assumptions!$C$75,33<Assumptions!$C$72),1,0)+IF(AND(33>=Assumptions!$C$73-Assumptions!$C$75,33<Assumptions!$C$73),1,0))) -> 0 | AI19: =IF(Assumptions!$E$6="Off",0,-Assumptions!$C$74/Assumptions!$C$75*(IF(AND(34>=Assumptions!$C$71-Assumptions!$C$75,34<Assumptions!$C$71),1,0)+IF(AND(34>=Assumptions!$C$72-Assumptions!$C$75,34<Assumptions!$C$72),1,0)+IF(AND(34>=Assumptions!$C$73-Assumptions!$C$75,34<Assumptions!$C$73),1,0))) -> 0 | AJ19: =IF(Assumptions!$E$6="Off",0,-Assumptions!$C$74/Assumptions!$C$75*(IF(AND(35>=Assumptions!$C$71-Assumptions!$C$75,35<Assumptions!$C$71),1,0)+IF(AND(35>=Assumptions!$C$72-Assumptions!$C$75,35<Assumptions!$C$72),1,0)+IF(AND(35>=Assumptions!$C$73-Assumptions!$C$75,35<Assumptions!$C$73),1,0))) -> 0 | AK19: =IF(Assumptions!$E$6="Off",0,-Assumptions!$C$74/Assumptions!$C$75*(IF(AND(36>=Assumptions!$C$71-Assumptions!$C$75,36<Assumptions!$C$71),1,0)+IF(AND(36>=Assumptions!$C$72-Assumptions!$C$75,36<Assumptions!$C$72),1,0)+IF(AND(36>=Assumptions!$C$73-Assumptions!$C$75,36<Assumptions!$C$73),1,0))) -> 0
A20: Total extension contribution | B20: =SUM(B13,B17) -> 0 | C20: =SUM(C13,C17) -> 0 | D20: =SUM(D13,D17) -> 0 | E20: =SUM(E13,E17) -> 0 | F20: =SUM(F13,F17) -> 0 | G20: =SUM(G13,G17) -> 0 | H20: =SUM(H13,H17) -> 0 | I20: =SUM(I13,I17) -> 0 | ... AK20: =SUM(AK13,AK17) -> 7000

Sheet Team Blueprint
A1: TUPENSACI | Team & Agency Blueprint v3.0
A2: Il round assegna €80k al team e €35k all'agenzia; il conto economico mostra il costo operativo lordo, che può essere sostenuto anche dal margine generato dal business fisico.
A4: LEAN RECURRING TEAM — MONTHLY COST BY PHASE
A5: Function | B5: M1–M3 | C5: M4–M6 | D5: M7–M12 | E5: M13+ | F5: Delivery model | G5: Scale rule
A6: Existing physical operations & administration | B6: 1250 | C6: 1250 | D6: 1250 | E6: 1250 | F6: Existing cost base | G6: Keep fixed while fulfillment remains outsourced
A7: AI product & technical maintenance | B7: 0 | C7: 2500 | D7: 2500 | E7: 2500 | F7: Vendor/fractional retainer after beta | G7: In-house only after product scale
A8: Growth leadership + performance agency | B8: 6500 | C8: 6500 | D8: 6500 | E8: 6500 | F8: Fractional owner + specialist agency | G8: Replace placeholders with signed contracts; one owner remains accountable
A9: Content & community | B9: 1500 | C9: 1500 | D9: 1500 | E9: 1500 | F9: Creator/editorial contractor | G9: Scale only if content improves conversion or retention
A10: Customer care & order operations | B10: 750 | C10: 750 | D10: 750 | E10: 750 | F10: Part-time / outsourced | G10: Expand above 1,000 physical orders/month
A11: QA, privacy, safety & legal | B11: 0 | C11: 250 | D11: 250 | E11: 250 | F11: Recurring oversight after initial setup | G11: No full-time role before enterprise complexity
A12: Incremental platforms & software | B12: 0 | C12: 250 | D12: 250 | E12: 250 | F12: Lean SaaS stack | G12: Add tools only against measurable need
A13: Founder strategic/editorial contribution | B13: 0 | C13: 0 | D13: 0 | E13: 0 | F13: Uncompensated in this model | G13: Revisit after runway and governance agreement
A14: TOTAL MONTHLY RECURRING STRUCTURE | B14: 10000 | C14: 13000 | D14: 13000 | E14: 13000
A17: OPERATING PRINCIPLES & GATES
A18: Principle | B18: Decision rule | E18: Why
A19: Capital allocation is not an opex ceiling | B19: Round allocation covers the first-year share; operating contribution may be reinvested | E19: Avoids underfunding campaigns when unit economics are working
A20: Growth has one accountable owner | B20: Head of Growth owns ecommerce, CRM, agency economics and conversion | E20: Avoids delegating the business result entirely to an agency
A21: Beta as soon as functional | B21: Open a controlled beta in M4 while the full build continues | E21: Moves willingness-to-pay and retention learning forward
A22: Capital remains gated | B22: Team, media and build budgets expand only after M3 and M6 evidence | E22: Protects the first €300k round
A23: Stop is an explicit outcome | B23: If M12 does not show a credible 2023 recovery and AI traction, do not finance Year 3 | E23: Prevents a weak three-year forecast from becoming a commitment

Sheet Team & Opex
A1: TUPENSACI | Team & Opex v3.0
A2: Il modello mantiene una struttura esecutiva piena da subito. La minore stima tecnologica non riduce il team: libera capitale per prodotto, creatività, campagne e runway. I ricavi operativi possono finanziare spesa ulteriore rispetto all'uso del round.
A5: Month | B5: M1 | C5: M2 | D5: M3 | E5: M4 | F5: M5 | G5: M6 | H5: M7 | I5: M8 | J5: M9 | K5: M10 | L5: M11 | M5: M12 | N5: M13 | O5: M14 | P5: M15 | Q5: M16 | R5: M17 | S5: M18 | T5: M19 | U5: M20 | V5: M21 | W5: M22 | X5: M23 | Y5: M24 | Z5: M25 | AA5: M26 | AB5: M27 | AC5: M28 | AD5: M29 | AE5: M30 | AF5: M31 | AG5: M32 | AH5: M33 | AI5: M34 | AJ5: M35 | AK5: M36
A6: Year | B6: Y1 | C6: Y1 | D6: Y1 | E6: Y1 | F6: Y1 | G6: Y1 | H6: Y1 | I6: Y1 | J6: Y1 | K6: Y1 | L6: Y1 | M6: Y1 | N6: Y2 | O6: Y2 | P6: Y2 | Q6: Y2 | R6: Y2 | S6: Y2 | T6: Y2 | U6: Y2 | V6: Y2 | W6: Y2 | X6: Y2 | Y6: Y2 | Z6: Y3 | AA6: Y3 | AB6: Y3 | AC6: Y3 | AD6: Y3 | AE6: Y3 | AF6: Y3 | AG6: Y3 | AH6: Y3 | AI6: Y3 | AJ6: Y3 | AK6: Y3
A7: Stage | B7: Relaunch | C7: Relaunch | D7: Relaunch | E7: Beta build | F7: Beta build | G7: Gate M6 | H7: AI launch | I7: AI launch | J7: AI launch | K7: Scale test | L7: Scale test | M7: Scale test | N7: Scale | O7: Scale | P7: Scale | Q7: Scale | R7: Scale | S7: Scale | T7: Scale | U7: Scale | V7: Scale | W7: Scale | X7: Scale | Y7: Scale | Z7: Scale | AA7: Scale | AB7: Scale | AC7: Scale | AD7: Scale | AE7: Scale | AF7: Scale | AG7: Scale | AH7: Scale | AI7: Scale | AJ7: Scale | AK7: Scale
A9: RECURRING OPERATING STRUCTURE
A10: Legacy physical fixed costs | B10: =-Assumptions!$C$45/12 -> -1250 | C10: =-Assumptions!$C$45/12 -> -1250 | D10: =-Assumptions!$C$45/12 -> -1250 | E10: =-Assumptions!$C$45/12 -> -1250 | F10: =-Assumptions!$C$45/12 -> -1250 | G10: =-Assumptions!$C$45/12 -> -1250 | H10: =-Assumptions!$C$45/12 -> -1250 | I10: =-Assumptions!$C$45/12 -> -1250 | ... AK10: =-Assumptions!$C$45/12 -> -1250
A11: Incremental operating team & platforms | B11: =-Assumptions!$C$60*IF(1<4,Assumptions!$C$61,IF(1<13,Assumptions!$C$62,Assumptions!$C$63)) -> -8750 | C11: =-Assumptions!$C$60*IF(2<4,Assumptions!$C$61,IF(2<13,Assumptions!$C$62,Assumptions!$C$63)) -> -8750 | D11: =-Assumptions!$C$60*IF(3<4,Assumptions!$C$61,IF(3<13,Assumptions!$C$62,Assumptions!$C$63)) -> -8750 | E11: =-Assumptions!$C$60*IF(4<4,Assumptions!$C$61,IF(4<13,Assumptions!$C$62,Assumptions!$C$63)) -> -11750 | F11: =-Assumptions!$C$60*IF(5<4,Assumptions!$C$61,IF(5<13,Assumptions!$C$62,Assumptions!$C$63)) -> -11750 | G11: =-Assumptions!$C$60*IF(6<4,Assumptions!$C$61,IF(6<13,Assumptions!$C$62,Assumptions!$C$63)) -> -11750 | H11: =-Assumptions!$C$60*IF(7<4,Assumptions!$C$61,IF(7<13,Assumptions!$C$62,Assumptions!$C$63)) -> -11750 | I11: =-Assumptions!$C$60*IF(8<4,Assumptions!$C$61,IF(8<13,Assumptions!$C$62,Assumptions!$C$63)) -> -11750 | J11: =-Assumptions!$C$60*IF(9<4,Assumptions!$C$61,IF(9<13,Assumptions!$C$62,Assumptions!$C$63)) -> -11750 | K11: =-Assumptions!$C$60*IF(10<4,Assumptions!$C$61,IF(10<13,Assumptions!$C$62,Assumptions!$C$63)) -> -11750 | L11: =-Assumptions!$C$60*IF(11<4,Assumptions!$C$61,IF(11<13,Assumptions!$C$62,Assumptions!$C$63)) -> -11750 | M11: =-Assumptions!$C$60*IF(12<4,Assumptions!$C$61,IF(12<13,Assumptions!$C$62,Assumptions!$C$63)) -> -11750 | N11: =-Assumptions!$C$60*IF(13<4,Assumptions!$C$61,IF(13<13,Assumptions!$C$62,Assumptions!$C$63)) -> -11750 | O11: =-Assumptions!$C$60*IF(14<4,Assumptions!$C$61,IF(14<13,Assumptions!$C$62,Assumptions!$C$63)) -> -11750 | P11: =-Assumptions!$C$60*IF(15<4,Assumptions!$C$61,IF(15<13,Assumptions!$C$62,Assumptions!$C$63)) -> -11750 | Q11: =-Assumptions!$C$60*IF(16<4,Assumptions!$C$61,IF(16<13,Assumptions!$C$62,Assumptions!$C$63)) -> -11750 | R11: =-Assumptions!$C$60*IF(17<4,Assumptions!$C$61,IF(17<13,Assumptions!$C$62,Assumptions!$C$63)) -> -11750 | S11: =-Assumptions!$C$60*IF(18<4,Assumptions!$C$61,IF(18<13,Assumptions!$C$62,Assumptions!$C$63)) -> -11750 | T11: =-Assumptions!$C$60*IF(19<4,Assumptions!$C$61,IF(19<13,Assumptions!$C$62,Assumptions!$C$63)) -> -11750 | U11: =-Assumptions!$C$60*IF(20<4,Assumptions!$C$61,IF(20<13,Assumptions!$C$62,Assumptions!$C$63)) -> -11750 | V11: =-Assumptions!$C$60*IF(21<4,Assumptions!$C$61,IF(21<13,Assumptions!$C$62,Assumptions!$C$63)) -> -11750 | W11: =-Assumptions!$C$60*IF(22<4,Assumptions!$C$61,IF(22<13,Assumptions!$C$62,Assumptions!$C$63)) -> -11750 | X11: =-Assumptions!$C$60*IF(23<4,Assumptions!$C$61,IF(23<13,Assumptions!$C$62,Assumptions!$C$63)) -> -11750 | Y11: =-Assumptions!$C$60*IF(24<4,Assumptions!$C$61,IF(24<13,Assumptions!$C$62,Assumptions!$C$63)) -> -11750 | Z11: =-Assumptions!$C$60*IF(25<4,Assumptions!$C$61,IF(25<13,Assumptions!$C$62,Assumptions!$C$63)) -> -11750 | AA11: =-Assumptions!$C$60*IF(26<4,Assumptions!$C$61,IF(26<13,Assumptions!$C$62,Assumptions!$C$63)) -> -11750 | AB11: =-Assumptions!$C$60*IF(27<4,Assumptions!$C$61,IF(27<13,Assumptions!$C$62,Assumptions!$C$63)) -> -11750 | AC11: =-Assumptions!$C$60*IF(28<4,Assumptions!$C$61,IF(28<13,Assumptions!$C$62,Assumptions!$C$63)) -> -11750 | AD11: =-Assumptions!$C$60*IF(29<4,Assumptions!$C$61,IF(29<13,Assumptions!$C$62,Assumptions!$C$63)) -> -11750 | AE11: =-Assumptions!$C$60*IF(30<4,Assumptions!$C$61,IF(30<13,Assumptions!$C$62,Assumptions!$C$63)) -> -11750 | AF11: =-Assumptions!$C$60*IF(31<4,Assumptions!$C$61,IF(31<13,Assumptions!$C$62,Assumptions!$C$63)) -> -11750 | AG11: =-Assumptions!$C$60*IF(32<4,Assumptions!$C$61,IF(32<13,Assumptions!$C$62,Assumptions!$C$63)) -> -11750 | AH11: =-Assumptions!$C$60*IF(33<4,Assumptions!$C$61,IF(33<13,Assumptions!$C$62,Assumptions!$C$63)) -> -11750 | AI11: =-Assumptions!$C$60*IF(34<4,Assumptions!$C$61,IF(34<13,Assumptions!$C$62,Assumptions!$C$63)) -> -11750 | AJ11: =-Assumptions!$C$60*IF(35<4,Assumptions!$C$61,IF(35<13,Assumptions!$C$62,Assumptions!$C$63)) -> -11750 | AK11: =-Assumptions!$C$60*IF(36<4,Assumptions!$C$61,IF(36<13,Assumptions!$C$62,Assumptions!$C$63)) -> -11750
A12: Founder compensation | B12: =-Assumptions!$C$46/12 -> 0 | C12: =-Assumptions!$C$46/12 -> 0 | D12: =-Assumptions!$C$46/12 -> 0 | E12: =-Assumptions!$C$46/12 -> 0 | F12: =-Assumptions!$C$46/12 -> 0 | G12: =-Assumptions!$C$46/12 -> 0 | H12: =-Assumptions!$C$46/12 -> 0 | I12: =-Assumptions!$C$46/12 -> 0 | ... AK12: =-Assumptions!$C$46/12 -> 0
A13: Recurring opex | B13: =SUM(B10:B12) -> -10000 | C13: =SUM(C10:C12) -> -10000 | D13: =SUM(D10:D12) -> -10000 | E13: =SUM(E10:E12) -> -13000 | F13: =SUM(F10:F12) -> -13000 | G13: =SUM(G10:G12) -> -13000 | H13: =SUM(H10:H12) -> -13000 | I13: =SUM(I10:I12) -> -13000 | ... AK13: =SUM(AK10:AK12) -> -13000
A15: External product & technology build | B15: =IF(1<=Assumptions!$C$55,-Assumptions!$C$54/Assumptions!$C$55,0) -> -10833.333 | C15: =IF(2<=Assumptions!$C$55,-Assumptions!$C$54/Assumptions!$C$55,0) -> -10833.333 | D15: =IF(3<=Assumptions!$C$55,-Assumptions!$C$54/Assumptions!$C$55,0) -> -10833.333 | E15: =IF(4<=Assumptions!$C$55,-Assumptions!$C$54/Assumptions!$C$55,0) -> -10833.333 | F15: =IF(5<=Assumptions!$C$55,-Assumptions!$C$54/Assumptions!$C$55,0) -> -10833.333 | G15: =IF(6<=Assumptions!$C$55,-Assumptions!$C$54/Assumptions!$C$55,0) -> -10833.333 | H15: =IF(7<=Assumptions!$C$55,-Assumptions!$C$54/Assumptions!$C$55,0) -> 0 | I15: =IF(8<=Assumptions!$C$55,-Assumptions!$C$54/Assumptions!$C$55,0) -> 0 | J15: =IF(9<=Assumptions!$C$55,-Assumptions!$C$54/Assumptions!$C$55,0) -> 0 | K15: =IF(10<=Assumptions!$C$55,-Assumptions!$C$54/Assumptions!$C$55,0) -> 0 | L15: =IF(11<=Assumptions!$C$55,-Assumptions!$C$54/Assumptions!$C$55,0) -> 0 | M15: =IF(12<=Assumptions!$C$55,-Assumptions!$C$54/Assumptions!$C$55,0) -> 0 | N15: =IF(13<=Assumptions!$C$55,-Assumptions!$C$54/Assumptions!$C$55,0) -> 0 | O15: =IF(14<=Assumptions!$C$55,-Assumptions!$C$54/Assumptions!$C$55,0) -> 0 | P15: =IF(15<=Assumptions!$C$55,-Assumptions!$C$54/Assumptions!$C$55,0) -> 0 | Q15: =IF(16<=Assumptions!$C$55,-Assumptions!$C$54/Assumptions!$C$55,0) -> 0 | R15: =IF(17<=Assumptions!$C$55,-Assumptions!$C$54/Assumptions!$C$55,0) -> 0 | S15: =IF(18<=Assumptions!$C$55,-Assumptions!$C$54/Assumptions!$C$55,0) -> 0 | T15: =IF(19<=Assumptions!$C$55,-Assumptions!$C$54/Assumptions!$C$55,0) -> 0 | U15: =IF(20<=Assumptions!$C$55,-Assumptions!$C$54/Assumptions!$C$55,0) -> 0 | V15: =IF(21<=Assumptions!$C$55,-Assumptions!$C$54/Assumptions!$C$55,0) -> 0 | W15: =IF(22<=Assumptions!$C$55,-Assumptions!$C$54/Assumptions!$C$55,0) -> 0 | X15: =IF(23<=Assumptions!$C$55,-Assumptions!$C$54/Assumptions!$C$55,0) -> 0 | Y15: =IF(24<=Assumptions!$C$55,-Assumptions!$C$54/Assumptions!$C$55,0) -> 0 | Z15: =IF(25<=Assumptions!$C$55,-Assumptions!$C$54/Assumptions!$C$55,0) -> 0 | AA15: =IF(26<=Assumptions!$C$55,-Assumptions!$C$54/Assumptions!$C$55,0) -> 0 | AB15: =IF(27<=Assumptions!$C$55,-Assumptions!$C$54/Assumptions!$C$55,0) -> 0 | AC15: =IF(28<=Assumptions!$C$55,-Assumptions!$C$54/Assumptions!$C$55,0) -> 0 | AD15: =IF(29<=Assumptions!$C$55,-Assumptions!$C$54/Assumptions!$C$55,0) -> 0 | AE15: =IF(30<=Assumptions!$C$55,-Assumptions!$C$54/Assumptions!$C$55,0) -> 0 | AF15: =IF(31<=Assumptions!$C$55,-Assumptions!$C$54/Assumptions!$C$55,0) -> 0 | AG15: =IF(32<=Assumptions!$C$55,-Assumptions!$C$54/Assumptions!$C$55,0) -> 0 | AH15: =IF(33<=Assumptions!$C$55,-Assumptions!$C$54/Assumptions!$C$55,0) -> 0 | AI15: =IF(34<=Assumptions!$C$55,-Assumptions!$C$54/Assumptions!$C$55,0) -> 0 | AJ15: =IF(35<=Assumptions!$C$55,-Assumptions!$C$54/Assumptions!$C$55,0) -> 0 | AK15: =IF(36<=Assumptions!$C$55,-Assumptions!$C$54/Assumptions!$C$55,0) -> 0
A16: Corpus and editorial architecture | B16: =IF(1<=Assumptions!$C$57,-Assumptions!$C$56/Assumptions!$C$57,0) -> -1666.6667 | C16: =IF(2<=Assumptions!$C$57,-Assumptions!$C$56/Assumptions!$C$57,0) -> -1666.6667 | D16: =IF(3<=Assumptions!$C$57,-Assumptions!$C$56/Assumptions!$C$57,0) -> -1666.6667 | E16: =IF(4<=Assumptions!$C$57,-Assumptions!$C$56/Assumptions!$C$57,0) -> -1666.6667 | F16: =IF(5<=Assumptions!$C$57,-Assumptions!$C$56/Assumptions!$C$57,0) -> -1666.6667 | G16: =IF(6<=Assumptions!$C$57,-Assumptions!$C$56/Assumptions!$C$57,0) -> -1666.6667 | H16: =IF(7<=Assumptions!$C$57,-Assumptions!$C$56/Assumptions!$C$57,0) -> 0 | I16: =IF(8<=Assumptions!$C$57,-Assumptions!$C$56/Assumptions!$C$57,0) -> 0 | J16: =IF(9<=Assumptions!$C$57,-Assumptions!$C$56/Assumptions!$C$57,0) -> 0 | K16: =IF(10<=Assumptions!$C$57,-Assumptions!$C$56/Assumptions!$C$57,0) -> 0 | L16: =IF(11<=Assumptions!$C$57,-Assumptions!$C$56/Assumptions!$C$57,0) -> 0 | M16: =IF(12<=Assumptions!$C$57,-Assumptions!$C$56/Assumptions!$C$57,0) -> 0 | N16: =IF(13<=Assumptions!$C$57,-Assumptions!$C$56/Assumptions!$C$57,0) -> 0 | O16: =IF(14<=Assumptions!$C$57,-Assumptions!$C$56/Assumptions!$C$57,0) -> 0 | P16: =IF(15<=Assumptions!$C$57,-Assumptions!$C$56/Assumptions!$C$57,0) -> 0 | Q16: =IF(16<=Assumptions!$C$57,-Assumptions!$C$56/Assumptions!$C$57,0) -> 0 | R16: =IF(17<=Assumptions!$C$57,-Assumptions!$C$56/Assumptions!$C$57,0) -> 0 | S16: =IF(18<=Assumptions!$C$57,-Assumptions!$C$56/Assumptions!$C$57,0) -> 0 | T16: =IF(19<=Assumptions!$C$57,-Assumptions!$C$56/Assumptions!$C$57,0) -> 0 | U16: =IF(20<=Assumptions!$C$57,-Assumptions!$C$56/Assumptions!$C$57,0) -> 0 | V16: =IF(21<=Assumptions!$C$57,-Assumptions!$C$56/Assumptions!$C$57,0) -> 0 | W16: =IF(22<=Assumptions!$C$57,-Assumptions!$C$56/Assumptions!$C$57,0) -> 0 | X16: =IF(23<=Assumptions!$C$57,-Assumptions!$C$56/Assumptions!$C$57,0) -> 0 | Y16: =IF(24<=Assumptions!$C$57,-Assumptions!$C$56/Assumptions!$C$57,0) -> 0 | Z16: =IF(25<=Assumptions!$C$57,-Assumptions!$C$56/Assumptions!$C$57,0) -> 0 | AA16: =IF(26<=Assumptions!$C$57,-Assumptions!$C$56/Assumptions!$C$57,0) -> 0 | AB16: =IF(27<=Assumptions!$C$57,-Assumptions!$C$56/Assumptions!$C$57,0) -> 0 | AC16: =IF(28<=Assumptions!$C$57,-Assumptions!$C$56/Assumptions!$C$57,0) -> 0 | AD16: =IF(29<=Assumptions!$C$57,-Assumptions!$C$56/Assumptions!$C$57,0) -> 0 | AE16: =IF(30<=Assumptions!$C$57,-Assumptions!$C$56/Assumptions!$C$57,0) -> 0 | AF16: =IF(31<=Assumptions!$C$57,-Assumptions!$C$56/Assumptions!$C$57,0) -> 0 | AG16: =IF(32<=Assumptions!$C$57,-Assumptions!$C$56/Assumptions!$C$57,0) -> 0 | AH16: =IF(33<=Assumptions!$C$57,-Assumptions!$C$56/Assumptions!$C$57,0) -> 0 | AI16: =IF(34<=Assumptions!$C$57,-Assumptions!$C$56/Assumptions!$C$57,0) -> 0 | AJ16: =IF(35<=Assumptions!$C$57,-Assumptions!$C$56/Assumptions!$C$57,0) -> 0 | AK16: =IF(36<=Assumptions!$C$57,-Assumptions!$C$56/Assumptions!$C$57,0) -> 0
A17: Privacy, safety & legal initial setup | B17: =IF(1<=Assumptions!$C$59,-Assumptions!$C$58/Assumptions!$C$59,0) -> -1666.6667 | C17: =IF(2<=Assumptions!$C$59,-Assumptions!$C$58/Assumptions!$C$59,0) -> -1666.6667 | D17: =IF(3<=Assumptions!$C$59,-Assumptions!$C$58/Assumptions!$C$59,0) -> -1666.6667 | E17: =IF(4<=Assumptions!$C$59,-Assumptions!$C$58/Assumptions!$C$59,0) -> -1666.6667 | F17: =IF(5<=Assumptions!$C$59,-Assumptions!$C$58/Assumptions!$C$59,0) -> -1666.6667 | G17: =IF(6<=Assumptions!$C$59,-Assumptions!$C$58/Assumptions!$C$59,0) -> -1666.6667 | H17: =IF(7<=Assumptions!$C$59,-Assumptions!$C$58/Assumptions!$C$59,0) -> 0 | I17: =IF(8<=Assumptions!$C$59,-Assumptions!$C$58/Assumptions!$C$59,0) -> 0 | J17: =IF(9<=Assumptions!$C$59,-Assumptions!$C$58/Assumptions!$C$59,0) -> 0 | K17: =IF(10<=Assumptions!$C$59,-Assumptions!$C$58/Assumptions!$C$59,0) -> 0 | L17: =IF(11<=Assumptions!$C$59,-Assumptions!$C$58/Assumptions!$C$59,0) -> 0 | M17: =IF(12<=Assumptions!$C$59,-Assumptions!$C$58/Assumptions!$C$59,0) -> 0 | N17: =IF(13<=Assumptions!$C$59,-Assumptions!$C$58/Assumptions!$C$59,0) -> 0 | O17: =IF(14<=Assumptions!$C$59,-Assumptions!$C$58/Assumptions!$C$59,0) -> 0 | P17: =IF(15<=Assumptions!$C$59,-Assumptions!$C$58/Assumptions!$C$59,0) -> 0 | Q17: =IF(16<=Assumptions!$C$59,-Assumptions!$C$58/Assumptions!$C$59,0) -> 0 | R17: =IF(17<=Assumptions!$C$59,-Assumptions!$C$58/Assumptions!$C$59,0) -> 0 | S17: =IF(18<=Assumptions!$C$59,-Assumptions!$C$58/Assumptions!$C$59,0) -> 0 | T17: =IF(19<=Assumptions!$C$59,-Assumptions!$C$58/Assumptions!$C$59,0) -> 0 | U17: =IF(20<=Assumptions!$C$59,-Assumptions!$C$58/Assumptions!$C$59,0) -> 0 | V17: =IF(21<=Assumptions!$C$59,-Assumptions!$C$58/Assumptions!$C$59,0) -> 0 | W17: =IF(22<=Assumptions!$C$59,-Assumptions!$C$58/Assumptions!$C$59,0) -> 0 | X17: =IF(23<=Assumptions!$C$59,-Assumptions!$C$58/Assumptions!$C$59,0) -> 0 | Y17: =IF(24<=Assumptions!$C$59,-Assumptions!$C$58/Assumptions!$C$59,0) -> 0 | Z17: =IF(25<=Assumptions!$C$59,-Assumptions!$C$58/Assumptions!$C$59,0) -> 0 | AA17: =IF(26<=Assumptions!$C$59,-Assumptions!$C$58/Assumptions!$C$59,0) -> 0 | AB17: =IF(27<=Assumptions!$C$59,-Assumptions!$C$58/Assumptions!$C$59,0) -> 0 | AC17: =IF(28<=Assumptions!$C$59,-Assumptions!$C$58/Assumptions!$C$59,0) -> 0 | AD17: =IF(29<=Assumptions!$C$59,-Assumptions!$C$58/Assumptions!$C$59,0) -> 0 | AE17: =IF(30<=Assumptions!$C$59,-Assumptions!$C$58/Assumptions!$C$59,0) -> 0 | AF17: =IF(31<=Assumptions!$C$59,-Assumptions!$C$58/Assumptions!$C$59,0) -> 0 | AG17: =IF(32<=Assumptions!$C$59,-Assumptions!$C$58/Assumptions!$C$59,0) -> 0 | AH17: =IF(33<=Assumptions!$C$59,-Assumptions!$C$58/Assumptions!$C$59,0) -> 0 | AI17: =IF(34<=Assumptions!$C$59,-Assumptions!$C$58/Assumptions!$C$59,0) -> 0 | AJ17: =IF(35<=Assumptions!$C$59,-Assumptions!$C$58/Assumptions!$C$59,0) -> 0 | AK17: =IF(36<=Assumptions!$C$59,-Assumptions!$C$58/Assumptions!$C$59,0) -> 0
A18: One-time build investment | B18: =SUM(B15:B17) -> -14166.667 | C18: =SUM(C15:C17) -> -14166.667 | D18: =SUM(D15:D17) -> -14166.667 | E18: =SUM(E15:E17) -> -14166.667 | F18: =SUM(F15:F17) -> -14166.667 | G18: =SUM(G15:G17) -> -14166.667 | H18: =SUM(H15:H17) -> 0 | I18: =SUM(I15:I17) -> 0 | ... AK18: =SUM(AK15:AK17) -> 0
A20: Total operating cash costs | B20: =SUM(B13,B18) -> -24166.667 | C20: =SUM(C13,C18) -> -24166.667 | D20: =SUM(D13,D18) -> -24166.667 | E20: =SUM(E13,E18) -> -27166.667 | F20: =SUM(F13,F18) -> -27166.667 | G20: =SUM(G13,G18) -> -27166.667 | H20: =SUM(H13,H18) -> -13000 | I20: =SUM(I13,I18) -> -13000 | ... AK20: =SUM(AK13,AK18) -> -13000

Sheet P&L 36 Months
A1: TUPENSACI | Integrated P&L — 36 Months
A2: Physical products, AI and the optional operating extensions are modeled as one company. EBITDA is before one-time build investment; cash result includes it.
A5: Month | B5: M1 | C5: M2 | D5: M3 | E5: M4 | F5: M5 | G5: M6 | H5: M7 | I5: M8 | J5: M9 | K5: M10 | L5: M11 | M5: M12 | N5: M13 | O5: M14 | P5: M15 | Q5: M16 | R5: M17 | S5: M18 | T5: M19 | U5: M20 | V5: M21 | W5: M22 | X5: M23 | Y5: M24 | Z5: M25 | AA5: M26 | AB5: M27 | AC5: M28 | AD5: M29 | AE5: M30 | AF5: M31 | AG5: M32 | AH5: M33 | AI5: M34 | AJ5: M35 | AK5: M36
A6: Year | B6: Y1 | C6: Y1 | D6: Y1 | E6: Y1 | F6: Y1 | G6: Y1 | H6: Y1 | I6: Y1 | J6: Y1 | K6: Y1 | L6: Y1 | M6: Y1 | N6: Y2 | O6: Y2 | P6: Y2 | Q6: Y2 | R6: Y2 | S6: Y2 | T6: Y2 | U6: Y2 | V6: Y2 | W6: Y2 | X6: Y2 | Y6: Y2 | Z6: Y3 | AA6: Y3 | AB6: Y3 | AC6: Y3 | AD6: Y3 | AE6: Y3 | AF6: Y3 | AG6: Y3 | AH6: Y3 | AI6: Y3 | AJ6: Y3 | AK6: Y3
A7: Stage | B7: Relaunch | C7: Relaunch | D7: Relaunch | E7: Beta build | F7: Beta build | G7: Gate M6 | H7: AI launch | I7: AI launch | J7: AI launch | K7: Scale test | L7: Scale test | M7: Scale test | N7: Scale | O7: Scale | P7: Scale | Q7: Scale | R7: Scale | S7: Scale | T7: Scale | U7: Scale | V7: Scale | W7: Scale | X7: Scale | Y7: Scale | Z7: Scale | AA7: Scale | AB7: Scale | AC7: Scale | AD7: Scale | AE7: Scale | AF7: Scale | AG7: Scale | AH7: Scale | AI7: Scale | AJ7: Scale | AK7: Scale
A9: INTEGRATED PROFIT & LOSS
A10: Physical + extension revenue | B10: =SUM('Physical Business'!B18,'Growth Extensions'!B11,'Growth Extensions'!B15) -> 19895.652 | C10: =SUM('Physical Business'!C18,'Growth Extensions'!C11,'Growth Extensions'!C15) -> 19927.652 | D10: =SUM('Physical Business'!D18,'Growth Extensions'!D11,'Growth Extensions'!D15) -> 19959.972 | E10: =SUM('Physical Business'!E18,'Growth Extensions'!E11,'Growth Extensions'!E15) -> 25557.833 | F10: =SUM('Physical Business'!F18,'Growth Extensions'!F11,'Growth Extensions'!F15) -> 25590.802 | G10: =SUM('Physical Business'!G18,'Growth Extensions'!G11,'Growth Extensions'!G15) -> 25624.102 | H10: =SUM('Physical Business'!H18,'Growth Extensions'!H11,'Growth Extensions'!H15) -> 34005.56 | I10: =SUM('Physical Business'!I18,'Growth Extensions'!I11,'Growth Extensions'!I15) -> 34039.529 | ... AK10: =SUM('Physical Business'!AK18,'Growth Extensions'!AK11,'Growth Extensions'!AK15) -> 55211.4
A11: AI revenue | B11: ='AI Cohorts'!B32 -> 0 | C11: ='AI Cohorts'!C32 -> 0 | D11: ='AI Cohorts'!D32 -> 0 | E11: ='AI Cohorts'!E32 -> 5696.4421 | F11: ='AI Cohorts'!F32 -> 6857.6602 | G11: ='AI Cohorts'!G32 -> 7926.8283 | H11: ='AI Cohorts'!H32 -> 13858.524 | I11: ='AI Cohorts'!I32 -> 15661.52 | ... AK11: ='AI Cohorts'!AK32 -> 43315.559
A12: Total revenue | B12: =SUM(B10:B11) -> 19895.652 | C12: =SUM(C10:C11) -> 19927.652 | D12: =SUM(D10:D11) -> 19959.972 | E12: =SUM(E10:E11) -> 31254.275 | F12: =SUM(F10:F11) -> 32448.463 | G12: =SUM(G10:G11) -> 33550.93 | H12: =SUM(H10:H11) -> 47864.084 | I12: =SUM(I10:I11) -> 49701.049 | ... AK12: =SUM(AK10:AK11) -> 98526.959
A14: Physical + extension direct costs | B14: =SUM('Physical Business'!B19,'Growth Extensions'!B12,'Growth Extensions'!B16) -> -7460.8696 | C14: =SUM('Physical Business'!C19,'Growth Extensions'!C12,'Growth Extensions'!C16) -> -7472.8696 | D14: =SUM('Physical Business'!D19,'Growth Extensions'!D12,'Growth Extensions'!D16) -> -7484.9896 | E14: =SUM('Physical Business'!E19,'Growth Extensions'!E12,'Growth Extensions'!E16) -> -9584.1873 | F14: =SUM('Physical Business'!F19,'Growth Extensions'!F12,'Growth Extensions'!F16) -> -9596.5509 | G14: =SUM('Physical Business'!G19,'Growth Extensions'!G12,'Growth Extensions'!G16) -> -9609.0381 | H14: =SUM('Physical Business'!H19,'Growth Extensions'!H12,'Growth Extensions'!H16) -> -12752.085 | I14: =SUM('Physical Business'!I19,'Growth Extensions'!I12,'Growth Extensions'!I16) -> -12764.823 | ... AK14: =SUM('Physical Business'!AK19,'Growth Extensions'!AK12,'Growth Extensions'!AK16) -> -21266.775
A15: AI variable delivery costs | B15: =-('AI Cohorts'!B32-'AI Cohorts'!B37) -> 0 | C15: =-('AI Cohorts'!C32-'AI Cohorts'!C37) -> 0 | D15: =-('AI Cohorts'!D32-'AI Cohorts'!D37) -> 0 | E15: =-('AI Cohorts'!E32-'AI Cohorts'!E37) -> -2911.0145 | F15: =-('AI Cohorts'!F32-'AI Cohorts'!F37) -> -3424.6873 | G15: =-('AI Cohorts'!G32-'AI Cohorts'!G37) -> -3897.6609 | H15: =-('AI Cohorts'!H32-'AI Cohorts'!H37) -> -6762.5589 | I15: =-('AI Cohorts'!I32-'AI Cohorts'!I37) -> -7560.0118 | ... AK15: =-('AI Cohorts'!AK32-'AI Cohorts'!AK37) -> -20138.631
A16: Gross profit | B16: =SUM(B12,B14:B15) -> 12434.783 | C16: =SUM(C12,C14:C15) -> 12454.783 | D16: =SUM(D12,D14:D15) -> 12474.983 | E16: =SUM(E12,E14:E15) -> 18759.073 | F16: =SUM(F12,F14:F15) -> 19427.224 | G16: =SUM(G12,G14:G15) -> 20044.231 | H16: =SUM(H12,H14:H15) -> 28349.44 | I16: =SUM(I12,I14:I15) -> 29376.214 | ... AK16: =SUM(AK12,AK14:AK15) -> 57121.554
A18: Physical acquisition spend | B18: ='Physical Business'!B20 -> -6000 | C18: ='Physical Business'!C20 -> -6000 | D18: ='Physical Business'!D20 -> -6000 | E18: ='Physical Business'!E20 -> -8000 | F18: ='Physical Business'!F20 -> -8000 | G18: ='Physical Business'!G20 -> -8000 | H18: ='Physical Business'!H20 -> -11000 | I18: ='Physical Business'!I20 -> -11000 | ... AK18: ='Physical Business'!AK20 -> -12000
A19: Direct AI acquisition spend | B19: ='AI Cohorts'!B38 -> 0 | C19: ='AI Cohorts'!C38 -> 0 | D19: ='AI Cohorts'!D38 -> 0 | E19: ='AI Cohorts'!E38 -> 0 | F19: ='AI Cohorts'!F38 -> 0 | G19: ='AI Cohorts'!G38 -> 0 | H19: ='AI Cohorts'!H38 -> -4000 | I19: ='AI Cohorts'!I38 -> -4000 | ... AK19: ='AI Cohorts'!AK38 -> -6000
A20: Contribution after acquisition | B20: =SUM(B16,B18:B19) -> 6434.7826 | C20: =SUM(C16,C18:C19) -> 6454.7826 | D20: =SUM(D16,D18:D19) -> 6474.9826 | E20: =SUM(E16,E18:E19) -> 10759.073 | F20: =SUM(F16,F18:F19) -> 11427.224 | G20: =SUM(G16,G18:G19) -> 12044.231 | H20: =SUM(H16,H18:H19) -> 13349.44 | I20: =SUM(I16,I18:I19) -> 14376.214 | ... AK20: =SUM(AK16,AK18:AK19) -> 39121.554
A22: Recurring operating opex | B22: ='Team & Opex'!B13 -> -10000 | C22: ='Team & Opex'!C13 -> -10000 | D22: ='Team & Opex'!D13 -> -10000 | E22: ='Team & Opex'!E13 -> -13000 | F22: ='Team & Opex'!F13 -> -13000 | G22: ='Team & Opex'!G13 -> -13000 | H22: ='Team & Opex'!H13 -> -13000 | I22: ='Team & Opex'!I13 -> -13000 | ... AK22: ='Team & Opex'!AK13 -> -13000
A23: Operating EBITDA before one-time build | B23: =SUM(B20,B22) -> -3565.2174 | C23: =SUM(C20,C22) -> -3545.2174 | D23: =SUM(D20,D22) -> -3525.0174 | E23: =SUM(E20,E22) -> -2240.9269 | F23: =SUM(F20,F22) -> -1572.7756 | G23: =SUM(G20,G22) -> -955.76896 | H23: =SUM(H20,H22) -> 349.44019 | I23: =SUM(I20,I22) -> 1376.2137 | ... AK23: =SUM(AK20,AK22) -> 26121.554
A24: Operating EBITDA margin | B24: =IF(B12=0,0,B23/B12) -> -0.1791958 | C24: =IF(C12=0,0,C23/C12) -> -0.17790442 | D24: =IF(D12=0,0,D23/D12) -> -0.17660432 | E24: =IF(E12=0,0,E23/E12) -> -0.071699851 | F24: =IF(F12=0,0,F23/F12) -> -0.048469958 | G24: =IF(G12=0,0,G23/G12) -> -0.028487108 | H24: =IF(H12=0,0,H23/H12) -> 0.0073006765 | I24: =IF(I12=0,0,I23/I12) -> 0.027689832 | ... AK24: =IF(AK12=0,0,AK23/AK12) -> 0.26512087
A26: MVP / corpus / privacy one-time build | B26: =SUM('Team & Opex'!B18,'Growth Extensions'!B19) -> -14166.667 | C26: =SUM('Team & Opex'!C18,'Growth Extensions'!C19) -> -14166.667 | D26: =SUM('Team & Opex'!D18,'Growth Extensions'!D19) -> -16666.667 | E26: =SUM('Team & Opex'!E18,'Growth Extensions'!E19) -> -16666.667 | F26: =SUM('Team & Opex'!F18,'Growth Extensions'!F19) -> -16666.667 | G26: =SUM('Team & Opex'!G18,'Growth Extensions'!G19) -> -16666.667 | H26: =SUM('Team & Opex'!H18,'Growth Extensions'!H19) -> -2500 | I26: =SUM('Team & Opex'!I18,'Growth Extensions'!I19) -> -2500 | ... AK26: =SUM('Team & Opex'!AK18,'Growth Extensions'!AK19) -> 0
A27: Cash operating result | B27: =SUM(B23,B26) -> -17731.884 | C27: =SUM(C23,C26) -> -17711.884 | D27: =SUM(D23,D26) -> -20191.684 | E27: =SUM(E23,E26) -> -18907.594 | F27: =SUM(F23,F26) -> -18239.442 | G27: =SUM(G23,G26) -> -17622.436 | H27: =SUM(H23,H26) -> -2150.5598 | I27: =SUM(I23,I26) -> -1123.7863 | ... AK27: =SUM(AK23,AK26) -> 26121.554

Sheet Use of Proceeds
A1: TUPENSACI | Use of Proceeds — €300k
A2: Il round viene raccolto integralmente. L'impiego è progressivo e subordinato ai gate; le allocazioni di capitale non sono un tetto all'opex lordo, perché il margine operativo può essere reinvestito.
A4: CAPITAL ALLOCATION
A5: Category | B5: Allocation | C5: % round | D5: What it funds | E5: Timing | F5: Gate | G5: P&L treatment | H5: Note
A6: Product & technology | B6: 75000 | C6: =B6/Assumptions!$C$47 -> 0.25 | D6: MVP, discovery, UX, integrations, corpus/prompt QA | E6: M1–M6 | F6: Functional core loop | G6: One-time build | H6: Extendi core MVP indication <€30k; envelope remains prudent
A7: Team | B7: 80000 | C7: =B7/Assumptions!$C$47 -> 0.26666667 | D7: Growth ownership, content/community, care, technical oversight | E7: M1–M12 | F7: Owners and cadence active | G7: Recurring opex | H7: Operating margin may co-finance the gross cost
A8: Agency & creative | B8: 35000 | C8: =B8/Assumptions!$C$47 -> 0.11666667 | D8: Performance execution, creative system, landing and production | E8: M1–M12 | F8: Creative and funnel cadence | G8: Recurring opex | H8: Signed scope replaces placeholder
A9: Paid media | B9: 70000 | C9: =B9/Assumptions!$C$47 -> 0.23333333 | D9: €25k warm/community + €45k broad | E9: M7–M18 | F9: CAC and retention gates | G9: Acquisition spend | H9: Accelerated envelope; Base remains capped
A10: Workbook relaunch | B10: 15000 | C10: =B10/Assumptions!$C$47 -> 0.05 | D10: Assets, ecommerce improvements and relaunch execution | E10: M1–M6 | F10: Commercial recovery | G10: Launch investment | H10: Physical margin is reinvestable
A11: Privacy, legal & governance | B11: 10000 | C11: =B11/Assumptions!$C$47 -> 0.033333333 | D11: Privacy, safety, contracts and governance | E11: M1–M6 | F11: Pre-launch compliance | G11: One-time setup | H11: Recurring oversight remains in team opex
A12: Reserve | B12: 15000 | C12: =B12/Assumptions!$C$47 -> 0.05 | D12: Ring-fenced contingency | E12: Held | F12: Board release | G12: Cash reserve | H12: Not automatically spent
A13: TOTAL | B13: =SUM(B6:B12) -> 300000 | C13: =SUM(C6:C12) -> 1 | H13: Must equal the €300k round
A16: DEPLOYMENT TRANCHES
A17: Phase | B17: Timing | C17: Capital released | D17: Cumulative | E17: Capital locked | F17: Primary objective | G17: Release evidence | H17: Decision
A18: Start | B18: M1–M3 | C18: 90000 | D18: 90000 | E18: =Assumptions!$C$47-D18 -> 210000 | F18: Relaunch + build start | G18: Owners appointed; 90-day plan live | H18: Launch
A19: Gate M3 | B19: M4–M6 | C19: 80000 | D19: 170000 | E19: =Assumptions!$C$47-D19 -> 130000 | F19: Beta + commercial proof | G19: Workbook recovery and functional core loop | H19: Release / correct / stop
A20: Gate M6 | B20: M7–M12 | C20: 115000 | D20: 285000 | E20: =Assumptions!$C$47-D20 -> 15000 | F20: Paid launch and scale test | G20: Paid product ready; CAC/retention measured | H20: Release / hold
A21: Reserve | B21: Held | C21: 15000 | D21: 300000 | E21: =Assumptions!$C$47-D21 -> 0 | F21: Contingency / board decision | G21: Documented need | H21: Release / retain

Sheet Capital Gates
A1: TUPENSACI | Capital Tranches & Decision Gates v3.0
A2: Il round da €300k è raccolto al closing. €285k sono autorizzabili per tranche; €15k restano in riserva fino a decisione esplicita del board.
A4: Gate | B4: Timing | C4: New tranche | D4: Cumulative authorized | E4: Capital locked | F4: Primary use | G4: Minimum evidence | H4: Decision
A5: Start | B5: M1 | C5: 90000 | D5: 90000 | E5: 210000 | F5: Team, agency, relaunch, product start | G5: Round closed; owners appointed; 90-day plan live | H5: Launch
A6: Gate M3 | B6: M4 | C6: 80000 | D6: 170000 | E6: 130000 | F6: Continue build, open beta, improve creative and funnel | G6: 3 workbooks relaunched; MER ≥2.2; CAC/order ≤€14; functional AI loop | H6: Release / correct / stop
A7: Gate M6 | B7: M7 | C7: 115000 | D7: 285000 | E7: 15000 | F7: Paid AI launch and controlled acceleration | G7: Paid beta ready; safety accepted; trial, pricing and analytics live | H7: Release / hold
A8: Reserve | B8: Held | C8: 15000 | D8: 300000 | E8: 0 | F8: Contingency only | G8: Board-approved need | H8: Release / retain
A9: Gate M9 | B9: M9 | C9: 0 | D9: 285000 | E9: 15000 | F9: Operating scale decision | G9: Physical recovery visible; AI return and retention acceptable | H9: Continue / resize
A10: Gate M12 | B10: M12 | C10: 0 | D10: 285000 | E10: 15000 | F10: Scale / follow-on decision | G10: Base ≈2k active; Accelerated 3k–3.5k only if CAC ≤€20 and churn ≤6% | H10: Scale / correct / stop
A13: MONTHLY CAPITAL CONTROL — BASE CASE ASSUMES OPERATING GATES PASSED
A14: Metric | B14: M1 | C14: M2 | D14: M3 | E14: M4 | F14: M5 | G14: M6 | H14: M7 | I14: M8 | J14: M9 | K14: M10 | L14: M11 | M14: M12
A15: Cumulative authorized | B15: =IF(1<4,$D$5,IF(1<7,$D$6,$D$7)) -> 90000 | C15: =IF(2<4,$D$5,IF(2<7,$D$6,$D$7)) -> 90000 | D15: =IF(3<4,$D$5,IF(3<7,$D$6,$D$7)) -> 90000 | E15: =IF(4<4,$D$5,IF(4<7,$D$6,$D$7)) -> 170000 | F15: =IF(5<4,$D$5,IF(5<7,$D$6,$D$7)) -> 170000 | G15: =IF(6<4,$D$5,IF(6<7,$D$6,$D$7)) -> 170000 | H15: =IF(7<4,$D$5,IF(7<7,$D$6,$D$7)) -> 285000 | I15: =IF(8<4,$D$5,IF(8<7,$D$6,$D$7)) -> 285000 | J15: =IF(9<4,$D$5,IF(9<7,$D$6,$D$7)) -> 285000 | K15: =IF(10<4,$D$5,IF(10<7,$D$6,$D$7)) -> 285000 | L15: =IF(11<4,$D$5,IF(11<7,$D$6,$D$7)) -> 285000 | M15: =IF(12<4,$D$5,IF(12<7,$D$6,$D$7)) -> 285000
A16: Capital locked | B16: =Assumptions!$C$47-B15 -> 210000 | C16: =Assumptions!$C$47-C15 -> 210000 | D16: =Assumptions!$C$47-D15 -> 210000 | E16: =Assumptions!$C$47-E15 -> 130000 | F16: =Assumptions!$C$47-F15 -> 130000 | G16: =Assumptions!$C$47-G15 -> 130000 | H16: =Assumptions!$C$47-H15 -> 15000 | I16: =Assumptions!$C$47-I15 -> 15000 | ... M16: =Assumptions!$C$47-M15 -> 15000
A17: Cumulative modeled cash use | B17: =-MIN(0,'Cash & Funding'!B$13) -> 17731.884 | C17: =-MIN(0,'Cash & Funding'!C$13) -> 35443.768 | D17: =-MIN(0,'Cash & Funding'!D$13) -> 55635.452 | E17: =-MIN(0,'Cash & Funding'!E$13) -> 74543.046 | F17: =-MIN(0,'Cash & Funding'!F$13) -> 92782.488 | G17: =-MIN(0,'Cash & Funding'!G$13) -> 110404.92 | H17: =-MIN(0,'Cash & Funding'!H$13) -> 112555.48 | I17: =-MIN(0,'Cash & Funding'!I$13) -> 113679.27 | ... M17: =-MIN(0,'Cash & Funding'!M$13) -> 90642.051
A18: Authorized headroom | B18: =B15-B17 -> 72268.116 | C18: =C15-C17 -> 54556.232 | D18: =D15-D17 -> 34364.548 | E18: =E15-E17 -> 95456.954 | F18: =F15-F17 -> 77217.512 | G18: =G15-G17 -> 59595.076 | H18: =H15-H17 -> 172444.52 | I18: =I15-I17 -> 171320.73 | ... M18: =M15-M17 -> 194357.95

Sheet Cash & Funding
A1: TUPENSACI | Cash & Funding v3.0
A2: Il round da €300k viene raccolto integralmente; €285k sono autorizzabili per tranche e €15k restano in riserva. Il Base misura la sostenibilità, l'Accelerato viene finanziato solo dopo evidenza.
A5: Month | B5: M1 | C5: M2 | D5: M3 | E5: M4 | F5: M5 | G5: M6 | H5: M7 | I5: M8 | J5: M9 | K5: M10 | L5: M11 | M5: M12 | N5: M13 | O5: M14 | P5: M15 | Q5: M16 | R5: M17 | S5: M18 | T5: M19 | U5: M20 | V5: M21 | W5: M22 | X5: M23 | Y5: M24 | Z5: M25 | AA5: M26 | AB5: M27 | AC5: M28 | AD5: M29 | AE5: M30 | AF5: M31 | AG5: M32 | AH5: M33 | AI5: M34 | AJ5: M35 | AK5: M36
A6: Year | B6: Y1 | C6: Y1 | D6: Y1 | E6: Y1 | F6: Y1 | G6: Y1 | H6: Y1 | I6: Y1 | J6: Y1 | K6: Y1 | L6: Y1 | M6: Y1 | N6: Y2 | O6: Y2 | P6: Y2 | Q6: Y2 | R6: Y2 | S6: Y2 | T6: Y2 | U6: Y2 | V6: Y2 | W6: Y2 | X6: Y2 | Y6: Y2 | Z6: Y3 | AA6: Y3 | AB6: Y3 | AC6: Y3 | AD6: Y3 | AE6: Y3 | AF6: Y3 | AG6: Y3 | AH6: Y3 | AI6: Y3 | AJ6: Y3 | AK6: Y3
A7: Stage | B7: Relaunch | C7: Relaunch | D7: Relaunch | E7: Beta build | F7: Beta build | G7: Gate M6 | H7: AI launch | I7: AI launch | J7: AI launch | K7: Scale test | L7: Scale test | M7: Scale test | N7: Scale | O7: Scale | P7: Scale | Q7: Scale | R7: Scale | S7: Scale | T7: Scale | U7: Scale | V7: Scale | W7: Scale | X7: Scale | Y7: Scale | Z7: Scale | AA7: Scale | AB7: Scale | AC7: Scale | AD7: Scale | AE7: Scale | AF7: Scale | AG7: Scale | AH7: Scale | AI7: Scale | AJ7: Scale | AK7: Scale
A9: MONTHLY CASH ROLL-FORWARD
A10: Opening cash | B10: =Assumptions!$C$47 -> 300000 | C10: =B12 -> 282268.12 | D10: =C12 -> 264556.23 | E10: =D12 -> 244364.55 | F10: =E12 -> 225456.95 | G10: =F12 -> 207217.51 | H10: =G12 -> 189595.08 | I10: =H12 -> 187444.52 | J10: =I12 -> 186320.73 | ... AK10: =AJ12 -> 588928.45
A11: Net cash flow | B11: ='P&L 36 Months'!B27 -> -17731.884 | C11: ='P&L 36 Months'!C27 -> -17711.884 | D11: ='P&L 36 Months'!D27 -> -20191.684 | E11: ='P&L 36 Months'!E27 -> -18907.594 | F11: ='P&L 36 Months'!F27 -> -18239.442 | G11: ='P&L 36 Months'!G27 -> -17622.436 | H11: ='P&L 36 Months'!H27 -> -2150.5598 | I11: ='P&L 36 Months'!I27 -> -1123.7863 | ... AK11: ='P&L 36 Months'!AK27 -> 26121.554
A12: Closing cash | B12: =SUM(B10:B11) -> 282268.12 | C12: =SUM(C10:C11) -> 264556.23 | D12: =SUM(D10:D11) -> 244364.55 | E12: =SUM(E10:E11) -> 225456.95 | F12: =SUM(F10:F11) -> 207217.51 | G12: =SUM(G10:G11) -> 189595.08 | H12: =SUM(H10:H11) -> 187444.52 | I12: =SUM(I10:I11) -> 186320.73 | ... AK12: =SUM(AK10:AK11) -> 615050.01
A13: Cumulative cash flow before financing | B13: =B11 -> -17731.884 | C13: =B13+C11 -> -35443.768 | D13: =C13+D11 -> -55635.452 | E13: =D13+E11 -> -74543.046 | F13: =E13+F11 -> -92782.488 | G13: =F13+G11 -> -110404.92 | H13: =G13+H11 -> -112555.48 | I13: =H13+I11 -> -113679.27 | J13: =I13+J11 -> -108356.05 | ... AK13: =AJ13+AK11 -> 315050.01
A16: FUNDING ADEQUACY
A17: Round under evaluation | B17: =Assumptions!$C$47 -> 300000
A18: Funding required through M12 — before contingency | B18: =-MIN(0,MIN(B13:M13)) -> 113679.27
A19: Contingency reserve | B19: =Assumptions!$C$48 -> 15000
A20: Initial 12-month funding requirement | B20: =SUM(B18:B19) -> 128679.27
A21: Surplus / (gap) vs €300k at M12 | B21: =B17-B20 -> 171320.73
A22: Closing cash at M12 | B22: =M12 -> 209357.95
A23: Funding required through M18 | B23: =-MIN(0,MIN(B13:S13))+Assumptions!$C$48 -> 128679.27
A24: Headroom / (gap) vs initial €300k at M18 | B24: =B17-B23 -> 171320.73
A25: Worst cash month | B25: =INDEX(B5:AK5,1,MATCH(MIN(B12:AK12),B12:AK12,0)) -> M8
A26: Minimum modeled cash balance | B26: =MIN(B12:AK12) -> 186320.73
A27: Verdict | B27: =IF(B21<0,"€300k insufficient for the Base proof plan",IF(B24<0,"Base is funded; prepare follow-on before M18","Base is funded with headroom; Accelerated deployment remains conditional on gates")) -> Base is funded with headroom; Accelerated deployment remains conditional on gates

Sheet Scenarios
A1: TUPENSACI | Scenario & Sensitivity v3.0
A2: Il Base è il piano integrato. L'Accelerato è modellato separatamente e richiede evidenza osservata, non la sola presenza di un'agenzia.
A4: SCENARIO UNIT ECONOMICS
A5: Metric | B5: Downside | C5: Base | D5: Upside | E5: Interpretation
A6: Monthly churn | B6: =Assumptions!C12 -> 0.1 | C6: =Assumptions!D12 -> 0.08 | D6: =Assumptions!E12 -> 0.05 | E6: Retention risk
A7: Direct AI blended CAC | B7: =Assumptions!C16 -> 30 | C7: =Assumptions!D16 -> 22.4 | D7: =Assumptions!E16 -> 15 | E7: Acquisition efficiency
A8: Monthly contribution / user | B8: =Assumptions!$C$37 -> 5.0204918 | C8: =Assumptions!$C$37 -> 5.0204918 | D8: =Assumptions!$C$37 -> 5.0204918 | E8: Confirmed economic model
A9: Illustrative LTV | B9: =B8/B6 -> 50.204918 | C9: =C8/C6 -> 62.756148 | D9: =D8/D6 -> 100.40984 | E9: Contribution / churn
A10: LTV / CAC | B10: =B9/B7 -> 1.6734973 | C10: =C9/C7 -> 2.8016137 | D10: =D9/D7 -> 6.6939891 | E10: Base pricing now targets >2x; paid scale requires ≥3x observed
A11: CAC payback (months) | B11: =B7/B8 -> 5.9755102 | C11: =C7/C8 -> 4.4617143 | D11: =D7/D8 -> 2.9877551 | E11: Months to recover CAC
A14: LTV / CAC SENSITIVITY
A15: Monthly churn ↓ / CAC → | B15: 15 | C15: 22.4 | D15: 30 | E15: Reading
A16: 0.05 | B16: =(Assumptions!$C$37/$A16)/B$15 -> 6.6939891 | C16: =(Assumptions!$C$37/$A16)/C$15 -> 4.482582 | D16: =(Assumptions!$C$37/$A16)/D$15 -> 3.3469945 | E16: Target retention
A17: 0.08 | B17: =(Assumptions!$C$37/$A17)/B$15 -> 4.1837432 | C17: =(Assumptions!$C$37/$A17)/C$15 -> 2.8016137 | D17: =(Assumptions!$C$37/$A17)/D$15 -> 2.0918716 | E17: Base churn
A18: 0.1 | B18: =(Assumptions!$C$37/$A18)/B$15 -> 3.3469945 | C18: =(Assumptions!$C$37/$A18)/C$15 -> 2.241291 | D18: =(Assumptions!$C$37/$A18)/D$15 -> 1.6734973 | E18: Downside churn
A21: CROSS-SELL LOGIC
A22: Lever | B22: Downside | C22: Base | D22: Upside | E22: Why it matters
A23: Historical customers converted | B23: =Assumptions!$C$42*Assumptions!C9 -> 210 | C23: =Assumptions!$C$42*Assumptions!D9 -> 420 | D23: =Assumptions!$C$42*Assumptions!E9 -> 840 | E23: Low-cost launch audience
A24: AI attach on 1,000 new physical buyers | B24: =1000*Assumptions!C10 -> 70 | C24: =1000*Assumptions!D10 -> 100 | D24: =1000*Assumptions!E10 -> 150 | E24: Built-in distribution at product purchase
A25: Annual payment share | B25: =Assumptions!C11 -> 0.25 | C25: =Assumptions!D11 -> 0.3 | D25: =Assumptions!E11 -> 0.35 | E25: Cash collected upfront
A26: Physical repeat / cross-sell | B26: =Assumptions!C14 -> 0.0893 | C26: =Assumptions!D14 -> 0.1 | D26: =Assumptions!E14 -> 0.15 | E26: Expands LTV beyond one workbook
A29: BASE / ACCELERATED BRANCH
A30: Metric | B30: Current branch | C30: Value | D30: Test rule | E30: Scale rule | F30: Decision
A31: Branch | B31: =Assumptions!E5 -> Test | D31: Validate willingness to pay | E31: Scale only after observed economics | F31: Branch is selected manually
A32: Effective blended CAC | B32: =Assumptions!C68 -> 22.4 | D32: Base ≈ €22.40 | E32: Warm €15; broad launch €28; scale ≤€20 | F32: Do not infer improvement from agency presence
A33: Effective monthly churn | B33: =Assumptions!C69 -> 0.08 | D33: Base 8% | E33: ≤6% observed | F33: Cohort retention is the binding metric
A34: LTV / CAC | B34: =Assumptions!C70 -> 2.8016137 | D34: >2x under new pricing | E34: ≥3x observed | F34: Gate uses contribution LTV
A35: Paid budget logic | B35: Base: capped acquisition | C35: Accelerated: €70k M7–M18, then only if gates pass | D35: ≈2k M12 / ≈4k M24 | E35: ≈3.2k M12 / ≈4.7–5k M24 | F35: See Accelerated Case and Commercial Funnel sheets
A36: Scale authorization | B36: =IF(AND(Assumptions!C68<=20,Assumptions!C69<=6%,Assumptions!C70>=3),"PASS","NOT YET") -> NOT YET | D36: No automatic scale | E36: All three conditions required | F36: Board/investor decision after evidence

Sheet Accelerated Case
A1: TUPENSACI | Base vs Accelerated AI
A2: Il Base resta il piano operativo. L'Accelerato è un'opzione subordinata a CAC ≤ €20, churn ≤ 6%, qualità/safety accettabili e reale ritorno d'uso.
A4: SCENARIO COMPARISON
A5: KPI | B5: Base | C5: Accelerated | D5: Delta | E5: Gate / interpretation | F5: Base source | G5: Accelerated source
A6: Active paid users — M12 | B6: ='AI Cohorts'!M26 -> 2079.2872 | C6: =M30 -> 3261.8358 | D6: =C6-B6 -> 1182.5486 | E6: Target 3,000–3,500 only after gates | F6: Base cohorts | G6: Warm + broad scale
A7: Active paid users — M24 | B7: ='AI Cohorts'!Y26 -> 3999.939 | C7: =Y30 -> 4736.0629 | D7: =C7-B7 -> 736.1239 | E7: Around 5,000, not an automatic commitment | F7: Base cohorts | G7: Conditional scale
A8: AI revenue — Year 1 | B8: =SUM('AI Cohorts'!B32:M32) -> 121142.09 | C8: =SUM(B34:M34) -> 170189.66 | D8: =C8-B8 -> 49047.567 | E8: Pricing €9 / €89 / €69 | F8: Integrated Base | G8: Accelerated cohorts
A9: AI revenue — Year 2 | B9: =SUM('AI Cohorts'!N32:Y32) -> 337997.88 | C9: =SUM(N34:Y34) -> 422019.19 | D9: =C9-B9 -> 84021.314 | E9: Scale only if retention holds | F9: Integrated Base | G9: Accelerated cohorts
A10: Paid AI media — M7–M18 | B10: =SUM('AI Cohorts'!H13:S13) -> 48000 | C10: =SUM(H16:S17) -> 70000 | D10: =C10-B10 -> 22000 | E10: Accelerated envelope = €70k | F10: Base paid test | G10: €25k warm + €45k broad
A11: Monthly churn | B11: =Assumptions!D12 -> 0.08 | C11: =Assumptions!C67 -> 0.06 | D11: =C11-B11 -> -0.02 | E11: Scale requires ≤6% observed | F11: Base assumption | G11: Scale gate
A12: ACCELERATED COHORT ENGINE — 24 MONTHS
A13: Metric | B13: M1 | C13: M2 | D13: M3 | E13: M4 | F13: M5 | G13: M6 | H13: M7 | I13: M8 | J13: M9 | K13: M10 | L13: M11 | M13: M12 | N13: M13 | O13: M14 | P13: M15 | Q13: M16 | R13: M17 | S13: M18 | T13: M19 | U13: M20 | V13: M21 | W13: M22 | X13: M23 | Y13: M24
A14: Historical CRM conversions — organic | B14: =IF(AND(1>=Assumptions!$C$49,1<Assumptions!$C$49+Assumptions!$C$52),Assumptions!$C$42*Assumptions!$D$9/Assumptions!$C$52,0) -> 0 | C14: =IF(AND(2>=Assumptions!$C$49,2<Assumptions!$C$49+Assumptions!$C$52),Assumptions!$C$42*Assumptions!$D$9/Assumptions!$C$52,0) -> 0 | D14: =IF(AND(3>=Assumptions!$C$49,3<Assumptions!$C$49+Assumptions!$C$52),Assumptions!$C$42*Assumptions!$D$9/Assumptions!$C$52,0) -> 0 | E14: =IF(AND(4>=Assumptions!$C$49,4<Assumptions!$C$49+Assumptions!$C$52),Assumptions!$C$42*Assumptions!$D$9/Assumptions!$C$52,0) -> 70 | F14: =IF(AND(5>=Assumptions!$C$49,5<Assumptions!$C$49+Assumptions!$C$52),Assumptions!$C$42*Assumptions!$D$9/Assumptions!$C$52,0) -> 70 | G14: =IF(AND(6>=Assumptions!$C$49,6<Assumptions!$C$49+Assumptions!$C$52),Assumptions!$C$42*Assumptions!$D$9/Assumptions!$C$52,0) -> 70 | H14: =IF(AND(7>=Assumptions!$C$49,7<Assumptions!$C$49+Assumptions!$C$52),Assumptions!$C$42*Assumptions!$D$9/Assumptions!$C$52,0) -> 70 | I14: =IF(AND(8>=Assumptions!$C$49,8<Assumptions!$C$49+Assumptions!$C$52),Assumptions!$C$42*Assumptions!$D$9/Assumptions!$C$52,0) -> 70 | J14: =IF(AND(9>=Assumptions!$C$49,9<Assumptions!$C$49+Assumptions!$C$52),Assumptions!$C$42*Assumptions!$D$9/Assumptions!$C$52,0) -> 70 | K14: =IF(AND(10>=Assumptions!$C$49,10<Assumptions!$C$49+Assumptions!$C$52),Assumptions!$C$42*Assumptions!$D$9/Assumptions!$C$52,0) -> 0 | L14: =IF(AND(11>=Assumptions!$C$49,11<Assumptions!$C$49+Assumptions!$C$52),Assumptions!$C$42*Assumptions!$D$9/Assumptions!$C$52,0) -> 0 | M14: =IF(AND(12>=Assumptions!$C$49,12<Assumptions!$C$49+Assumptions!$C$52),Assumptions!$C$42*Assumptions!$D$9/Assumptions!$C$52,0) -> 0 | N14: =IF(AND(13>=Assumptions!$C$49,13<Assumptions!$C$49+Assumptions!$C$52),Assumptions!$C$42*Assumptions!$D$9/Assumptions!$C$52,0) -> 0 | O14: =IF(AND(14>=Assumptions!$C$49,14<Assumptions!$C$49+Assumptions!$C$52),Assumptions!$C$42*Assumptions!$D$9/Assumptions!$C$52,0) -> 0 | P14: =IF(AND(15>=Assumptions!$C$49,15<Assumptions!$C$49+Assumptions!$C$52),Assumptions!$C$42*Assumptions!$D$9/Assumptions!$C$52,0) -> 0 | Q14: =IF(AND(16>=Assumptions!$C$49,16<Assumptions!$C$49+Assumptions!$C$52),Assumptions!$C$42*Assumptions!$D$9/Assumptions!$C$52,0) -> 0 | R14: =IF(AND(17>=Assumptions!$C$49,17<Assumptions!$C$49+Assumptions!$C$52),Assumptions!$C$42*Assumptions!$D$9/Assumptions!$C$52,0) -> 0 | S14: =IF(AND(18>=Assumptions!$C$49,18<Assumptions!$C$49+Assumptions!$C$52),Assumptions!$C$42*Assumptions!$D$9/Assumptions!$C$52,0) -> 0 | T14: =IF(AND(19>=Assumptions!$C$49,19<Assumptions!$C$49+Assumptions!$C$52),Assumptions!$C$42*Assumptions!$D$9/Assumptions!$C$52,0) -> 0 | U14: =IF(AND(20>=Assumptions!$C$49,20<Assumptions!$C$49+Assumptions!$C$52),Assumptions!$C$42*Assumptions!$D$9/Assumptions!$C$52,0) -> 0 | V14: =IF(AND(21>=Assumptions!$C$49,21<Assumptions!$C$49+Assumptions!$C$52),Assumptions!$C$42*Assumptions!$D$9/Assumptions!$C$52,0) -> 0 | W14: =IF(AND(22>=Assumptions!$C$49,22<Assumptions!$C$49+Assumptions!$C$52),Assumptions!$C$42*Assumptions!$D$9/Assumptions!$C$52,0) -> 0 | X14: =IF(AND(23>=Assumptions!$C$49,23<Assumptions!$C$49+Assumptions!$C$52),Assumptions!$C$42*Assumptions!$D$9/Assumptions!$C$52,0) -> 0 | Y14: =IF(AND(24>=Assumptions!$C$49,24<Assumptions!$C$49+Assumptions!$C$52),Assumptions!$C$42*Assumptions!$D$9/Assumptions!$C$52,0) -> 0
A15: Physical buyer AI attach | B15: =IF(1<Assumptions!$C$49,0,'Physical Business'!B15*Assumptions!$D$10) -> 0 | C15: =IF(2<Assumptions!$C$49,0,'Physical Business'!C15*Assumptions!$D$10) -> 0 | D15: =IF(3<Assumptions!$C$49,0,'Physical Business'!D15*Assumptions!$D$10) -> 0 | E15: =IF(4<Assumptions!$C$49,0,'Physical Business'!E15*Assumptions!$D$10) -> 79.868227 | F15: =IF(5<Assumptions!$C$49,0,'Physical Business'!F15*Assumptions!$D$10) -> 79.971257 | G15: =IF(6<Assumptions!$C$49,0,'Physical Business'!G15*Assumptions!$D$10) -> 80.075318 | H15: =IF(7<Assumptions!$C$49,0,'Physical Business'!H15*Assumptions!$D$10) -> 106.26738 | I15: =IF(8<Assumptions!$C$49,0,'Physical Business'!I15*Assumptions!$D$10) -> 106.37353 | J15: =IF(9<Assumptions!$C$49,0,'Physical Business'!J15*Assumptions!$D$10) -> 106.48074 | K15: =IF(10<Assumptions!$C$49,0,'Physical Business'!K15*Assumptions!$D$10) -> 106.69731 | L15: =IF(11<Assumptions!$C$49,0,'Physical Business'!L15*Assumptions!$D$10) -> 106.91822 | M15: =IF(12<Assumptions!$C$49,0,'Physical Business'!M15*Assumptions!$D$10) -> 107.14354 | N15: =IF(13<Assumptions!$C$49,0,'Physical Business'!N15*Assumptions!$D$10) -> 116.06902 | O15: =IF(14<Assumptions!$C$49,0,'Physical Business'!O15*Assumptions!$D$10) -> 116.30344 | P15: =IF(15<Assumptions!$C$49,0,'Physical Business'!P15*Assumptions!$D$10) -> 116.54255 | Q15: =IF(16<Assumptions!$C$49,0,'Physical Business'!Q15*Assumptions!$D$10) -> 116.78645 | R15: =IF(17<Assumptions!$C$49,0,'Physical Business'!R15*Assumptions!$D$10) -> 117.03522 | S15: =IF(18<Assumptions!$C$49,0,'Physical Business'!S15*Assumptions!$D$10) -> 117.28897 | T15: =IF(19<Assumptions!$C$49,0,'Physical Business'!T15*Assumptions!$D$10) -> 117.54779 | U15: =IF(20<Assumptions!$C$49,0,'Physical Business'!U15*Assumptions!$D$10) -> 117.81179 | V15: =IF(21<Assumptions!$C$49,0,'Physical Business'!V15*Assumptions!$D$10) -> 118.08107 | W15: =IF(22<Assumptions!$C$49,0,'Physical Business'!W15*Assumptions!$D$10) -> 118.35573 | X15: =IF(23<Assumptions!$C$49,0,'Physical Business'!X15*Assumptions!$D$10) -> 118.63589 | Y15: =IF(24<Assumptions!$C$49,0,'Physical Business'!Y15*Assumptions!$D$10) -> 118.92165
A16: Warm/community media | B16: =IF(AND(1>=7,1<=12),Assumptions!$C$85/6,0) -> 0 | C16: =IF(AND(2>=7,2<=12),Assumptions!$C$85/6,0) -> 0 | D16: =IF(AND(3>=7,3<=12),Assumptions!$C$85/6,0) -> 0 | E16: =IF(AND(4>=7,4<=12),Assumptions!$C$85/6,0) -> 0 | F16: =IF(AND(5>=7,5<=12),Assumptions!$C$85/6,0) -> 0 | G16: =IF(AND(6>=7,6<=12),Assumptions!$C$85/6,0) -> 0 | H16: =IF(AND(7>=7,7<=12),Assumptions!$C$85/6,0) -> 4166.6667 | I16: =IF(AND(8>=7,8<=12),Assumptions!$C$85/6,0) -> 4166.6667 | J16: =IF(AND(9>=7,9<=12),Assumptions!$C$85/6,0) -> 4166.6667 | K16: =IF(AND(10>=7,10<=12),Assumptions!$C$85/6,0) -> 4166.6667 | L16: =IF(AND(11>=7,11<=12),Assumptions!$C$85/6,0) -> 4166.6667 | M16: =IF(AND(12>=7,12<=12),Assumptions!$C$85/6,0) -> 4166.6667 | N16: =IF(AND(13>=7,13<=12),Assumptions!$C$85/6,0) -> 0 | O16: =IF(AND(14>=7,14<=12),Assumptions!$C$85/6,0) -> 0 | P16: =IF(AND(15>=7,15<=12),Assumptions!$C$85/6,0) -> 0 | Q16: =IF(AND(16>=7,16<=12),Assumptions!$C$85/6,0) -> 0 | R16: =IF(AND(17>=7,17<=12),Assumptions!$C$85/6,0) -> 0 | S16: =IF(AND(18>=7,18<=12),Assumptions!$C$85/6,0) -> 0 | T16: =IF(AND(19>=7,19<=12),Assumptions!$C$85/6,0) -> 0 | U16: =IF(AND(20>=7,20<=12),Assumptions!$C$85/6,0) -> 0 | V16: =IF(AND(21>=7,21<=12),Assumptions!$C$85/6,0) -> 0 | W16: =IF(AND(22>=7,22<=12),Assumptions!$C$85/6,0) -> 0 | X16: =IF(AND(23>=7,23<=12),Assumptions!$C$85/6,0) -> 0 | Y16: =IF(AND(24>=7,24<=12),Assumptions!$C$85/6,0) -> 0
A17: Broad media | B17: =IF(AND(1>=7,1<=12),Assumptions!$C$86/6,IF(AND(1>=13,1<=18),Assumptions!$C$87/6,IF(1>=19,Assumptions!$C$88,0))) -> 0 | C17: =IF(AND(2>=7,2<=12),Assumptions!$C$86/6,IF(AND(2>=13,2<=18),Assumptions!$C$87/6,IF(2>=19,Assumptions!$C$88,0))) -> 0 | D17: =IF(AND(3>=7,3<=12),Assumptions!$C$86/6,IF(AND(3>=13,3<=18),Assumptions!$C$87/6,IF(3>=19,Assumptions!$C$88,0))) -> 0 | E17: =IF(AND(4>=7,4<=12),Assumptions!$C$86/6,IF(AND(4>=13,4<=18),Assumptions!$C$87/6,IF(4>=19,Assumptions!$C$88,0))) -> 0 | F17: =IF(AND(5>=7,5<=12),Assumptions!$C$86/6,IF(AND(5>=13,5<=18),Assumptions!$C$87/6,IF(5>=19,Assumptions!$C$88,0))) -> 0 | G17: =IF(AND(6>=7,6<=12),Assumptions!$C$86/6,IF(AND(6>=13,6<=18),Assumptions!$C$87/6,IF(6>=19,Assumptions!$C$88,0))) -> 0 | H17: =IF(AND(7>=7,7<=12),Assumptions!$C$86/6,IF(AND(7>=13,7<=18),Assumptions!$C$87/6,IF(7>=19,Assumptions!$C$88,0))) -> 2833.3333 | I17: =IF(AND(8>=7,8<=12),Assumptions!$C$86/6,IF(AND(8>=13,8<=18),Assumptions!$C$87/6,IF(8>=19,Assumptions!$C$88,0))) -> 2833.3333 | J17: =IF(AND(9>=7,9<=12),Assumptions!$C$86/6,IF(AND(9>=13,9<=18),Assumptions!$C$87/6,IF(9>=19,Assumptions!$C$88,0))) -> 2833.3333 | K17: =IF(AND(10>=7,10<=12),Assumptions!$C$86/6,IF(AND(10>=13,10<=18),Assumptions!$C$87/6,IF(10>=19,Assumptions!$C$88,0))) -> 2833.3333 | L17: =IF(AND(11>=7,11<=12),Assumptions!$C$86/6,IF(AND(11>=13,11<=18),Assumptions!$C$87/6,IF(11>=19,Assumptions!$C$88,0))) -> 2833.3333 | M17: =IF(AND(12>=7,12<=12),Assumptions!$C$86/6,IF(AND(12>=13,12<=18),Assumptions!$C$87/6,IF(12>=19,Assumptions!$C$88,0))) -> 2833.3333 | N17: =IF(AND(13>=7,13<=12),Assumptions!$C$86/6,IF(AND(13>=13,13<=18),Assumptions!$C$87/6,IF(13>=19,Assumptions!$C$88,0))) -> 4666.6667 | O17: =IF(AND(14>=7,14<=12),Assumptions!$C$86/6,IF(AND(14>=13,14<=18),Assumptions!$C$87/6,IF(14>=19,Assumptions!$C$88,0))) -> 4666.6667 | P17: =IF(AND(15>=7,15<=12),Assumptions!$C$86/6,IF(AND(15>=13,15<=18),Assumptions!$C$87/6,IF(15>=19,Assumptions!$C$88,0))) -> 4666.6667 | Q17: =IF(AND(16>=7,16<=12),Assumptions!$C$86/6,IF(AND(16>=13,16<=18),Assumptions!$C$87/6,IF(16>=19,Assumptions!$C$88,0))) -> 4666.6667 | R17: =IF(AND(17>=7,17<=12),Assumptions!$C$86/6,IF(AND(17>=13,17<=18),Assumptions!$C$87/6,IF(17>=19,Assumptions!$C$88,0))) -> 4666.6667 | S17: =IF(AND(18>=7,18<=12),Assumptions!$C$86/6,IF(AND(18>=13,18<=18),Assumptions!$C$87/6,IF(18>=19,Assumptions!$C$88,0))) -> 4666.6667 | T17: =IF(AND(19>=7,19<=12),Assumptions!$C$86/6,IF(AND(19>=13,19<=18),Assumptions!$C$87/6,IF(19>=19,Assumptions!$C$88,0))) -> 5000 | U17: =IF(AND(20>=7,20<=12),Assumptions!$C$86/6,IF(AND(20>=13,20<=18),Assumptions!$C$87/6,IF(20>=19,Assumptions!$C$88,0))) -> 5000 | V17: =IF(AND(21>=7,21<=12),Assumptions!$C$86/6,IF(AND(21>=13,21<=18),Assumptions!$C$87/6,IF(21>=19,Assumptions!$C$88,0))) -> 5000 | W17: =IF(AND(22>=7,22<=12),Assumptions!$C$86/6,IF(AND(22>=13,22<=18),Assumptions!$C$87/6,IF(22>=19,Assumptions!$C$88,0))) -> 5000 | X17: =IF(AND(23>=7,23<=12),Assumptions!$C$86/6,IF(AND(23>=13,23<=18),Assumptions!$C$87/6,IF(23>=19,Assumptions!$C$88,0))) -> 5000 | Y17: =IF(AND(24>=7,24<=12),Assumptions!$C$86/6,IF(AND(24>=13,24<=18),Assumptions!$C$87/6,IF(24>=19,Assumptions!$C$88,0))) -> 5000
A18: Warm paid users | B18: =B16/Assumptions!$C$89 -> 0 | C18: =C16/Assumptions!$C$89 -> 0 | D18: =D16/Assumptions!$C$89 -> 0 | E18: =E16/Assumptions!$C$89 -> 0 | F18: =F16/Assumptions!$C$89 -> 0 | G18: =G16/Assumptions!$C$89 -> 0 | H18: =H16/Assumptions!$C$89 -> 277.77778 | I18: =I16/Assumptions!$C$89 -> 277.77778 | ... Y18: =Y16/Assumptions!$C$89 -> 0
A19: Broad paid users | B19: =B17/IF(1<19,Assumptions!$C$90,Assumptions!$C$91) -> 0 | C19: =C17/IF(2<19,Assumptions!$C$90,Assumptions!$C$91) -> 0 | D19: =D17/IF(3<19,Assumptions!$C$90,Assumptions!$C$91) -> 0 | E19: =E17/IF(4<19,Assumptions!$C$90,Assumptions!$C$91) -> 0 | F19: =F17/IF(5<19,Assumptions!$C$90,Assumptions!$C$91) -> 0 | G19: =G17/IF(6<19,Assumptions!$C$90,Assumptions!$C$91) -> 0 | H19: =H17/IF(7<19,Assumptions!$C$90,Assumptions!$C$91) -> 101.19048 | I19: =I17/IF(8<19,Assumptions!$C$90,Assumptions!$C$91) -> 101.19048 | J19: =J17/IF(9<19,Assumptions!$C$90,Assumptions!$C$91) -> 101.19048 | K19: =K17/IF(10<19,Assumptions!$C$90,Assumptions!$C$91) -> 101.19048 | L19: =L17/IF(11<19,Assumptions!$C$90,Assumptions!$C$91) -> 101.19048 | M19: =M17/IF(12<19,Assumptions!$C$90,Assumptions!$C$91) -> 101.19048 | N19: =N17/IF(13<19,Assumptions!$C$90,Assumptions!$C$91) -> 166.66667 | O19: =O17/IF(14<19,Assumptions!$C$90,Assumptions!$C$91) -> 166.66667 | P19: =P17/IF(15<19,Assumptions!$C$90,Assumptions!$C$91) -> 166.66667 | Q19: =Q17/IF(16<19,Assumptions!$C$90,Assumptions!$C$91) -> 166.66667 | R19: =R17/IF(17<19,Assumptions!$C$90,Assumptions!$C$91) -> 166.66667 | S19: =S17/IF(18<19,Assumptions!$C$90,Assumptions!$C$91) -> 166.66667 | T19: =T17/IF(19<19,Assumptions!$C$90,Assumptions!$C$91) -> 250 | U19: =U17/IF(20<19,Assumptions!$C$90,Assumptions!$C$91) -> 250 | V19: =V17/IF(21<19,Assumptions!$C$90,Assumptions!$C$91) -> 250 | W19: =W17/IF(22<19,Assumptions!$C$90,Assumptions!$C$91) -> 250 | X19: =X17/IF(23<19,Assumptions!$C$90,Assumptions!$C$91) -> 250 | Y19: =Y17/IF(24<19,Assumptions!$C$90,Assumptions!$C$91) -> 250
A20: Beta direct users | B20: =IF(AND(1>=Assumptions!$C$49,1<=Assumptions!$C$50),Assumptions!$D$20,0) -> 0 | C20: =IF(AND(2>=Assumptions!$C$49,2<=Assumptions!$C$50),Assumptions!$D$20,0) -> 0 | D20: =IF(AND(3>=Assumptions!$C$49,3<=Assumptions!$C$50),Assumptions!$D$20,0) -> 0 | E20: =IF(AND(4>=Assumptions!$C$49,4<=Assumptions!$C$50),Assumptions!$D$20,0) -> 50 | F20: =IF(AND(5>=Assumptions!$C$49,5<=Assumptions!$C$50),Assumptions!$D$20,0) -> 50 | G20: =IF(AND(6>=Assumptions!$C$49,6<=Assumptions!$C$50),Assumptions!$D$20,0) -> 50 | H20: =IF(AND(7>=Assumptions!$C$49,7<=Assumptions!$C$50),Assumptions!$D$20,0) -> 0 | I20: =IF(AND(8>=Assumptions!$C$49,8<=Assumptions!$C$50),Assumptions!$D$20,0) -> 0 | J20: =IF(AND(9>=Assumptions!$C$49,9<=Assumptions!$C$50),Assumptions!$D$20,0) -> 0 | K20: =IF(AND(10>=Assumptions!$C$49,10<=Assumptions!$C$50),Assumptions!$D$20,0) -> 0 | L20: =IF(AND(11>=Assumptions!$C$49,11<=Assumptions!$C$50),Assumptions!$D$20,0) -> 0 | M20: =IF(AND(12>=Assumptions!$C$49,12<=Assumptions!$C$50),Assumptions!$D$20,0) -> 0 | N20: =IF(AND(13>=Assumptions!$C$49,13<=Assumptions!$C$50),Assumptions!$D$20,0) -> 0 | O20: =IF(AND(14>=Assumptions!$C$49,14<=Assumptions!$C$50),Assumptions!$D$20,0) -> 0 | P20: =IF(AND(15>=Assumptions!$C$49,15<=Assumptions!$C$50),Assumptions!$D$20,0) -> 0 | Q20: =IF(AND(16>=Assumptions!$C$49,16<=Assumptions!$C$50),Assumptions!$D$20,0) -> 0 | R20: =IF(AND(17>=Assumptions!$C$49,17<=Assumptions!$C$50),Assumptions!$D$20,0) -> 0 | S20: =IF(AND(18>=Assumptions!$C$49,18<=Assumptions!$C$50),Assumptions!$D$20,0) -> 0 | T20: =IF(AND(19>=Assumptions!$C$49,19<=Assumptions!$C$50),Assumptions!$D$20,0) -> 0 | U20: =IF(AND(20>=Assumptions!$C$49,20<=Assumptions!$C$50),Assumptions!$D$20,0) -> 0 | V20: =IF(AND(21>=Assumptions!$C$49,21<=Assumptions!$C$50),Assumptions!$D$20,0) -> 0 | W20: =IF(AND(22>=Assumptions!$C$49,22<=Assumptions!$C$50),Assumptions!$D$20,0) -> 0 | X20: =IF(AND(23>=Assumptions!$C$49,23<=Assumptions!$C$50),Assumptions!$D$20,0) -> 0 | Y20: =IF(AND(24>=Assumptions!$C$49,24<=Assumptions!$C$50),Assumptions!$D$20,0) -> 0
A21: Total new AI users | B21: =SUM(B14:B15,B18:B20) -> 0 | C21: =SUM(C14:C15,C18:C20) -> 0 | D21: =SUM(D14:D15,D18:D20) -> 0 | E21: =SUM(E14:E15,E18:E20) -> 199.86823 | F21: =SUM(F14:F15,F18:F20) -> 199.97126 | G21: =SUM(G14:G15,G18:G20) -> 200.07532 | H21: =SUM(H14:H15,H18:H20) -> 555.23563 | I21: =SUM(I14:I15,I18:I20) -> 555.34178 | ... Y21: =SUM(Y14:Y15,Y18:Y20) -> 368.92165
A22: Founding annual users (€69) | B22: =SUM(B14:B15,B18)*Assumptions!$D$11 -> 0 | C22: =SUM(C14:C15,C18)*Assumptions!$D$11 -> 0 | D22: =SUM(D14:D15,D18)*Assumptions!$D$11 -> 0 | E22: =SUM(E14:E15,E18)*Assumptions!$D$11 -> 44.960468 | F22: =SUM(F14:F15,F18)*Assumptions!$D$11 -> 44.991377 | G22: =SUM(G14:G15,G18)*Assumptions!$D$11 -> 45.022595 | H22: =SUM(H14:H15,H18)*Assumptions!$D$11 -> 136.21355 | I22: =SUM(I14:I15,I18)*Assumptions!$D$11 -> 136.24539 | ... Y22: =SUM(Y14:Y15,Y18)*Assumptions!$D$11 -> 35.676495
A23: Standard annual users (€89) | B23: =SUM(B19:B20)*Assumptions!$D$11 -> 0 | C23: =SUM(C19:C20)*Assumptions!$D$11 -> 0 | D23: =SUM(D19:D20)*Assumptions!$D$11 -> 0 | E23: =SUM(E19:E20)*Assumptions!$D$11 -> 15 | F23: =SUM(F19:F20)*Assumptions!$D$11 -> 15 | G23: =SUM(G19:G20)*Assumptions!$D$11 -> 15 | H23: =SUM(H19:H20)*Assumptions!$D$11 -> 30.357143 | I23: =SUM(I19:I20)*Assumptions!$D$11 -> 30.357143 | ... Y23: =SUM(Y19:Y20)*Assumptions!$D$11 -> 75
A24: New monthly users (€9) | B24: =B21*(1-Assumptions!$D$11) -> 0 | C24: =C21*(1-Assumptions!$D$11) -> 0 | D24: =D21*(1-Assumptions!$D$11) -> 0 | E24: =E21*(1-Assumptions!$D$11) -> 139.90776 | F24: =F21*(1-Assumptions!$D$11) -> 139.97988 | G24: =G21*(1-Assumptions!$D$11) -> 140.05272 | H24: =H21*(1-Assumptions!$D$11) -> 388.66494 | I24: =I21*(1-Assumptions!$D$11) -> 388.73925 | ... Y24: =Y21*(1-Assumptions!$D$11) -> 258.24516
A25: Annual renewals (€89) | B25: 0 | C25: 0 | D25: 0 | E25: 0 | F25: 0 | G25: 0 | H25: 0 | I25: 0 | J25: 0 | K25: 0 | L25: 0 | M25: 0 | N25: =SUM(B22:B23,B25)*Assumptions!$D$13 -> 0 | O25: =SUM(C22:C23,C25)*Assumptions!$D$13 -> 0 | P25: =SUM(D22:D23,D25)*Assumptions!$D$13 -> 0 | Q25: =SUM(E22:E23,E25)*Assumptions!$D$13 -> 26.982211 | R25: =SUM(F22:F23,F25)*Assumptions!$D$13 -> 26.99612 | S25: =SUM(G22:G23,G25)*Assumptions!$D$13 -> 27.010168 | T25: =SUM(H22:H23,H25)*Assumptions!$D$13 -> 74.95681 | U25: =SUM(I22:I23,I25)*Assumptions!$D$13 -> 74.97114 | ... Y25: =SUM(M22:M23,M25)*Assumptions!$D$13 -> 65.625092
A26: Opening active monthly users | B26: 0 | C26: =B28 -> 0 | D26: =C28 -> 0 | E26: =D28 -> 0 | F26: =E28 -> 139.90776 | G26: =F28 -> 271.49317 | H26: =G28 -> 395.25631 | I26: =H28 -> 760.20587 | J26: =I28 -> 1103.3328 | ... Y26: =X28 -> 2981.1885
A27: Monthly churned users | B27: =-B26*Assumptions!$C$67 -> 0 | C27: =-C26*Assumptions!$C$67 -> 0 | D27: =-D26*Assumptions!$C$67 -> 0 | E27: =-E26*Assumptions!$C$67 -> 0 | F27: =-F26*Assumptions!$C$67 -> -8.3944656 | G27: =-G26*Assumptions!$C$67 -> -16.28959 | H27: =-H26*Assumptions!$C$67 -> -23.715378 | I27: =-I26*Assumptions!$C$67 -> -45.612352 | ... Y27: =-Y26*Assumptions!$C$67 -> -178.87131
A28: Closing active monthly users | B28: =SUM(B26:B27,B24) -> 0 | C28: =SUM(C26:C27,C24) -> 0 | D28: =SUM(D26:D27,D24) -> 0 | E28: =SUM(E26:E27,E24) -> 139.90776 | F28: =SUM(F26:F27,F24) -> 271.49317 | G28: =SUM(G26:G27,G24) -> 395.25631 | H28: =SUM(H26:H27,H24) -> 760.20587 | I28: =SUM(I26:I27,I24) -> 1103.3328 | ... Y28: =SUM(Y26:Y27,Y24) -> 3060.5623
A29: Active annual users | B29: =SUM(B22:B23)+SUM(B25) -> 0 | C29: =SUM(B22:C23)+SUM(B25:C25) -> 0 | D29: =SUM(B22:D23)+SUM(B25:D25) -> 0 | E29: =SUM(B22:E23)+SUM(B25:E25) -> 59.960468 | F29: =SUM(B22:F23)+SUM(B25:F25) -> 119.95185 | G29: =SUM(B22:G23)+SUM(B25:G25) -> 179.97444 | H29: =SUM(B22:H23)+SUM(B25:H25) -> 346.54513 | I29: =SUM(B22:I23)+SUM(B25:I25) -> 513.14766 | J29: =SUM(B22:J23)+SUM(B25:J25) -> 679.78236 | K29: =SUM(B22:K23)+SUM(B25:K25) -> 825.48203 | L29: =SUM(B22:L23)+SUM(B25:L25) -> 971.24797 | M29: =SUM(B22:M23)+SUM(B25:M25) -> 1117.0815 | N29: =SUM(C22:N23)+SUM(C25:N25) -> 1201.9022 | O29: =SUM(D22:O23)+SUM(D25:O25) -> 1286.7932 | P29: =SUM(E22:P23)+SUM(E25:P25) -> 1371.756 | Q29: =SUM(F22:Q23)+SUM(F25:Q25) -> 1423.8137 | R29: =SUM(G22:R23)+SUM(G25:R25) -> 1475.929 | S29: =SUM(H22:S23)+SUM(H25:S25) -> 1528.1033 | T29: =SUM(I22:T23)+SUM(I25:T25) -> 1546.7537 | ... Y29: =SUM(N22:Y23)+SUM(N25:Y25) -> 1675.5005
A30: Total active AI users | B30: =SUM(B28:B29) -> 0 | C30: =SUM(C28:C29) -> 0 | D30: =SUM(D28:D29) -> 0 | E30: =SUM(E28:E29) -> 199.86823 | F30: =SUM(F28:F29) -> 391.44502 | G30: =SUM(G28:G29) -> 575.23075 | H30: =SUM(H28:H29) -> 1106.751 | I30: =SUM(I28:I29) -> 1616.4804 | ... Y30: =SUM(Y28:Y29) -> 4736.0629
A31: Monthly subscription revenue | B31: =B28*Assumptions!$C$29 -> 0 | C31: =C28*Assumptions!$C$29 -> 0 | D31: =D28*Assumptions!$C$29 -> 0 | E31: =E28*Assumptions!$C$29 -> 1259.1698 | F31: =F28*Assumptions!$C$29 -> 2443.4386 | G31: =G28*Assumptions!$C$29 -> 3557.3068 | H31: =H28*Assumptions!$C$29 -> 6841.8528 | I31: =I28*Assumptions!$C$29 -> 9929.9949 | ... Y31: =Y28*Assumptions!$C$29 -> 27545.061
A32: Founding annual bookings | B32: =B22*Assumptions!$C$31 -> 0 | C32: =C22*Assumptions!$C$31 -> 0 | D32: =D22*Assumptions!$C$31 -> 0 | E32: =E22*Assumptions!$C$31 -> 3102.2723 | F32: =F22*Assumptions!$C$31 -> 3104.405 | G32: =G22*Assumptions!$C$31 -> 3106.5591 | H32: =H22*Assumptions!$C$31 -> 9398.7347 | I32: =I22*Assumptions!$C$31 -> 9400.932 | ... Y32: =Y22*Assumptions!$C$31 -> 2461.6782
A33: Standard + renewal annual bookings | B33: =B23*Assumptions!$C$30+B25*Assumptions!$C$30 -> 0 | C33: =C23*Assumptions!$C$30+C25*Assumptions!$C$30 -> 0 | D33: =D23*Assumptions!$C$30+D25*Assumptions!$C$30 -> 0 | E33: =E23*Assumptions!$C$30+E25*Assumptions!$C$30 -> 1335 | F33: =F23*Assumptions!$C$30+F25*Assumptions!$C$30 -> 1335 | G33: =G23*Assumptions!$C$30+G25*Assumptions!$C$30 -> 1335 | H33: =H23*Assumptions!$C$30+H25*Assumptions!$C$30 -> 2701.7857 | I33: =I23*Assumptions!$C$30+I25*Assumptions!$C$30 -> 2701.7857 | ... Y33: =Y23*Assumptions!$C$30+Y25*Assumptions!$C$30 -> 12515.633
A34: Total AI revenue | B34: =SUM(B31:B33) -> 0 | C34: =SUM(C31:C33) -> 0 | D34: =SUM(D31:D33) -> 0 | E34: =SUM(E31:E33) -> 5696.4421 | F34: =SUM(F31:F33) -> 6882.8436 | G34: =SUM(G31:G33) -> 7998.8658 | H34: =SUM(H31:H33) -> 18942.373 | I34: =SUM(I31:I33) -> 22032.713 | ... Y34: =SUM(Y31:Y33) -> 42522.372
A35: Monthly contribution | B35: =B28*Assumptions!$C$37 -> 0 | C35: =C28*Assumptions!$C$37 -> 0 | D35: =D28*Assumptions!$C$37 -> 0 | E35: =E28*Assumptions!$C$37 -> 702.40576 | F35: =F28*Assumptions!$C$37 -> 1363.0293 | G35: =G28*Assumptions!$C$37 -> 1984.381 | H35: =H28*Assumptions!$C$37 -> 3816.6073 | I35: =I28*Assumptions!$C$37 -> 5539.2731 | ... Y35: =Y28*Assumptions!$C$37 -> 15365.528
A36: Founding annual contribution | B36: =B22*Assumptions!$C$39 -> 0 | C36: =C22*Assumptions!$C$39 -> 0 | D36: =D22*Assumptions!$C$39 -> 0 | E36: =E22*Assumptions!$C$39 -> 1410.7268 | F36: =F22*Assumptions!$C$39 -> 1411.6967 | G36: =G22*Assumptions!$C$39 -> 1412.6762 | H36: =H22*Assumptions!$C$39 -> 4273.9791 | I36: =I22*Assumptions!$C$39 -> 4274.9784 | ... Y36: =Y22*Assumptions!$C$39 -> 1119.4232
A37: Standard + renewal contribution | B37: =SUM(B23,B25)*Assumptions!$C$38 -> 0 | C37: =SUM(C23,C25)*Assumptions!$C$38 -> 0 | D37: =SUM(D23,D25)*Assumptions!$C$38 -> 0 | E37: =SUM(E23,E25)*Assumptions!$C$38 -> 672.29508 | F37: =SUM(F23,F25)*Assumptions!$C$38 -> 672.29508 | G37: =SUM(G23,G25)*Assumptions!$C$38 -> 672.29508 | H37: =SUM(H23,H25)*Assumptions!$C$38 -> 1360.5972 | I37: =SUM(I23,I25)*Assumptions!$C$38 -> 1360.5972 | ... Y37: =SUM(Y23,Y25)*Assumptions!$C$38 -> 6302.7705
A38: AI contribution before acquisition | B38: =SUM(B35:B37) -> 0 | C38: =SUM(C35:C37) -> 0 | D38: =SUM(D35:D37) -> 0 | E38: =SUM(E35:E37) -> 2785.4277 | F38: =SUM(F35:F37) -> 3447.021 | G38: =SUM(G35:G37) -> 4069.3523 | H38: =SUM(H35:H37) -> 9451.1837 | I38: =SUM(I35:I37) -> 11174.849 | ... Y38: =SUM(Y35:Y37) -> 22787.722
A39: Direct AI acquisition spend | B39: =-SUM(B16:B17) -> 0 | C39: =-SUM(C16:C17) -> 0 | D39: =-SUM(D16:D17) -> 0 | E39: =-SUM(E16:E17) -> 0 | F39: =-SUM(F16:F17) -> 0 | G39: =-SUM(G16:G17) -> 0 | H39: =-SUM(H16:H17) -> -7000 | I39: =-SUM(I16:I17) -> -7000 | ... Y39: =-SUM(Y16:Y17) -> -5000
A40: AI contribution after acquisition | B40: =SUM(B38:B39) -> 0 | C40: =SUM(C38:C39) -> 0 | D40: =SUM(D38:D39) -> 0 | E40: =SUM(E38:E39) -> 2785.4277 | F40: =SUM(F38:F39) -> 3447.021 | G40: =SUM(G38:G39) -> 4069.3523 | H40: =SUM(H38:H39) -> 2451.1837 | I40: =SUM(I38:I39) -> 4174.8486 | ... Y40: =SUM(Y38:Y39) -> 17787.722
A41: AI recurring revenue run-rate / month | B41: =B28*Assumptions!$C$29+B29*Assumptions!$C$30/12 -> 0 | C41: =C28*Assumptions!$C$29+C29*Assumptions!$C$30/12 -> 0 | D41: =D28*Assumptions!$C$29+D29*Assumptions!$C$30/12 -> 0 | E41: =E28*Assumptions!$C$29+E29*Assumptions!$C$30/12 -> 1703.8766 | F41: =F28*Assumptions!$C$29+F29*Assumptions!$C$30/12 -> 3333.0814 | G41: =G28*Assumptions!$C$29+G29*Assumptions!$C$30/12 -> 4892.1172 | H41: =H28*Assumptions!$C$29+H29*Assumptions!$C$30/12 -> 9412.0625 | I41: =I28*Assumptions!$C$29+I29*Assumptions!$C$30/12 -> 13735.84 | ... Y41: =Y28*Assumptions!$C$29+Y29*Assumptions!$C$30/12 -> 39971.69
A42: AI annualized revenue run-rate | B42: =B41*12 -> 0 | C42: =C41*12 -> 0 | D42: =D41*12 -> 0 | E42: =E41*12 -> 20446.52 | F42: =F41*12 -> 39996.977 | G42: =G41*12 -> 58705.406 | H42: =H41*12 -> 112944.75 | I42: =I41*12 -> 164830.08 | ... Y42: =Y41*12 -> 479660.28

Sheet Commercial Funnel
A1: TUPENSACI | Commercial Funnel v3.0
A2: La prova gratuita è un'esperienza guidata di 7 giorni senza carta. Non è un prodotto free permanente e non sostituisce il CAC: il CAC resta misurato sul cliente pagante.
A4: OFFER ARCHITECTURE
A5: Element | B5: Value | C5: Unit | D5: Who receives it | E5: Renewal / exit | F5: Why | G5: Status | H5: Model link
A6: Monthly plan | B6: =Assumptions!$C$29 -> 9 | C6: €/month | D6: All paid users | E6: Monthly | F6: Low-friction entry | G6: Confirmed | H6: AI Cohorts
A7: Annual standard | B7: =Assumptions!$C$30 -> 89 | C7: €/year | D7: Broad / standard users | E7: Renews at €89 | F7: Upfront cash and retention | G7: Confirmed | H7: AI Cohorts
A8: Annual founding | B8: =Assumptions!$C$31 -> 69 | C8: €/first year | D8: Community, clients, workbook-linked | E8: Renews at €89 | F8: Launch incentive without lowering list price | G8: Confirmed | H8: AI Cohorts
A9: Guided trial | B9: =Assumptions!$C$84 -> 7 | C9: days | D9: New prospects | E9: Pay or stop | F9: Experience the product before payment | G9: Confirmed | H9: Operational funnel
A10: Payment card | B10: No | C10: — | D10: Trial users | E10: Checkout after trial | F10: Reduces trial friction | G10: Confirmed | H10: Product rule
A11: Permanent free tier | B11: No | C11: — | D11: — | E11: — | F11: Protects product value and cost control | G11: Confirmed | H11: Product rule
A12: Inactive data retention | B12: =Assumptions!$C$94 -> 30 | C12: days | D12: Expired trial/account | E12: Delete per policy | F12: Clear user control | G12: To formalize | H12: Privacy rule
A15: TRIAL FUNNEL — ACCELERATED CASE
A16: Audience | B16: Media | C16: Paid CAC | D16: Paid users | E16: Trial-to-paid | F16: Implied trials | G16: Implied cost / trial | H16: Interpretation
A17: Warm/community M7–M12 | B17: =Assumptions!$C$85 -> 25000 | C17: =Assumptions!$C$89 -> 15 | D17: =B17/C17 -> 1666.6667 | E17: =Assumptions!$C$92 -> 0.35 | F17: =D17/E17 -> 4761.9048 | G17: =B17/F17 -> 5.25 | H17: Existing relationship should improve conversion
A18: Broad M7–M12 | B18: =Assumptions!$C$86 -> 17000 | C18: =Assumptions!$C$90 -> 28 | D18: =B18/C18 -> 607.14286 | E18: =Assumptions!$C$93 -> 0.25 | F18: =D18/E18 -> 2428.5714 | G18: =B18/F18 -> 7 | H18: Broad starts cautiously; do not assume immediate optimization
A19: Broad M13–M18 | B19: =Assumptions!$C$87 -> 28000 | C19: =Assumptions!$C$90 -> 28 | D19: =B19/C19 -> 1000 | E19: =Assumptions!$C$93 -> 0.25 | F19: =D19/E19 -> 4000 | G19: =B19/F19 -> 7 | H19: Released only after retention and safety evidence
A20: TOTAL / blended | B20: =SUM(B17:B19) -> 70000 | C20: =B20/SUM(D17:D19) -> 21.381818 | D20: =SUM(D17:D19) -> 3273.8095 | E20: =SUM(D17:D19)/SUM(F17:F19) -> 0.29255319 | F20: =SUM(F17:F19) -> 11190.476 | G20: =B20/F20 -> 6.2553191 | H20: €70k accelerated envelope across the first 12 paid months
A23: MEASUREMENT RULE
A24: Il trial-to-paid è un KPI di prodotto e funnel. Il CAC del modello è già espresso per cliente pagante: non va moltiplicato una seconda volta per il tasso di conversione. Il test sarà superato soltanto se le persone pagano, tornano dopo il primo uso e restano a 30, 60 e 90 giorni.

Sheet Checks & Sources
A1: TUPENSACI | Checks & Sources v3.0
A2: Model integrity, scenario gates and source lineage. All checks should read OK before external use.
A4: MODEL CHECKS
A5: Check | B5: Value | C5: Status | D5: Purpose
A6: P&L revenue tie | B6: =SUM('P&L 36 Months'!B12:AK12)-SUM('Physical Business'!B18:AK18)-SUM('Growth Extensions'!B11:AK11)-SUM('Growth Extensions'!B15:AK15)-SUM('AI Cohorts'!B32:AK32) -> 0 | C6: =IF(ABS(B6)<0.01,"OK","ERROR") -> OK | D6: Physical + AI equals total revenue
A7: Cash roll-forward tie | B7: =SUM('Cash & Funding'!B12:AK12)-SUM('Cash & Funding'!B10:AK10)-SUM('Cash & Funding'!B11:AK11) -> 0 | C7: =IF(ABS(B7)<0.01,"OK","ERROR") -> OK | D7: Opening + net flow equals closing
A8: AI mix tie | B8: =SUM('AI Cohorts'!B15:AK15)-SUM('AI Cohorts'!B17:AK19) -> 0 | C8: =IF(ABS(B8)<0.01,"OK","ERROR") -> OK | D8: Annual + monthly cohorts equal new users
A9: Physical orders non-negative | B9: =MIN('Physical Business'!B14:AK14) -> 621.73913 | C9: =IF(B9>=0,"OK","ERROR") -> OK | D9: No negative volume
A10: AI active users non-negative | B10: =MIN('AI Cohorts'!B26:AK26) -> 0 | C10: =IF(B10>=0,"OK","ERROR") -> OK | D10: No negative active cohort
A11: Selected scenario valid | B11: =IF(OR(Assumptions!B5="Downside",Assumptions!B5="Base",Assumptions!B5="Upside"),1,0) -> 1 | C11: =IF(B11=1,"OK","ERROR") -> OK | D11: Control cell is one of three scenarios
A12: Founder compensation visible | B12: =Assumptions!C46 -> 0 | C12: =IF(B12>=0,"OK","ERROR") -> OK | D12: No hidden founder cost assumption
A13: Lean team blueprint tie | B13: =SUM('Team Blueprint'!E6:E13)+'Team & Opex'!T13 -> 0 | C13: =IF(ABS(B13)<0.01,"OK","ERROR") -> OK | D13: M19 recurring opex equals the detailed team blueprint
A14: AI branch valid | B14: =IF(OR(Assumptions!E5="Test",Assumptions!E5="Scale"),1,0) -> 1 | C14: =IF(B14=1,"OK","ERROR") -> OK | D14: Test or Scale only
A15: Growth extension control valid | B15: =IF(OR(Assumptions!E6="On",Assumptions!E6="Off"),1,0) -> 1 | C15: =IF(B15=1,"OK","ERROR") -> OK | D15: On or Off only
A16: Current branch unit economics | B16: =Assumptions!C70 -> 2.8016137 | C16: =IF(IF(Assumptions!E5="Scale",B16>=3,B16>=2),"OK","REVIEW") -> OK | D16: Test ≥2x; Scale ≥3x
A17: Use of proceeds total | B17: =SUM('Use of Proceeds'!B6:B12)-Assumptions!C47 -> 0 | C17: =IF(ABS(B17)<0.01,"OK","ERROR") -> OK | D17: Allocation equals €300k round
A18: Pricing contribution positive | B18: =MIN(Assumptions!C37:C39) -> 5.0204918 | C18: =IF(B18>0,"OK","ERROR") -> OK | D18: All three offers contribute after delivery costs
A19: Accelerated M12 target | B19: ='Accelerated Case'!M30 -> 3261.8358 | C19: =IF(AND(B19>=3000,B19<=3500),"OK","REVIEW") -> OK | D19: Gated target range 3,000–3,500
A20: Accelerated M24 ceiling | B20: ='Accelerated Case'!Y30 -> 4736.0629 | C20: =IF(AND(B20>=4500,B20<=5500),"OK","REVIEW") -> OK | D20: Around 5,000, not unconstrained scale
A21: Capital operating authorization | B21: =SUM('Capital Gates'!C5:C7) -> 285000 | C21: =IF(B21=285000,"OK","ERROR") -> OK | D21: €285k released by gates; €15k reserve held
A23: SOURCE REGISTER
A24: Source | B24: Type | C24: Location | D24: Used for | E24: Period | F24: Owner | G24: Confidence | H24: Notes
A25: ANALISI ORDINI TP (1).xlsx | B25: Internal actuals | C25: Workspace root | D25: Revenue, ADV, fulfillment, historical trends | E25: 2023–17 Jun 2026 | F25: TUPENSACI | G25: High | H25: Primary financial actuals
A26: TUPENSACI AI - Modello economico riconciliato v1.0.xlsx | B26: Internal model | C26: output/financial-model | D26: AI unit economics, churn/CAC, cost structure | E26: Current | F26: TUPENSACI | G26: Medium | H26: Assumptions require market validation
A27: Business Plan Tupensaci AI (3).xlsx | B27: Legacy model | C27: Workspace root | D27: Prior operating cost architecture | E27: Legacy | F27: TUPENSACI | G27: Medium | H27: Used only after reconciliation
A28: Management working session | B28: Confirmed inputs | C28: This task | D28: Pricing €9/€89/€69, 7-day trial, acceleration gates and round allocation | E28: Aug 2026 | F28: Founders | G28: High | H28: Commercial inputs confirmed in conversation
A29: Extendi preliminary MVP indication | B29: Vendor pre-quote | C29: Management correspondence / technical package | D29: Core web-app MVP indication below €30k; not a signed quote | E29: Jul 2026 | F29: Extendi | G29: Low / preliminary | H29: v3 keeps a €75k product envelope including work beyond core coding
A30: Team & Agency Blueprint v3.0 | B30: Operating design | C30: Team Blueprint sheet | D30: Team, agency and accountable growth architecture | E30: 36-month plan | F30: TUPENSACI | G30: Medium | H30: Management-approved planning structure; agency quote pending
A31: Competitive Evidence Pack — TUPENSACI.pdf | B31: Independent desk research | C31: Workspace root | D31: Competitive landscape and positioning | E31: Jul 2026 | F31: External research | G31: Medium | H31: Supports differentiation thesis; does not prove demand or TAM
A32: Capital Gates v3.0 | B32: Capital authorization plan | C32: Capital Gates sheet | D32: €90k / €80k / €115k operating tranches + €15k reserve | E32: 12-month proof plan | F32: TUPENSACI | G32: Medium | H32: Board authorization model; thresholds must be replaced with observed results
